Workbook
Name CUBE: Parameters!$B$1
Name East_List: Lists!$C$1:$C$10
Name ENTITY: Parameters!$B$2
Name MEASURE: Parameters!$B$3
Name Month: Parameters!$B$9
Name MONTH_CURRENT: Parameters!$C$9
Name MONTH_CURRENT_YTD: Parameters!$C$10
Name MONTH_LY: Parameters!$D$9
Name MONTH_LY_YTD: Parameters!$D$10
Name North_List: Lists!$E$1:$E$6
Name South_List: Lists!$G$1:$G$9
Name West_List: Lists!$I$1:$I$9
Name YEAR: Parameters!$B$10

Sheet Cognos_Office_Connection_Cache

Sheet Parameters
A1: CUBE: | B1: Coates:General Ledger | J1: CY | K1: PY
A2: Financial Entity | B2: All Financial Entities | I2: Jul | J2: 2026-07 | K2: 2025-07
A3: Plan Measure | B3: Total | I3: Aug | J3: 2026-08 | K3: 2025-08
I4: Sep | J4: 2026-09 | K4: 2025-09
A5: Actual | B5: Actual | I5: Oct | J5: 2026-10 | K5: 2025-10
A6: Budget | B6: Target Budget | I6: Nov | J6: 2026-11 | K6: 2025-11
A7: Forecast | B7: Forecast Current | I7: Dec | J7: 2026-12 | K7: 2025-12
I8: Jan | J8: 2027-01 | K8: 2026-01
A9: Month | B9: Jul | C9: =+_xlfn.XLOOKUP($B9,$I$1:$I$13,J1:J13) -> 2026-07 | D9: =+_xlfn.XLOOKUP($B9,$I$1:$I$13,K1:K13) -> 2025-07 | I9: Feb | J9: 2027-02 | K9: 2026-02
B10: 2026 | C10: =+CONCATENATE(MONTH_CURRENT&"-YTD") -> 2026-07-YTD | D10: =+CONCATENATE(MONTH_LY&"-YTD") -> 2025-07-YTD | I10: Mar | J10: 2027-03 | K10: 2026-03
I11: Apr | J11: 2027-04 | K11: 2026-04
I12: May | J12: 2027-05 | K12: 2026-05
I13: Jun | J13: 2027-06 | K13: 2026-06

Sheet Lists
A1: IS | C1: IS_EAST BU | E1: IS_NORTH BU | G1: IS_SOUTH BU | I1: IS_WEST BU
C2: EAIS | E2: NOIS | G2: STIS | I2: WAIS
C3: THOR | E3: PHOS | G3: ROXD | I3: BAWI
C4: ISNS | E4: GLST | I4: MURR
I5: ONSL

Sheet Summary P&L>>

Sheet Group
A1: CUBE: | C1: Coates:General Ledger
A2: Financial Entity | C2: All Financial Entities
A3: Plan Measure | C3: Total
D4: =+Parameters!$B$10 -> 2026 | E4: =+Parameters!$B$10 -> 2026 | G4: =+Parameters!$B$10 -> 2026 | I4: =+D4-1 -> 2025 | L4: =+D4 -> 2026 | M4: =+E4 -> 2026 | O4: =+G4 -> 2026 | Q4: =+I4 -> 2025
D5: =+Parameters!$B$9 -> Jul | E5: =+Parameters!$B$9 -> Jul | G5: =+Parameters!$B$9 -> Jul | I5: =+E5 -> Jul | L5: =CONCATENATE(D5," ","YTD") -> Jul YTD | M5: =CONCATENATE(E5," ","YTD") -> Jul YTD | O5: =CONCATENATE(G5," ","YTD") -> Jul YTD | Q5: =CONCATENATE(I5," ","YTD") -> Jul YTD
D6: =+Parameters!B5 -> Actual | E6: =+Parameters!$B$6 -> Target Budget | G6: =+Parameters!$B$7 -> Forecast Current | I6: =+D6 -> Actual | L6: =+D6 -> Actual | M6: =+E6 -> Target Budget | O6: =+G6 -> Forecast Current | Q6: =+I6 -> Actual
D7: =+Lists!A1 -> IS | E7: =+D7 -> IS | F7: =+E7 -> IS | G7: =+F7 -> IS | H7: =+G7 -> IS | I7: =+H7 -> IS | J7: =+I7 -> IS | K7: =+J7 -> IS | L7: =+K7 -> IS | ... R7: =+Q7 -> IS
C8: FINANCIAL YEAR 2027 | D8: Industrial Solutions
D10: =CONCATENATE($D$5," ","MTD") -> Jul MTD | L10: =CONCATENATE($D$5," ","YTD") -> Jul YTD
D11: Actual | E11: Budget | F11: Var Bud | G11: Forecast | H11: Var Forecast | I11: Last Year | J11: Var LY | L11: Actual | M11: Budget | N11: Var Bud | O11: Forecast | P11: Var Forecast | Q11: Last Year | R11: Var LY
A12: Hire Revenue | B12: -1 | C12: Hire Revenue | D12: 3120323.8 | E12: 3399847.6 | F12: =+D12-E12 -> -279523.78 | G12: 0 | H12: =+D12-G12 -> 3120323.8 | I12: 2968368.8 | J12: =+D12-I12 -> 151955.04 | L12: 3120323.8 | M12: 3399847.6 | N12: =+L12-M12 -> -279523.78 | O12: 0 | P12: =+L12-O12 -> 3120323.8 | Q12: 2968368.8 | R12: =+L12-Q12 -> 151955.04 | T12: =D12/E12-1 -> -0.082216561 | U12: =+D12/I12-1 -> 0.051191429 | W12: =L12/M12-1 -> -0.082216561 | X12: =+L12/Q12-1 -> 0.051191429
A13: Rehire Revenue | B13: -1 | C13: Rehire Revenue | D13: 1121356.1 | E13: 623122.95 | F13: =+D13-E13 -> 498233.17 | G13: 0 | H13: =+D13-G13 -> 1121356.1 | I13: 462803.51 | J13: =+D13-I13 -> 658552.61 | L13: 1121356.1 | M13: 623122.95 | N13: =+L13-M13 -> 498233.17 | O13: 0 | P13: =+L13-O13 -> 1121356.1 | Q13: 462803.51 | R13: =+L13-Q13 -> 658552.61 | T13: =D13/E13-1 -> 0.79957441 | U13: =+D13/I13-1 -> 1.4229637 | W13: =L13/M13-1 -> 0.79957441 | X13: =+L13/Q13-1 -> 1.4229637
A14: Transport | B14: -1 | C14: Transport Revenue | D14: 443313.52 | E14: 313906.81 | F14: =+D14-E14 -> 129406.71 | G14: 0 | H14: =+D14-G14 -> 443313.52 | I14: 220060.08 | J14: =+D14-I14 -> 223253.44 | L14: 443313.52 | M14: 313906.81 | N14: =+L14-M14 -> 129406.71 | O14: 0 | P14: =+L14-O14 -> 443313.52 | Q14: 220060.08 | R14: =+L14-Q14 -> 223253.44 | T14: =D14/E14-1 -> 0.41224564 | U14: =+D14/I14-1 -> 1.0145113 | W14: =L14/M14-1 -> 0.41224564 | X14: =+L14/Q14-1 -> 1.0145113
A15: Other Revenue. | B15: -1 | C15: Other Revenue | D15: 1006392.8 | E15: 1320339.2 | F15: =+D15-E15 -> -313946.4 | G15: 0 | H15: =+D15-G15 -> 1006392.8 | I15: 791985.29 | J15: =+D15-I15 -> 214407.49 | L15: 1006392.8 | M15: 1320339.2 | N15: =+L15-M15 -> -313946.4 | O15: 0 | P15: =+L15-O15 -> 1006392.8 | Q15: 791985.29 | R15: =+L15-Q15 -> 214407.49 | T15: =D15/E15-1 -> -0.23777708 | U15: =+D15/I15-1 -> 0.27072156 | W15: =L15/M15-1 -> -0.23777708 | X15: =+L15/Q15-1 -> 0.27072156
A16: Total Combined Revenue | B16: -1 | C16: Total Revenue | D16: 5691386.2 | E16: 5657216.5 | F16: =+D16-E16 -> 34169.709 | G16: 0 | H16: =+D16-G16 -> 5691386.2 | I16: 4443217.6 | J16: =+D16-I16 -> 1248168.6 | L16: 5691386.2 | M16: 5657216.5 | N16: =+L16-M16 -> 34169.709 | O16: 0 | P16: =+L16-O16 -> 5691386.2 | Q16: 4443217.6 | R16: =+L16-Q16 -> 1248168.6 | T16: =D16/E16-1 -> 0.0060400215 | U16: =+D16/I16-1 -> 0.28091547 | W16: =L16/M16-1 -> 0.0060400215 | X16: =+L16/Q16-1 -> 0.28091547
A17: Total Repairs & Maintenance | B17: 1 | C17: Total Repairs & Maint | D17: 833490.17 | E17: 654170.76 | F17: =+D17-E17 -> 179319.41 | G17: 0 | H17: =+D17-G17 -> 833490.17 | I17: 588110.85 | J17: =+D17-I17 -> 245379.32 | L17: 833490.17 | M17: 654170.76 | N17: =+L17-M17 -> 179319.41 | O17: 0 | P17: =+L17-O17 -> 833490.17 | Q17: 588110.85 | R17: =+L17-Q17 -> 245379.32 | T17: =D17/E17-1 -> 0.27411713 | U17: =+D17/I17-1 -> 0.41723311 | W17: =L17/M17-1 -> 0.27411713 | X17: =+L17/Q17-1 -> 0.41723311
A18: Transport Expenses (Stat) | B18: 1 | C18: Transport | D18: 418026.62 | E18: 274176.39 | F18: =+D18-E18 -> 143850.23 | G18: 0 | H18: =+D18-G18 -> 418026.62 | I18: 258588.78 | J18: =+D18-I18 -> 159437.84 | L18: 418026.62 | M18: 274176.39 | N18: =+L18-M18 -> 143850.23 | O18: 0 | P18: =+L18-O18 -> 418026.62 | Q18: 258588.78 | R18: =+L18-Q18 -> 159437.84 | T18: =D18/E18-1 -> 0.52466308 | U18: =+D18/I18-1 -> 0.61656906 | W18: =L18/M18-1 -> 0.52466308 | X18: =+L18/Q18-1 -> 0.61656906
A19: Rehire Expenses | B19: 1 | C19: Rehire | D19: 895682.45 | E19: 530001.7 | F19: =+D19-E19 -> 365680.75 | G19: 0 | H19: =+D19-G19 -> 895682.45 | I19: 418146.33 | J19: =+D19-I19 -> 477536.12 | L19: 895682.45 | M19: 530001.7 | N19: =+L19-M19 -> 365680.75 | O19: 0 | P19: =+L19-O19 -> 895682.45 | Q19: 418146.33 | R19: =+L19-Q19 -> 477536.12 | T19: =D19/E19-1 -> 0.68996148 | U19: =+D19/I19-1 -> 1.1420311 | W19: =L19/M19-1 -> 0.68996148 | X19: =+L19/Q19-1 -> 1.1420311
A20: Profit/Loss on Sale of Asset | B20: 1 | C20: POSA | D20: 0 | E20: 0 | F20: =+D20-E20 -> 0 | G20: 0 | H20: =+D20-G20 -> 0 | I20: 0 | J20: =+D20-I20 -> 0 | L20: 0 | M20: 0 | N20: =+L20-M20 -> 0 | O20: 0 | P20: =+L20-O20 -> 0 | Q20: 0 | R20: =+L20-Q20 -> 0
A21: Other Direct Costs | B21: 1 | C21: Other Direct Costs | D21: 837430.39 | E21: 1106545.2 | F21: =+D21-E21 -> -269114.8 | G21: 0 | H21: =+D21-G21 -> 837430.39 | I21: 682634.77 | J21: =+D21-I21 -> 154795.62 | L21: 837430.39 | M21: 1106545.2 | N21: =+L21-M21 -> -269114.8 | O21: 0 | P21: =+L21-O21 -> 837430.39 | Q21: 682634.77 | R21: =+L21-Q21 -> 154795.62 | T21: =D21/E21-1 -> -0.24320272 | U21: =+D21/I21-1 -> 0.22676199 | W21: =L21/M21-1 -> -0.24320272 | X21: =+L21/Q21-1 -> 0.22676199
A22: Total Combined Direct Costs (Stat) | B22: 1 | C22: Total Direct Costs | D22: 2984629.6 | E22: 2564894 | F22: =+D22-E22 -> 419735.6 | G22: 0 | H22: =+D22-G22 -> 2984629.6 | I22: 1947480.7 | J22: =+D22-I22 -> 1037148.9 | L22: 2984629.6 | M22: 2564894 | N22: =+L22-M22 -> 419735.6 | O22: 0 | P22: =+L22-O22 -> 2984629.6 | Q22: 1947480.7 | R22: =+L22-Q22 -> 1037148.9 | T22: =D22/E22-1 -> 0.16364637 | U22: =+D22/I22-1 -> 0.53255926 | W22: =L22/M22-1 -> 0.16364637 | X22: =+L22/Q22-1 -> 0.53255926
A23: Gross Margin - Post Allocations (Stat) | B23: -1 | C23: Gross Margin | D23: 2706756.6 | E23: 3092322.5 | F23: =+D23-E23 -> -385565.89 | G23: 0 | H23: =+D23-G23 -> 2706756.6 | I23: 2495736.9 | J23: =+D23-I23 -> 211019.68 | L23: 2706756.6 | M23: 3092322.5 | N23: =+L23-M23 -> -385565.89 | O23: 0 | P23: =+L23-O23 -> 2706756.6 | Q23: 2495736.9 | R23: =+L23-Q23 -> 211019.68 | T23: =D23/E23-1 -> -0.12468489 | U23: =+D23/I23-1 -> 0.084552053 | W23: =L23/M23-1 -> -0.12468489 | X23: =+L23/Q23-1 -> 0.084552053
A24: Property (Stat) | B24: 1 | C24: Property | D24: 163404.8 | E24: 154645.62 | F24: =+D24-E24 -> 8759.1777 | G24: 0 | H24: =+D24-G24 -> 163404.8 | I24: 143745.34 | J24: =+D24-I24 -> 19659.46 | L24: 163404.8 | M24: 154645.62 | N24: =+L24-M24 -> 8759.1777 | O24: 0 | P24: =+L24-O24 -> 163404.8 | Q24: 143745.34 | R24: =+L24-Q24 -> 19659.46 | T24: =D24/E24-1 -> 0.056640321 | U24: =+D24/I24-1 -> 0.13676589 | W24: =L24/M24-1 -> 0.056640321 | X24: =+L24/Q24-1 -> 0.13676589
A25: Direct Staff Costs (Stat) | B25: 1 | C25: Direct Staff | D25: 321844.25 | E25: 378225.84 | F25: =+D25-E25 -> -56381.587 | G25: 0 | H25: =+D25-G25 -> 321844.25 | I25: 448435.18 | J25: =+D25-I25 -> -126590.93 | L25: 321844.25 | M25: 378225.84 | N25: =+L25-M25 -> -56381.587 | O25: 0 | P25: =+L25-O25 -> 321844.25 | Q25: 448435.18 | R25: =+L25-Q25 -> -126590.93 | T25: =D25/E25-1 -> -0.14906858 | U25: =+D25/I25-1 -> -0.28229482 | W25: =L25/M25-1 -> -0.14906858 | X25: =+L25/Q25-1 -> -0.28229482
A26: Indirect Staff Costs | B26: 1 | C26: Indirect Staff | D26: 13786.49 | E26: 14480.228 | F26: =+D26-E26 -> -693.73766 | G26: 0 | H26: =+D26-G26 -> 13786.49 | I26: 20678.24 | J26: =+D26-I26 -> -6891.75 | L26: 13786.49 | M26: 14480.228 | N26: =+L26-M26 -> -693.73766 | O26: 0 | P26: =+L26-O26 -> 13786.49 | Q26: 20678.24 | R26: =+L26-Q26 -> -6891.75 | T26: =D26/E26-1 -> -0.047909306 | U26: =+D26/I26-1 -> -0.33328513 | W26: =L26/M26-1 -> -0.047909306 | X26: =+L26/Q26-1 -> -0.33328513
A27: Marketing and Entertainment (BUFR) | B27: 1 | C27: Marketing/Entertainment | D27: 373.95 | E27: 432.30089 | F27: =+D27-E27 -> -58.35089 | G27: 0 | H27: =+D27-G27 -> 373.95 | I27: 15.68 | J27: =+D27-I27 -> 358.27 | L27: 373.95 | M27: 432.30089 | N27: =+L27-M27 -> -58.35089 | O27: 0 | P27: =+L27-O27 -> 373.95 | Q27: 15.68 | R27: =+L27-Q27 -> 358.27
A28: Telecommunications | B28: 1 | C28: Telecommunications | D28: 7791.84 | E28: 8308.4086 | F28: =+D28-E28 -> -516.56859 | G28: 0 | H28: =+D28-G28 -> 7791.84 | I28: 8969.2 | J28: =+D28-I28 -> -1177.36 | L28: 7791.84 | M28: 8308.4086 | N28: =+L28-M28 -> -516.56859 | O28: 0 | P28: =+L28-O28 -> 7791.84 | Q28: 8969.2 | R28: =+L28-Q28 -> -1177.36 | T28: =D28/E28-1 -> -0.062174192 | U28: =+D28/I28-1 -> -0.131267 | W28: =L28/M28-1 -> -0.062174192 | X28: =+L28/Q28-1 -> -0.131267
A29: IT & EDP Expenses | B29: 1 | C29: IT&EDP | D29: 9783.79 | E29: 4615.7283 | F29: =+D29-E29 -> 5168.0617 | G29: 0 | H29: =+D29-G29 -> 9783.79 | I29: 2663.06 | J29: =+D29-I29 -> 7120.73 | L29: 9783.79 | M29: 4615.7283 | N29: =+L29-M29 -> 5168.0617 | O29: 0 | P29: =+L29-O29 -> 9783.79 | Q29: 2663.06 | R29: =+L29-Q29 -> 7120.73 | T29: =D29/E29-1 -> 1.1196633 | U29: =+D29/I29-1 -> 2.6738902 | W29: =L29/M29-1 -> 1.1196633 | X29: =+L29/Q29-1 -> 2.6738902
A30: Travel & Accomodation Expense | B30: 1 | C30: Travel & Accommodation | D30: 22276.94 | E30: 13131.251 | F30: =+D30-E30 -> 9145.6889 | G30: 0 | H30: =+D30-G30 -> 22276.94 | I30: 18769.05 | J30: =+D30-I30 -> 3507.89 | L30: 22276.94 | M30: 13131.251 | N30: =+L30-M30 -> 9145.6889 | O30: 0 | P30: =+L30-O30 -> 22276.94 | Q30: 18769.05 | R30: =+L30-Q30 -> 3507.89 | T30: =D30/E30-1 -> 0.69648268 | U30: =+D30/I30-1 -> 0.18689758 | W30: =L30/M30-1 -> 0.69648268 | X30: =+L30/Q30-1 -> 0.18689758
A31: Bad Debts | B31: 1 | C31: Bad Debts | D31: 9930.72 | E31: 9490.7509 | F31: =+D31-E31 -> 439.96907 | G31: 0 | H31: =+D31-G31 -> 9930.72 | I31: 7642.54 | J31: =+D31-I31 -> 2288.18 | L31: 9930.72 | M31: 9490.7509 | N31: =+L31-M31 -> 439.96907 | O31: 0 | P31: =+L31-O31 -> 9930.72 | Q31: 7642.54 | R31: =+L31-Q31 -> 2288.18 | T31: =D31/E31-1 -> 0.046357667 | U31: =+D31/I31-1 -> 0.29940046 | W31: =L31/M31-1 -> 0.046357667 | X31: =+L31/Q31-1 -> 0.29940046
A32: Branch Admin (Stat) | B32: 1 | C32: Total Branch Administration | D32: 25778.56 | E32: 24575.884 | F32: =+D32-E32 -> 1202.6757 | G32: 0 | H32: =+D32-G32 -> 25778.56 | I32: 40999.6 | J32: =+D32-I32 -> -15221.04 | L32: 25778.56 | M32: 24575.884 | N32: =+L32-M32 -> 1202.6757 | O32: 0 | P32: =+L32-O32 -> 25778.56 | Q32: 40999.6 | R32: =+L32-Q32 -> -15221.04 | T32: =D32/E32-1 -> 0.048937231 | U32: =+D32/I32-1 -> -0.3712485 | W32: =L32/M32-1 -> 0.048937231 | X32: =+L32/Q32-1 -> -0.3712485
A33: Statutory Cost | B33: 1 | C33: Statutory | D33: 5470.64 | E33: 5474.1733 | F33: =+D33-E33 -> -3.5332598 | G33: 0 | H33: =+D33-G33 -> 5470.64 | I33: 5321.53 | J33: =+D33-I33 -> 149.11 | L33: 5470.64 | M33: 5474.1733 | N33: =+L33-M33 -> -3.5332598 | O33: 0 | P33: =+L33-O33 -> 5470.64 | Q33: 5321.53 | R33: =+L33-Q33 -> 149.11 | T33: =D33/E33-1 -> -0.00064544171 | U33: =+D33/I33-1 -> 0.028020137 | W33: =L33/M33-1 -> -0.00064544171 | X33: =+L33/Q33-1 -> 0.028020137
A34: Shared services & Allocated Costs | B34: 1 | C34: Shared services & Allocated Costs | D34: 726668.08 | E34: 711838.57 | F34: =+D34-E34 -> 14829.507 | G34: 0 | H34: =+D34-G34 -> 726668.08 | I34: 679637.45 | J34: =+D34-I34 -> 47030.63 | L34: 726668.08 | M34: 711838.57 | N34: =+L34-M34 -> 14829.507 | O34: 0 | P34: =+L34-O34 -> 726668.08 | Q34: 679637.45 | R34: =+L34-Q34 -> 47030.63 | T34: =D34/E34-1 -> 0.020832683 | U34: =+D34/I34-1 -> 0.069199586 | W34: =L34/M34-1 -> 0.020832683 | X34: =+L34/Q34-1 -> 0.069199586
A35: Total Combined Overheads (Stat) | B35: 1 | C35: Total Overheads | D35: 1307110.1 | E35: 1325218.8 | F35: =+D35-E35 -> -18108.698 | G35: 0 | H35: =+D35-G35 -> 1307110.1 | I35: 1376876.9 | J35: =+D35-I35 -> -69766.81 | L35: 1307110.1 | M35: 1325218.8 | N35: =+L35-M35 -> -18108.698 | O35: 0 | P35: =+L35-O35 -> 1307110.1 | Q35: 1376876.9 | R35: =+L35-Q35 -> -69766.81 | T35: =D35/E35-1 -> -0.013664686 | U35: =+D35/I35-1 -> -0.050670333 | W35: =L35/M35-1 -> -0.013664686 | X35: =+L35/Q35-1 -> -0.050670333
A36: EBITDA - Post Allocations (Stat) | B36: -1 | C36: EBITDA | D36: 1399646.5 | E36: 1767103.7 | F36: =+D36-E36 -> -367457.19 | G36: 0 | H36: =+D36-G36 -> 1399646.5 | I36: 1118860 | J36: =+D36-I36 -> 280786.49 | L36: 1399646.5 | M36: 1767103.7 | N36: =+L36-M36 -> -367457.19 | O36: 0 | P36: =+L36-O36 -> 1399646.5 | Q36: 1118860 | R36: =+L36-Q36 -> 280786.49 | T36: =D36/E36-1 -> -0.20794319 | U36: =+D36/I36-1 -> 0.25095765 | W36: =L36/M36-1 -> -0.20794319 | X36: =+L36/Q36-1 -> 0.25095765
A37: Total Combined Depreciation (Stat) | B37: 1 | C37: Depreciation | D37: 688818.24 | E37: 728249.92 | F37: =+D37-E37 -> -39431.678 | G37: 0 | H37: =+D37-G37 -> 688818.24 | I37: 667543.06 | J37: =+D37-I37 -> 21275.18 | L37: 688818.24 | M37: 728249.92 | N37: =+L37-M37 -> -39431.678 | O37: 0 | P37: =+L37-O37 -> 688818.24 | Q37: 667543.06 | R37: =+L37-Q37 -> 21275.18 | T37: =D37/E37-1 -> -0.054145804 | U37: =+D37/I37-1 -> 0.031870873 | W37: =L37/M37-1 -> -0.054145804 | X37: =+L37/Q37-1 -> 0.031870873
A38: EBIT - Post Allocations (Stat) | B38: -1 | C38: EBIT | D38: 710828.29 | E38: 1038853.8 | F38: =+D38-E38 -> -328025.51 | G38: 0 | H38: =+D38-G38 -> 710828.29 | I38: 451316.98 | J38: =+D38-I38 -> 259511.31 | L38: 710828.29 | M38: 1038853.8 | N38: =+L38-M38 -> -328025.51 | O38: 0 | P38: =+L38-O38 -> 710828.29 | Q38: 451316.98 | R38: =+L38-Q38 -> 259511.31 | T38: =D38/E38-1 -> -0.31575715 | U38: =+D38/I38-1 -> 0.57500897 | W38: =L38/M38-1 -> -0.31575715 | X38: =+L38/Q38-1 -> 0.57500897
P39: =+L39-O39 -> 0
B40: 1 | C40: Profit and Loss KPI Ratios | P40: =+L40-O40 -> 0
A41: Rehire Recovery % | B41: 1 | C41: Rehire Recovery | D41: 1.2519572 | E41: 1.1756999 | F41: =+D41-E41 -> 0.076257311 | G41: 0 | H41: =+D41-G41 -> 1.2519572 | I41: 1.106798 | J41: =+D41-I41 -> 0.14515926 | L41: 1.2519572 | M41: 1.1756999 | N41: =+L41-M41 -> 0.076257311 | O41: 0 | P41: =+L41-O41 -> 1.2519572 | Q41: 1.106798 | R41: =+L41-Q41 -> 0.14515926
A42: Transport Recovery % | B42: 1 | C42: Transport Recovery | D42: 1.0604911 | E42: 1.1449082 | F42: =+D42-E42 -> -0.084417107 | G42: 0 | H42: =+D42-G42 -> 1.0604911 | I42: 0.84997515 | J42: =+D42-I42 -> 0.21051597 | L42: 1.0604911 | M42: 1.1449082 | N42: =+L42-M42 -> -0.084417107 | O42: 0 | P42: =+L42-O42 -> 1.0604911 | Q42: 0.84997515 | R42: =+L42-Q42 -> 0.21051597
A43: Installation Recovery% | B43: 1 | C43: Labour Recovery - Installation | D43: 1.2489305 | E43: 1.1325518 | F43: =+D43-E43 -> 0.11637869 | G43: 0 | H43: =+D43-G43 -> 1.2489305 | I43: 1.0353336 | J43: =+D43-I43 -> 0.21359689 | L43: 1.2489305 | M43: 1.1325518 | N43: =+L43-M43 -> 0.11637869 | O43: 0 | P43: =+L43-O43 -> 1.2489305 | Q43: 1.0353336 | R43: =+L43-Q43 -> 0.21359689
A44: Consumables Recovery% | B44: 1 | C44: Consumable Recovery | D44: 1.1127976 | E44: 1.2329105 | F44: =+D44-E44 -> -0.12011289 | G44: 0 | H44: =+D44-G44 -> 1.1127976 | I44: 1.6982947 | J44: =+D44-I44 -> -0.58549708 | L44: 1.1127976 | M44: 1.2329105 | N44: =+L44-M44 -> -0.12011289 | O44: 0 | P44: =+L44-O44 -> 1.1127976 | Q44: 1.6982947 | R44: =+L44-Q44 -> -0.58549708
A45: GM % | B45: 1 | C45: Gross Margin % | D45: 0.47558828 | E45: 0.54661554 | F45: =+D45-E45 -> -0.071027262 | G45: 0 | H45: =+D45-G45 -> 0.47558828 | I45: 0.56169585 | J45: =+D45-I45 -> -0.086107569 | L45: 0.47558828 | M45: 0.54661554 | N45: =+L45-M45 -> -0.071027262 | O45: 0 | P45: =+L45-O45 -> 0.47558828 | Q45: 0.56169585 | R45: =+L45-Q45 -> -0.086107569
A46: R&M % | B46: 1 | C46: R&M / Hire Revenue | D46: 0.26622745 | E46: 0.19212026 | F46: =+D46-E46 -> 0.074107193 | G46: 0 | H46: =+D46-G46 -> 0.26622745 | I46: 0.19767544 | J46: =+D46-I46 -> 0.068552015 | L46: 0.26622745 | M46: 0.19212026 | N46: =+L46-M46 -> 0.074107193 | O46: 0 | P46: =+L46-O46 -> 0.26622745 | Q46: 0.19767544 | R46: =+L46-Q46 -> 0.068552015
A47: EBITDA % | B47: 1 | C47: EBITDA / Revenue | D47: 0.24592366 | E47: 0.31236275 | F47: =+D47-E47 -> -0.066439092 | G47: 0 | H47: =+D47-G47 -> 0.24592366 | I47: 0.25181302 | J47: =+D47-I47 -> -0.0058893571 | L47: 0.24592366 | M47: 0.31236275 | N47: =+L47-M47 -> -0.066439092 | O47: 0 | P47: =+L47-O47 -> 0.24592366 | Q47: 0.25181302 | R47: =+L47-Q47 -> -0.0058893571
A48: EBIT % | B48: 1 | C48: EBIT / Revenue | D48: 0.12489546 | E48: 0.18363338 | F48: =+D48-E48 -> -0.058737924 | G48: 0 | H48: =+D48-G48 -> 0.12489546 | I48: 0.10157436 | J48: =+D48-I48 -> 0.0233211 | L48: 0.12489546 | M48: 0.18363338 | N48: =+L48-M48 -> -0.058737924 | O48: 0 | P48: =+L48-O48 -> 0.12489546 | Q48: 0.10157436 | R48: =+L48-Q48 -> 0.0233211
B49: 1
C50: TU | D50: =+'IS Total'!E414 -> 0.67660101 | I50: =+'IS Total'!J414 -> 0.66637696 | J50: =D50-I50 -> 0.010224058 | L50: =+'IS Total'!M414 -> 0.67660101 | Q50: =+'IS Total'!R414 -> 0.66637696 | R50: =L50-Q50 -> 0.010224058
C51: ROC | D51: =+'IS Total'!E412 -> 0.10478955 | I51: =+'IS Total'!J412 -> 0.06847744 | J51: =D51-I51 -> 0.036312108 | L51: =+'IS Total'!M412 -> 0.10478955 | Q51: =+'IS Total'!R412 -> 0.06847744 | R51: =L51-Q51 -> 0.036312108
C52: Redline | D52: =+'IS Total'!E415 -> 0.18136311 | I52: =+'IS Total'!J415 -> 0.16940499 | J52: =D52-I52 -> 0.011958112 | L52: =+'IS Total'!M415 -> 0.18136311 | Q52: =+'IS Total'!R415 -> 0.16940499 | R52: =L52-Q52 -> 0.011958112
C53: Fleet Original Cost | D53: =+'IS Total'!E416 -> 82514.8 | I53: =+'IS Total'!J416 -> 77800.574 | J53: =D53-I53 -> 4714.2267 | L53: =+'IS Total'!M416 -> 82514.8 | Q53: =+'IS Total'!R416 -> 77800.574 | R53: =L53-Q53 -> 4714.2267
C58: Check v Details | D58: =D38-'IS Total'!E410 -> 0 | E58: =E38-'IS Total'!F410 -> 0 | F58: =F38-'IS Total'!G410 -> 0 | G58: =G38-'IS Total'!H410 -> 0 | H58: =H38-'IS Total'!I410 -> 0 | I58: =I38-'IS Total'!J410 -> 0 | J58: =J38-'IS Total'!K410 -> 0 | K58: =K38-'IS Total'!L410 -> 0 | ... R58: =R38-'IS Total'!S410 -> 0
C59: check to BU | D59: =+D38-East!D38-North!D38-South!D38-West!D38 -> 8.1490725e-10 | E59: =+E38-East!E38-North!E38-South!E38-West!E38 -> 1.5716068e-09 | F59: =+F38-East!F38-North!F38-South!F38-West!F38 -> -6.4028427e-10 | G59: =+G38-East!G38-North!G38-South!G38-West!G38 -> 0 | H59: =+H38-East!H38-North!H38-South!H38-West!H38 -> 8.1490725e-10 | I59: =+I38-East!I38-North!I38-South!I38-West!I38 -> -1.1059456e-09 | J59: =+J38-East!J38-North!J38-South!J38-West!J38 -> 1.9499566e-09 | K59: =+K38-East!K38-North!K38-South!K38-West!K38 -> 0 | ... R59: =+R38-East!R38-North!R38-South!R38-West!R38 -> 1.9499566e-09

Sheet East
A1: CUBE: | C1: Coates:General Ledger
A2: Financial Entity | C2: All Financial Entities
A3: Plan Measure | C3: Total
D4: =+Parameters!$B$10 -> 2026 | E4: =+Parameters!$B$10 -> 2026 | G4: =+Parameters!$B$10 -> 2026 | I4: =+D4-1 -> 2025 | L4: =+D4 -> 2026 | M4: =+E4 -> 2026 | O4: =+G4 -> 2026 | Q4: =+I4 -> 2025
D5: =+Parameters!$B$9 -> Jul | E5: =+Parameters!$B$9 -> Jul | G5: =+Parameters!$B$9 -> Jul | I5: =+E5 -> Jul | L5: =CONCATENATE(D5," ","YTD") -> Jul YTD | M5: =CONCATENATE(E5," ","YTD") -> Jul YTD | O5: =CONCATENATE(G5," ","YTD") -> Jul YTD | Q5: =CONCATENATE(I5," ","YTD") -> Jul YTD
D6: =+Parameters!B5 -> Actual | E6: =+Parameters!$B$6 -> Target Budget | G6: =+Parameters!$B$7 -> Forecast Current | I6: =+D6 -> Actual | L6: =+D6 -> Actual | M6: =+E6 -> Target Budget | O6: =+G6 -> Forecast Current | Q6: =+I6 -> Actual
D7: =+Lists!C1 -> IS_EAST BU | E7: =+D7 -> IS_EAST BU | F7: =+E7 -> IS_EAST BU | G7: =+F7 -> IS_EAST BU | H7: =+G7 -> IS_EAST BU | I7: =+H7 -> IS_EAST BU | J7: =+I7 -> IS_EAST BU | K7: =+J7 -> IS_EAST BU | L7: =+K7 -> IS_EAST BU | ... R7: =+Q7 -> IS_EAST BU
C8: =+Group!$C$8 -> FINANCIAL YEAR 2027 | D8: East - Industrial Solutions
D10: =CONCATENATE($D$5," ","MTD") -> Jul MTD | L10: =CONCATENATE($D$5," ","YTD") -> Jul YTD
D11: Actual | E11: Budget | F11: Var Bud | G11: Forecast | H11: Var Forecast | I11: Last Year | J11: Var LY | L11: Actual | M11: Budget | N11: Var Bud | O11: Forecast | P11: Var Forecast | Q11: Last Year | R11: Var LY
A12: Hire Revenue | B12: -1 | C12: Hire Revenue | D12: 295833.71 | E12: 342398.13 | F12: =+D12-E12 -> -46564.423 | G12: 0 | H12: =+D12-G12 -> 295833.71 | I12: 339897.2 | J12: =+D12-I12 -> -44063.49 | L12: 295833.71 | M12: 342398.13 | N12: =+L12-M12 -> -46564.423 | O12: 0 | P12: =+L12-O12 -> 295833.71 | Q12: 339897.2 | R12: =+L12-Q12 -> -44063.49
A13: Rehire Revenue | B13: -1 | C13: Rehire Revenue | D13: 31460.19 | E13: 58193.218 | F13: =+D13-E13 -> -26733.028 | G13: 0 | H13: =+D13-G13 -> 31460.19 | I13: 12448.17 | J13: =+D13-I13 -> 19012.02 | L13: 31460.19 | M13: 58193.218 | N13: =+L13-M13 -> -26733.028 | O13: 0 | P13: =+L13-O13 -> 31460.19 | Q13: 12448.17 | R13: =+L13-Q13 -> 19012.02
A14: Transport | B14: -1 | C14: Transport Revenue | D14: 34016.74 | E14: 50418.684 | F14: =+D14-E14 -> -16401.944 | G14: 0 | H14: =+D14-G14 -> 34016.74 | I14: 37516.46 | J14: =+D14-I14 -> -3499.72 | L14: 34016.74 | M14: 50418.684 | N14: =+L14-M14 -> -16401.944 | O14: 0 | P14: =+L14-O14 -> 34016.74 | Q14: 37516.46 | R14: =+L14-Q14 -> -3499.72
A15: Other Revenue. | B15: -1 | C15: Other Revenue | D15: 39410.3 | E15: 84577.144 | F15: =+D15-E15 -> -45166.844 | G15: 0 | H15: =+D15-G15 -> 39410.3 | I15: 53735.05 | J15: =+D15-I15 -> -14324.75 | L15: 39410.3 | M15: 84577.144 | N15: =+L15-M15 -> -45166.844 | O15: 0 | P15: =+L15-O15 -> 39410.3 | Q15: 53735.05 | R15: =+L15-Q15 -> -14324.75
A16: Total Combined Revenue | B16: -1 | C16: Total Revenue | D16: 400720.94 | E16: 535587.18 | F16: =+D16-E16 -> -134866.24 | G16: 0 | H16: =+D16-G16 -> 400720.94 | I16: 443596.88 | J16: =+D16-I16 -> -42875.94 | L16: 400720.94 | M16: 535587.18 | N16: =+L16-M16 -> -134866.24 | O16: 0 | P16: =+L16-O16 -> 400720.94 | Q16: 443596.88 | R16: =+L16-Q16 -> -42875.94 | T16: =D16/E16 -> 0.74818994
A17: Total Repairs & Maintenance | B17: 1 | C17: Total Repairs & Maint | D17: 83582.93 | E17: 62304.963 | F17: =+D17-E17 -> 21277.967 | G17: 0 | H17: =+D17-G17 -> 83582.93 | I17: 71650.28 | J17: =+D17-I17 -> 11932.65 | L17: 83582.93 | M17: 62304.963 | N17: =+L17-M17 -> 21277.967 | O17: 0 | P17: =+L17-O17 -> 83582.93 | Q17: 71650.28 | R17: =+L17-Q17 -> 11932.65
A18: Transport Expenses (Stat) | B18: 1 | C18: Transport | D18: 32645.06 | E18: 46646.407 | F18: =+D18-E18 -> -14001.347 | G18: 0 | H18: =+D18-G18 -> 32645.06 | I18: 58320.71 | J18: =+D18-I18 -> -25675.65 | L18: 32645.06 | M18: 46646.407 | N18: =+L18-M18 -> -14001.347 | O18: 0 | P18: =+L18-O18 -> 32645.06 | Q18: 58320.71 | R18: =+L18-Q18 -> -25675.65
A19: Rehire Expenses | B19: 1 | C19: Rehire | D19: 32658.08 | E19: 45111.022 | F19: =+D19-E19 -> -12452.942 | G19: 0 | H19: =+D19-G19 -> 32658.08 | I19: 14507.84 | J19: =+D19-I19 -> 18150.24 | L19: 32658.08 | M19: 45111.022 | N19: =+L19-M19 -> -12452.942 | O19: 0 | P19: =+L19-O19 -> 32658.08 | Q19: 14507.84 | R19: =+L19-Q19 -> 18150.24
A20: Profit/Loss on Sale of Asset | B20: 1 | C20: POSA | D20: 0 | E20: 0 | F20: =+D20-E20 -> 0 | G20: 0 | H20: =+D20-G20 -> 0 | I20: 0 | J20: =+D20-I20 -> 0 | L20: 0 | M20: 0 | N20: =+L20-M20 -> 0 | O20: 0 | P20: =+L20-O20 -> 0 | Q20: 0 | R20: =+L20-Q20 -> 0
A21: Other Direct Costs | B21: 1 | C21: Other Direct Costs | D21: 39481.51 | E21: 73474.596 | F21: =+D21-E21 -> -33993.086 | G21: 0 | H21: =+D21-G21 -> 39481.51 | I21: 11277.17 | J21: =+D21-I21 -> 28204.34 | L21: 39481.51 | M21: 73474.596 | N21: =+L21-M21 -> -33993.086 | O21: 0 | P21: =+L21-O21 -> 39481.51 | Q21: 11277.17 | R21: =+L21-Q21 -> 28204.34
A22: Total Combined Direct Costs (Stat) | B22: 1 | C22: Total Direct Costs | D22: 188367.58 | E22: 227536.99 | F22: =+D22-E22 -> -39169.408 | G22: 0 | H22: =+D22-G22 -> 188367.58 | I22: 155756 | J22: =+D22-I22 -> 32611.58 | L22: 188367.58 | M22: 227536.99 | N22: =+L22-M22 -> -39169.408 | O22: 0 | P22: =+L22-O22 -> 188367.58 | Q22: 155756 | R22: =+L22-Q22 -> 32611.58 | T22: =D22/E22 -> 0.82785477
A23: Gross Margin - Post Allocations (Stat) | B23: -1 | C23: Gross Margin | D23: 212353.36 | E23: 308050.19 | F23: =+D23-E23 -> -95696.83 | G23: 0 | H23: =+D23-G23 -> 212353.36 | I23: 287840.88 | J23: =+D23-I23 -> -75487.52 | L23: 212353.36 | M23: 308050.19 | N23: =+L23-M23 -> -95696.83 | O23: 0 | P23: =+L23-O23 -> 212353.36 | Q23: 287840.88 | R23: =+L23-Q23 -> -75487.52 | T23: =+D23/D16 -> 0.52992828 | U23: =+E23/E16 -> 0.57516349
A24: Property (Stat) | B24: 1 | C24: Property | D24: 35543.75 | E24: 37815.408 | F24: =+D24-E24 -> -2271.6578 | G24: 0 | H24: =+D24-G24 -> 35543.75 | I24: 36236.91 | J24: =+D24-I24 -> -693.16 | L24: 35543.75 | M24: 37815.408 | N24: =+L24-M24 -> -2271.6578 | O24: 0 | P24: =+L24-O24 -> 35543.75 | Q24: 36236.91 | R24: =+L24-Q24 -> -693.16
A25: Direct Staff Costs (Stat) | B25: 1 | C25: Direct Staff | D25: 33231.13 | E25: 39888.072 | F25: =+D25-E25 -> -6656.9425 | G25: 0 | H25: =+D25-G25 -> 33231.13 | I25: 69902.57 | J25: =+D25-I25 -> -36671.44 | L25: 33231.13 | M25: 39888.072 | N25: =+L25-M25 -> -6656.9425 | O25: 0 | P25: =+L25-O25 -> 33231.13 | Q25: 69902.57 | R25: =+L25-Q25 -> -36671.44
A26: Indirect Staff Costs | B26: 1 | C26: Indirect Staff | D26: 209.85 | E26: 757.81347 | F26: =+D26-E26 -> -547.96347 | G26: 0 | H26: =+D26-G26 -> 209.85 | I26: 171.66 | J26: =+D26-I26 -> 38.19 | L26: 209.85 | M26: 757.81347 | N26: =+L26-M26 -> -547.96347 | O26: 0 | P26: =+L26-O26 -> 209.85 | Q26: 171.66 | R26: =+L26-Q26 -> 38.19
A27: Marketing and Entertainment (BUFR) | B27: 1 | C27: Marketing/Entertainment | D27: 0 | E27: 105.42672 | F27: =+D27-E27 -> -105.42672 | G27: 0 | H27: =+D27-G27 -> 0 | I27: 0 | J27: =+D27-I27 -> 0 | L27: 0 | M27: 105.42672 | N27: =+L27-M27 -> -105.42672 | O27: 0 | P27: =+L27-O27 -> 0 | Q27: 0 | R27: =+L27-Q27 -> 0
A28: Telecommunications | B28: 1 | C28: Telecommunications | D28: 1134.39 | E28: 1352.1444 | F28: =+D28-E28 -> -217.75442 | G28: 0 | H28: =+D28-G28 -> 1134.39 | I28: 1208.34 | J28: =+D28-I28 -> -73.95 | L28: 1134.39 | M28: 1352.1444 | N28: =+L28-M28 -> -217.75442 | O28: 0 | P28: =+L28-O28 -> 1134.39 | Q28: 1208.34 | R28: =+L28-Q28 -> -73.95
A29: IT & EDP Expenses | B29: 1 | C29: IT&EDP | D29: 1484 | E29: 1305.6466 | F29: =+D29-E29 -> 178.35338 | G29: 0 | H29: =+D29-G29 -> 1484 | I29: 918.9 | J29: =+D29-I29 -> 565.1 | L29: 1484 | M29: 1305.6466 | N29: =+L29-M29 -> 178.35338 | O29: 0 | P29: =+L29-O29 -> 1484 | Q29: 918.9 | R29: =+L29-Q29 -> 565.1
A30: Travel & Accomodation Expense | B30: 1 | C30: Travel & Accommodation | D30: 1174.08 | E30: 2315.6767 | F30: =+D30-E30 -> -1141.5967 | G30: 0 | H30: =+D30-G30 -> 1174.08 | I30: 10801.22 | J30: =+D30-I30 -> -9627.14 | L30: 1174.08 | M30: 2315.6767 | N30: =+L30-M30 -> -1141.5967 | O30: 0 | P30: =+L30-O30 -> 1174.08 | Q30: 10801.22 | R30: =+L30-Q30 -> -9627.14
A31: Bad Debts | B31: 1 | C31: Bad Debts | D31: 763.26 | E31: 1029.3034 | F31: =+D31-E31 -> -266.04343 | G31: 0 | H31: =+D31-G31 -> 763.26 | I31: 763.15 | J31: =+D31-I31 -> 0.11 | L31: 763.26 | M31: 1029.3034 | N31: =+L31-M31 -> -266.04343 | O31: 0 | P31: =+L31-O31 -> 763.26 | Q31: 763.15 | R31: =+L31-Q31 -> 0.11
A32: Branch Admin (Stat) | B32: 1 | C32: Total Branch Administration | D32: 6465.17 | E32: 6951.4279 | F32: =+D32-E32 -> -486.2579 | G32: 0 | H32: =+D32-G32 -> 6465.17 | I32: 9261.28 | J32: =+D32-I32 -> -2796.11 | L32: 6465.17 | M32: 6951.4279 | N32: =+L32-M32 -> -486.2579 | O32: 0 | P32: =+L32-O32 -> 6465.17 | Q32: 9261.28 | R32: =+L32-Q32 -> -2796.11
A33: Statutory Cost | B33: 1 | C33: Statutory | D33: 801.03 | E33: 804.56839 | F33: =+D33-E33 -> -3.538393 | G33: 0 | H33: =+D33-G33 -> 801.03 | I33: 779.67 | J33: =+D33-I33 -> 21.36 | L33: 801.03 | M33: 804.56839 | N33: =+L33-M33 -> -3.538393 | O33: 0 | P33: =+L33-O33 -> 801.03 | Q33: 779.67 | R33: =+L33-Q33 -> 21.36
A34: Shared services & Allocated Costs | B34: 1 | C34: Shared services & Allocated Costs | D34: 68196.34 | E34: 66837.161 | F34: =+D34-E34 -> 1359.1786 | G34: 0 | H34: =+D34-G34 -> 68196.34 | I34: 55868.95 | J34: =+D34-I34 -> 12327.39 | L34: 68196.34 | M34: 66837.161 | N34: =+L34-M34 -> 1359.1786 | O34: 0 | P34: =+L34-O34 -> 68196.34 | Q34: 55868.95 | R34: =+L34-Q34 -> 12327.39
A35: Total Combined Overheads (Stat) | B35: 1 | C35: Total Overheads | D35: 149003 | E35: 159162.65 | F35: =+D35-E35 -> -10159.649 | G35: 0 | H35: =+D35-G35 -> 149003 | I35: 185912.65 | J35: =+D35-I35 -> -36909.65 | L35: 149003 | M35: 159162.65 | N35: =+L35-M35 -> -10159.649 | O35: 0 | P35: =+L35-O35 -> 149003 | Q35: 185912.65 | R35: =+L35-Q35 -> -36909.65
... A38: EBIT - Post Allocations (Stat) | B38: -1 | C38: EBIT | D38: 36854.15 | E38: 107357.54 | F38: =+D38-E38 -> -70503.393 | G38: 0 | H38: =+D38-G38 -> 36854.15 | I38: 69382.65 | J38: =+D38-I38 -> -32528.5 | L38: 36854.15 | M38: 107357.54 | N38: =+L38-M38 -> -70503.393 | O38: 0 | P38: =+L38-O38 -> 36854.15 | Q38: 69382.65 | R38: =+L38-Q38 -> -32528.5
P39: =+L39-O39 -> 0
B40: 1 | C40: Profit and Loss KPI Ratios | P40: =+L40-O40 -> 0
A41: Rehire Recovery % | B41: 1 | C41: Rehire Recovery | D41: 0.96332026 | E41: 1.29 | F41: =+D41-E41 -> -0.32667974 | G41: 0 | H41: =+D41-G41 -> 0.96332026 | I41: 0.85803055 | J41: =+D41-I41 -> 0.1052897 | L41: 0.96332026 | M41: 1.29 | N41: =+L41-M41 -> -0.32667974 | O41: 0 | P41: =+L41-O41 -> 0.96332026 | Q41: 0.85803055 | R41: =+L41-Q41 -> 0.1052897
A42: Transport Recovery % | B42: 1 | C42: Transport Recovery | D42: 1.042018 | E42: 1.0808696 | F42: =+D42-E42 -> -0.038851604 | G42: 0 | H42: =+D42-G42 -> 1.042018 | I42: 0.64327852 | J42: =+D42-I42 -> 0.39873948 | L42: 1.042018 | M42: 1.0808696 | N42: =+L42-M42 -> -0.038851604 | O42: 0 | P42: =+L42-O42 -> 1.042018 | Q42: 0.64327852 | R42: =+L42-Q42 -> 0.39873948
A43: Installation Recovery% | B43: 1 | C43: Labour Recovery - Installation | D43: 0 | E43: 1.28 | F43: =+D43-E43 -> -1.28 | G43: 0 | H43: =+D43-G43 -> 0 | I43: -15.157559 | J43: =+D43-I43 -> 15.157559 | L43: 0 | M43: 1.28 | N43: =+L43-M43 -> -1.28 | O43: 0 | P43: =+L43-O43 -> 0 | Q43: -15.157559 | R43: =+L43-Q43 -> 15.157559
A44: Consumables Recovery% | B44: 1 | C44: Consumable Recovery | D44: 0.65410447 | E44: 1.27 | F44: =+D44-E44 -> -0.61589553 | G44: 0 | H44: =+D44-G44 -> 0.65410447 | I44: 16.084184 | J44: =+D44-I44 -> -15.43008 | L44: 0.65410447 | M44: 1.27 | N44: =+L44-M44 -> -0.61589553 | O44: 0 | P44: =+L44-O44 -> 0.65410447 | Q44: 16.084184 | R44: =+L44-Q44 -> -15.43008
A45: GM % | B45: 1 | C45: Gross Margin % | D45: 0.52992828 | E45: 0.57516349 | F45: =+D45-E45 -> -0.045235205 | G45: 0 | H45: =+D45-G45 -> 0.52992828 | I45: 0.64887941 | J45: =+D45-I45 -> -0.11895112 | L45: 0.52992828 | M45: 0.57516349 | N45: =+L45-M45 -> -0.045235205 | O45: 0 | P45: =+L45-O45 -> 0.52992828 | Q45: 0.64887941 | R45: =+L45-Q45 -> -0.11895112
A46: R&M % | B46: 1 | C46: R&M / Hire Revenue | D46: 0.28114579 | E46: 0.18131097 | F46: =+D46-E46 -> 0.099834811 | G46: 0 | H46: =+D46-G46 -> 0.28114579 | I46: 0.20883658 | J46: =+D46-I46 -> 0.072309203 | L46: 0.28114579 | M46: 0.18131097 | N46: =+L46-M46 -> 0.099834811 | O46: 0 | P46: =+L46-O46 -> 0.28114579 | Q46: 0.20883658 | R46: =+L46-Q46 -> 0.072309203
A47: EBITDA % | B47: 1 | C47: EBITDA / Revenue | D47: 0.15809096 | E47: 0.27798937 | F47: =+D47-E47 -> -0.1198984 | G47: 0 | H47: =+D47-G47 -> 0.15809096 | I47: 0.22977671 | J47: =+D47-I47 -> -0.071685742 | L47: 0.15809096 | M47: 0.27798937 | N47: =+L47-M47 -> -0.1198984 | O47: 0 | P47: =+L47-O47 -> 0.15809096 | Q47: 0.22977671 | R47: =+L47-Q47 -> -0.071685742
A48: EBIT % | B48: 1 | C48: EBIT / Revenue | D48: 0.091969614 | E48: 0.20044831 | F48: =+D48-E48 -> -0.10847869 | G48: 0 | H48: =+D48-G48 -> 0.091969614 | I48: 0.15640924 | J48: =+D48-I48 -> -0.064439624 | L48: 0.091969614 | M48: 0.20044831 | N48: =+L48-M48 -> -0.10847869 | O48: 0 | P48: =+L48-O48 -> 0.091969614 | Q48: 0.15640924 | R48: =+L48-Q48 -> -0.064439624
B49: 1
C50: TU | D50: =+'IS East'!E414 -> 0.16807618 | I50: =+'IS East'!J414 -> 0.13863694 | J50: =+D50-I50 -> 0.029439236 | L50: =+'IS East'!M414 -> 0.16807618 | Q50: =+'IS East'!R414 -> 0.13863694 | R50: =+L50-Q50 -> 0.029439236
C51: ROC | D51: =+'IS East'!E412 -> 0.10760836 | I51: =+'IS East'!J412 -> 0.17987957 | J51: =+D51-I51 -> -0.07227121 | L51: =+'IS East'!M412 -> 0.10760836 | Q51: =+'IS East'!R412 -> 0.17987957 | R51: =+L51-Q51 -> -0.07227121
C52: Redline | D52: =+'IS East'!E415 -> 0.26044046 | I52: =+'IS East'!J415 -> 0.43671527 | J52: =+D52-I52 -> -0.17627481 | L52: =+'IS East'!M415 -> 0.26044046 | Q52: =+'IS East'!R415 -> 0.43671527 | R52: =+L52-Q52 -> -0.17627481
C53: Fleet Original Cost | D53: =+'IS East'!E416 -> 3930.661 | I53: =+'IS East'!J416 -> 4527.183 | J53: =+D53-I53 -> -596.52196 | L53: =+'IS East'!M416 -> 3930.661 | Q53: =+'IS East'!R416 -> 4527.183 | R53: =+L53-Q53 -> -596.52196
C58: Check | D58: =D38-'IS East'!E410 -> 0 | E58: =E38-'IS East'!F410 -> 0 | F58: =F38-'IS East'!G410 -> 0 | G58: =G38-'IS East'!H410 -> 0 | H58: =H38-'IS East'!I410 -> 0 | I58: =I38-'IS East'!J410 -> 0 | J58: =J38-'IS East'!K410 -> 0 | K58: =K38-'IS East'!L410 -> 0 | ... R58: =R38-'IS East'!S410 -> 0

Sheet North
A1: CUBE: | C1: Coates:General Ledger | E1: Target Budget FY25 Copy
A2: Financial Entity | C2: All Financial Entities
A3: Plan Measure | C3: Total
D4: =+Parameters!$B$10 -> 2026 | E4: =+Parameters!$B$10 -> 2026 | G4: =+Parameters!$B$10 -> 2026 | I4: =+D4-1 -> 2025 | L4: =+D4 -> 2026 | M4: =+E4 -> 2026 | O4: =+G4 -> 2026 | Q4: =+I4 -> 2025
D5: =+Parameters!$B$9 -> Jul | E5: =+Parameters!$B$9 -> Jul | G5: =+Parameters!$B$9 -> Jul | I5: =+E5 -> Jul | L5: =CONCATENATE(D5," ","YTD") -> Jul YTD | M5: =CONCATENATE(E5," ","YTD") -> Jul YTD | O5: =CONCATENATE(G5," ","YTD") -> Jul YTD | Q5: =CONCATENATE(I5," ","YTD") -> Jul YTD
D6: =+Parameters!B5 -> Actual | E6: =+Parameters!$B$6 -> Target Budget | G6: =+Parameters!$B$7 -> Forecast Current | I6: =+D6 -> Actual | L6: =+D6 -> Actual | M6: =+E6 -> Target Budget | O6: =+G6 -> Forecast Current | Q6: =+I6 -> Actual
D7: =+Lists!E1 -> IS_NORTH BU | E7: =+D7 -> IS_NORTH BU | F7: =+E7 -> IS_NORTH BU | G7: =+F7 -> IS_NORTH BU | H7: =+G7 -> IS_NORTH BU | I7: =+H7 -> IS_NORTH BU | J7: =+I7 -> IS_NORTH BU | K7: =+J7 -> IS_NORTH BU | L7: =+K7 -> IS_NORTH BU | ... R7: =+Q7 -> IS_NORTH BU
C8: =+Group!$C$8 -> FINANCIAL YEAR 2027 | D8: North - Industrial Solutions
D10: =CONCATENATE($D$5," ","MTD") -> Jul MTD | L10: =CONCATENATE($D$5," ","YTD") -> Jul YTD
D11: Actual | E11: Budget | F11: Var Bud | G11: Forecast | H11: Var Forecast | I11: Last Year | J11: Var LY | L11: Actual | M11: Budget | N11: Var Bud | O11: Forecast | P11: Var Forecast | Q11: Last Year | R11: Var LY
A12: Hire Revenue | B12: -1 | C12: Hire Revenue | D12: 792502.63 | E12: 760493.98 | F12: =+D12-E12 -> 32008.65 | G12: 0 | H12: =+D12-G12 -> 792502.63 | I12: 703471.47 | J12: =+D12-I12 -> 89031.16 | L12: 792502.63 | M12: 760493.98 | N12: =+L12-M12 -> 32008.65 | O12: 0 | P12: =+L12-O12 -> 792502.63 | Q12: 703471.47 | R12: =+L12-Q12 -> 89031.16
A13: Rehire Revenue | B13: -1 | C13: Rehire Revenue | D13: 164876.21 | E13: 122944.81 | F13: =+D13-E13 -> 41931.4 | G13: 0 | H13: =+D13-G13 -> 164876.21 | I13: 97045.5 | J13: =+D13-I13 -> 67830.71 | L13: 164876.21 | M13: 122944.81 | N13: =+L13-M13 -> 41931.4 | O13: 0 | P13: =+L13-O13 -> 164876.21 | Q13: 97045.5 | R13: =+L13-Q13 -> 67830.71
A14: Transport | B14: -1 | C14: Transport Revenue | D14: 196906.03 | E14: 103310.2 | F14: =+D14-E14 -> 93595.829 | G14: 0 | H14: =+D14-G14 -> 196906.03 | I14: 63096.01 | J14: =+D14-I14 -> 133810.02 | L14: 196906.03 | M14: 103310.2 | N14: =+L14-M14 -> 93595.829 | O14: 0 | P14: =+L14-O14 -> 196906.03 | Q14: 63096.01 | R14: =+L14-Q14 -> 133810.02
A15: Other Revenue. | B15: -1 | C15: Other Revenue | D15: 225330.46 | E15: 173074.34 | F15: =+D15-E15 -> 52256.119 | G15: 0 | H15: =+D15-G15 -> 225330.46 | I15: 53841.59 | J15: =+D15-I15 -> 171488.87 | L15: 225330.46 | M15: 173074.34 | N15: =+L15-M15 -> 52256.119 | O15: 0 | P15: =+L15-O15 -> 225330.46 | Q15: 53841.59 | R15: =+L15-Q15 -> 171488.87
A16: Total Combined Revenue | B16: -1 | C16: Total Revenue | D16: 1379615.3 | E16: 1159823.3 | F16: =+D16-E16 -> 219792 | G16: 0 | H16: =+D16-G16 -> 1379615.3 | I16: 917454.57 | J16: =+D16-I16 -> 462160.76 | L16: 1379615.3 | M16: 1159823.3 | N16: =+L16-M16 -> 219792 | O16: 0 | P16: =+L16-O16 -> 1379615.3 | Q16: 917454.57 | R16: =+L16-Q16 -> 462160.76 | T16: =D16/E16 -> 1.1895047
A17: Total Repairs & Maintenance | B17: 1 | C17: Total Repairs & Maint | D17: 188830.04 | E17: 149365.18 | F17: =+D17-E17 -> 39464.864 | G17: 0 | H17: =+D17-G17 -> 188830.04 | I17: 94879.4 | J17: =+D17-I17 -> 93950.64 | L17: 188830.04 | M17: 149365.18 | N17: =+L17-M17 -> 39464.864 | O17: 0 | P17: =+L17-O17 -> 188830.04 | Q17: 94879.4 | R17: =+L17-Q17 -> 93950.64
A18: Transport Expenses (Stat) | B18: 1 | C18: Transport | D18: 177517.12 | E18: 90478.882 | F18: =+D18-E18 -> 87038.238 | G18: 0 | H18: =+D18-G18 -> 177517.12 | I18: 64857.77 | J18: =+D18-I18 -> 112659.35 | L18: 177517.12 | M18: 90478.882 | N18: =+L18-M18 -> 87038.238 | O18: 0 | P18: =+L18-O18 -> 177517.12 | Q18: 64857.77 | R18: =+L18-Q18 -> 112659.35
A19: Rehire Expenses | B19: 1 | C19: Rehire | D19: 140650.11 | E19: 94688.155 | F19: =+D19-E19 -> 45961.955 | G19: 0 | H19: =+D19-G19 -> 140650.11 | I19: 80821.96 | J19: =+D19-I19 -> 59828.15 | L19: 140650.11 | M19: 94688.155 | N19: =+L19-M19 -> 45961.955 | O19: 0 | P19: =+L19-O19 -> 140650.11 | Q19: 80821.96 | R19: =+L19-Q19 -> 59828.15
A20: Profit/Loss on Sale of Asset | B20: 1 | C20: POSA | D20: 0 | E20: 0 | F20: =+D20-E20 -> 0 | G20: 0 | H20: =+D20-G20 -> 0 | I20: 0 | J20: =+D20-I20 -> 0 | L20: 0 | M20: 0 | N20: =+L20-M20 -> 0 | O20: 0 | P20: =+L20-O20 -> 0 | Q20: 0 | R20: =+L20-Q20 -> 0
A21: Other Direct Costs | B21: 1 | C21: Other Direct Costs | D21: 140188.56 | E21: 121628.99 | F21: =+D21-E21 -> 18559.574 | G21: 0 | H21: =+D21-G21 -> 140188.56 | I21: 35148.25 | J21: =+D21-I21 -> 105040.31 | L21: 140188.56 | M21: 121628.99 | N21: =+L21-M21 -> 18559.574 | O21: 0 | P21: =+L21-O21 -> 140188.56 | Q21: 35148.25 | R21: =+L21-Q21 -> 105040.31
A22: Total Combined Direct Costs (Stat) | B22: 1 | C22: Total Direct Costs | D22: 647185.83 | E22: 456161.2 | F22: =+D22-E22 -> 191024.63 | G22: 0 | H22: =+D22-G22 -> 647185.83 | I22: 275707.38 | J22: =+D22-I22 -> 371478.45 | L22: 647185.83 | M22: 456161.2 | N22: =+L22-M22 -> 191024.63 | O22: 0 | P22: =+L22-O22 -> 647185.83 | Q22: 275707.38 | R22: =+L22-Q22 -> 371478.45 | T22: =D22/E22 -> 1.4187656
A23: Gross Margin - Post Allocations (Stat) | B23: -1 | C23: Gross Margin | D23: 732429.5 | E23: 703662.13 | F23: =+D23-E23 -> 28767.366 | G23: 0 | H23: =+D23-G23 -> 732429.5 | I23: 641747.19 | J23: =+D23-I23 -> 90682.31 | L23: 732429.5 | M23: 703662.13 | N23: =+L23-M23 -> 28767.366 | O23: 0 | P23: =+L23-O23 -> 732429.5 | Q23: 641747.19 | R23: =+L23-Q23 -> 90682.31 | T23: =+D23/D16 -> 0.530894 | U23: =+E23/E16 -> 0.60669769
A24: Property (Stat) | B24: 1 | C24: Property | D24: 41248.3 | E24: 44024.154 | F24: =+D24-E24 -> -2775.8537 | G24: 0 | H24: =+D24-G24 -> 41248.3 | I24: 46354.06 | J24: =+D24-I24 -> -5105.76 | L24: 41248.3 | M24: 44024.154 | N24: =+L24-M24 -> -2775.8537 | O24: 0 | P24: =+L24-O24 -> 41248.3 | Q24: 46354.06 | R24: =+L24-Q24 -> -5105.76
A25: Direct Staff Costs (Stat) | B25: 1 | C25: Direct Staff | D25: 51117.11 | E25: 88411.927 | F25: =+D25-E25 -> -37294.817 | G25: 0 | H25: =+D25-G25 -> 51117.11 | I25: 121188.54 | J25: =+D25-I25 -> -70071.43 | L25: 51117.11 | M25: 88411.927 | N25: =+L25-M25 -> -37294.817 | O25: 0 | P25: =+L25-O25 -> 51117.11 | Q25: 121188.54 | R25: =+L25-Q25 -> -70071.43
A26: Indirect Staff Costs | B26: 1 | C26: Indirect Staff | D26: 728.44 | E26: 747.70002 | F26: =+D26-E26 -> -19.260023 | G26: 0 | H26: =+D26-G26 -> 728.44 | I26: 82.56 | J26: =+D26-I26 -> 645.88 | L26: 728.44 | M26: 747.70002 | N26: =+L26-M26 -> -19.260023 | O26: 0 | P26: =+L26-O26 -> 728.44 | Q26: 82.56 | R26: =+L26-Q26 -> 645.88
A27: Marketing and Entertainment (BUFR) | B27: 1 | C27: Marketing/Entertainment | D27: 373.95 | E27: 26.591667 | F27: =+D27-E27 -> 347.35833 | G27: 0 | H27: =+D27-G27 -> 373.95 | I27: 0 | J27: =+D27-I27 -> 373.95 | L27: 373.95 | M27: 26.591667 | N27: =+L27-M27 -> 347.35833 | O27: 0 | P27: =+L27-O27 -> 373.95 | Q27: 0 | R27: =+L27-Q27 -> 373.95
A28: Telecommunications | B28: 1 | C28: Telecommunications | D28: 1597.86 | E28: 1932.8658 | F28: =+D28-E28 -> -335.00583 | G28: 0 | H28: =+D28-G28 -> 1597.86 | I28: 2325.22 | J28: =+D28-I28 -> -727.36 | L28: 1597.86 | M28: 1932.8658 | N28: =+L28-M28 -> -335.00583 | O28: 0 | P28: =+L28-O28 -> 1597.86 | Q28: 2325.22 | R28: =+L28-Q28 -> -727.36
A29: IT & EDP Expenses | B29: 1 | C29: IT&EDP | D29: 5895.79 | E29: 1093.0708 | F29: =+D29-E29 -> 4802.7192 | G29: 0 | H29: =+D29-G29 -> 5895.79 | I29: -218.56 | J29: =+D29-I29 -> 6114.35 | L29: 5895.79 | M29: 1093.0708 | N29: =+L29-M29 -> 4802.7192 | O29: 0 | P29: =+L29-O29 -> 5895.79 | Q29: -218.56 | R29: =+L29-Q29 -> 6114.35
A30: Travel & Accomodation Expense | B30: 1 | C30: Travel & Accommodation | D30: 5979.85 | E30: 5373.8018 | F30: =+D30-E30 -> 606.04817 | G30: 0 | H30: =+D30-G30 -> 5979.85 | I30: 2801.89 | J30: =+D30-I30 -> 3177.96 | L30: 5979.85 | M30: 5373.8018 | N30: =+L30-M30 -> 606.04817 | O30: 0 | P30: =+L30-O30 -> 5979.85 | Q30: 2801.89 | R30: =+L30-Q30 -> 3177.96
A31: Bad Debts | B31: 1 | C31: Bad Debts | D31: 2277.73 | E31: 1949.4994 | F31: =+D31-E31 -> 328.2306 | G31: 0 | H31: =+D31-G31 -> 2277.73 | I31: 1578.37 | J31: =+D31-I31 -> 699.36 | L31: 2277.73 | M31: 1949.4994 | N31: =+L31-M31 -> 328.2306 | O31: 0 | P31: =+L31-O31 -> 2277.73 | Q31: 1578.37 | R31: =+L31-Q31 -> 699.36
A32: Branch Admin (Stat) | B32: 1 | C32: Total Branch Administration | D32: 4407.97 | E32: 4904.2078 | F32: =+D32-E32 -> -496.23782 | G32: 0 | H32: =+D32-G32 -> 4407.97 | I32: 9891.12 | J32: =+D32-I32 -> -5483.15 | L32: 4407.97 | M32: 4904.2078 | N32: =+L32-M32 -> -496.23782 | O32: 0 | P32: =+L32-O32 -> 4407.97 | Q32: 9891.12 | R32: =+L32-Q32 -> -5483.15
A33: Statutory Cost | B33: 1 | C33: Statutory | D33: 838.18 | E33: 838.1757 | F33: =+D33-E33 -> 0.0042999214 | G33: 0 | H33: =+D33-G33 -> 838.18 | I33: 784.32 | J33: =+D33-I33 -> 53.86 | L33: 838.18 | M33: 838.1757 | N33: =+L33-M33 -> 0.0042999214 | O33: 0 | P33: =+L33-O33 -> 838.18 | Q33: 784.32 | R33: =+L33-Q33 -> 53.86
A34: Shared services & Allocated Costs | B34: 1 | C34: Shared services & Allocated Costs | D34: 155023.5 | E34: 153400.22 | F34: =+D34-E34 -> 1623.2766 | G34: 0 | H34: =+D34-G34 -> 155023.5 | I34: 157691.59 | J34: =+D34-I34 -> -2668.09 | L34: 155023.5 | M34: 153400.22 | N34: =+L34-M34 -> 1623.2766 | O34: 0 | P34: =+L34-O34 -> 155023.5 | Q34: 157691.59 | R34: =+L34-Q34 -> -2668.09
A35: Total Combined Overheads (Stat) | B35: 1 | C35: Total Overheads | D35: 269488.68 | E35: 302702.22 | F35: =+D35-E35 -> -33213.537 | G35: 0 | H35: =+D35-G35 -> 269488.68 | I35: 342479.11 | J35: =+D35-I35 -> -72990.43 | L35: 269488.68 | M35: 302702.22 | N35: =+L35-M35 -> -33213.537 | O35: 0 | P35: =+L35-O35 -> 269488.68 | Q35: 342479.11 | R35: =+L35-Q35 -> -72990.43
... A38: EBIT - Post Allocations (Stat) | B38: -1 | C38: EBIT | D38: 297551.26 | E38: 237834.38 | F38: =+D38-E38 -> 59716.882 | G38: 0 | H38: =+D38-G38 -> 297551.26 | I38: 131484.96 | J38: =+D38-I38 -> 166066.3 | L38: 297551.26 | M38: 237834.38 | N38: =+L38-M38 -> 59716.882 | O38: 0 | P38: =+L38-O38 -> 297551.26 | Q38: 131484.96 | R38: =+L38-Q38 -> 166066.3
P39: =+L39-O39 -> 0
B40: 1 | C40: Profit and Loss KPI Ratios | P40: =+L40-O40 -> 0
A41: Rehire Recovery % | B41: 1 | C41: Rehire Recovery | D41: 1.1722437 | E41: 1.2984181 | F41: =+D41-E41 -> -0.12617433 | G41: 0 | H41: =+D41-G41 -> 1.1722437 | I41: 1.2007318 | J41: =+D41-I41 -> -0.028488098 | L41: 1.1722437 | M41: 1.2984181 | N41: =+L41-M41 -> -0.12617433 | O41: 0 | P41: =+L41-O41 -> 1.1722437 | Q41: 1.2007318 | R41: =+L41-Q41 -> -0.028488098
A42: Transport Recovery % | B42: 1 | C42: Transport Recovery | D42: 1.1092228 | E42: 1.1418156 | F42: =+D42-E42 -> -0.032592853 | G42: 0 | H42: =+D42-G42 -> 1.1092228 | I42: 0.97283656 | J42: =+D42-I42 -> 0.1363862 | L42: 1.1092228 | M42: 1.1418156 | N42: =+L42-M42 -> -0.032592853 | O42: 0 | P42: =+L42-O42 -> 1.1092228 | Q42: 0.97283656 | R42: =+L42-Q42 -> 0.1363862
A43: Installation Recovery% | B43: 1 | C43: Labour Recovery - Installation | D43: 1.2454228 | E43: 1.3005598 | F43: =+D43-E43 -> -0.055136995 | G43: 0 | H43: =+D43-G43 -> 1.2454228 | I43: 2.0048863 | J43: =+D43-I43 -> -0.7594635 | L43: 1.2454228 | M43: 1.3005598 | N43: =+L43-M43 -> -0.055136995 | O43: 0 | P43: =+L43-O43 -> 1.2454228 | Q43: 2.0048863 | R43: =+L43-Q43 -> -0.7594635
A44: Consumables Recovery% | B44: 1 | C44: Consumable Recovery | D44: 1.1759449 | E44: 1.1995467 | F44: =+D44-E44 -> -0.023601812 | G44: 0 | H44: =+D44-G44 -> 1.1759449 | I44: -0.028460743 | J44: =+D44-I44 -> 1.2044056 | L44: 1.1759449 | M44: 1.1995467 | N44: =+L44-M44 -> -0.023601812 | O44: 0 | P44: =+L44-O44 -> 1.1759449 | Q44: -0.028460743 | R44: =+L44-Q44 -> 1.2044056
A45: GM % | B45: 1 | C45: Gross Margin % | D45: 0.530894 | E45: 0.60669769 | F45: =+D45-E45 -> -0.075803688 | G45: 0 | H45: =+D45-G45 -> 0.530894 | I45: 0.69948661 | J45: =+D45-I45 -> -0.16859261 | L45: 0.530894 | M45: 0.60669769 | N45: =+L45-M45 -> -0.075803688 | O45: 0 | P45: =+L45-O45 -> 0.530894 | Q45: 0.69948661 | R45: =+L45-Q45 -> -0.16859261
A46: R&M % | B46: 1 | C46: R&M / Hire Revenue | D46: 0.23767438 | E46: 0.19569881 | F46: =+D46-E46 -> 0.041975577 | G46: 0 | H46: =+D46-G46 -> 0.23767438 | I46: 0.13440416 | J46: =+D46-I46 -> 0.10327023 | L46: 0.23767438 | M46: 0.19569881 | N46: =+L46-M46 -> 0.041975577 | O46: 0 | P46: =+L46-O46 -> 0.23767438 | Q46: 0.13440416 | R46: =+L46-Q46 -> 0.10327023
A47: EBITDA % | B47: 1 | C47: EBITDA / Revenue | D47: 0.3355579 | E47: 0.34570775 | F47: =+D47-E47 -> -0.010149854 | G47: 0 | H47: =+D47-G47 -> 0.3355579 | I47: 0.3261939 | J47: =+D47-I47 -> 0.0093640025 | L47: 0.3355579 | M47: 0.34570775 | N47: =+L47-M47 -> -0.010149854 | O47: 0 | P47: =+L47-O47 -> 0.3355579 | Q47: 0.3261939 | R47: =+L47-Q47 -> 0.0093640025
A48: EBIT % | B48: 1 | C48: EBIT / Revenue | D48: 0.21567697 | E48: 0.20506087 | F48: =+D48-E48 -> 0.010616108 | G48: 0 | H48: =+D48-G48 -> 0.21567697 | I48: 0.14331495 | J48: =+D48-I48 -> 0.07236202 | L48: 0.21567697 | M48: 0.20506087 | N48: =+L48-M48 -> 0.010616108 | O48: 0 | P48: =+L48-O48 -> 0.21567697 | Q48: 0.14331495 | R48: =+L48-Q48 -> 0.07236202
B49: 1
C50: TU | D50: =+'IS North'!E414 -> 0.68116805 | I50: =+'IS North'!J414 -> 0.51202314 | J50: =+D50-I50 -> 0.16914491 | L50: =+'IS North'!M414 -> 0.68116805 | Q50: =+'IS North'!R414 -> 0.51202314 | R50: =+L50-Q50 -> 0.16914491
C51: ROC | D51: =+'IS North'!E412 -> 0.16050758 | I51: =+'IS North'!J412 -> 0.075319155 | J51: =+D51-I51 -> 0.085188427 | L51: =+'IS North'!M412 -> 0.16050758 | Q51: =+'IS North'!R412 -> 0.075319155 | R51: =+L51-Q51 -> 0.085188427
C52: Redline | D52: =+'IS North'!E415 -> 0.1550612 | I52: =+'IS North'!J415 -> 0.14613715 | J52: =+D52-I52 -> 0.0089240509 | L52: =+'IS North'!M415 -> 0.1550612 | Q52: =+'IS North'!R415 -> 0.14613715 | R52: =+L52-Q52 -> 0.0089240509
C53: Fleet Original Cost | D53: =+'IS North'!E416 -> 22830.997 | I53: =+'IS North'!J416 -> 20699.926 | J53: =+D53-I53 -> 2131.0706 | L53: =+'IS North'!M416 -> 22830.997 | Q53: =+'IS North'!R416 -> 20699.926 | R53: =+L53-Q53 -> 2131.0706
C58: Check | D58: =D38-'IS North'!E410 -> 0 | E58: =E38-'IS North'!F410 -> 0 | F58: =F38-'IS North'!G410 -> 0 | G58: =G38-'IS North'!H410 -> 0 | H58: =H38-'IS North'!I410 -> 0 | I58: =I38-'IS North'!J410 -> 0 | J58: =J38-'IS North'!K410 -> 0 | K58: =K38-'IS North'!L410 -> 0 | ... R58: =R38-'IS North'!S410 -> 0

Sheet South
A1: CUBE: | C1: Coates:General Ledger | E1: Target Budget FY25 Copy
A2: Financial Entity | C2: All Financial Entities
A3: Plan Measure | C3: Total
D4: =+Parameters!$B$10 -> 2026 | E4: =+Parameters!$B$10 -> 2026 | G4: =+Parameters!$B$10 -> 2026 | I4: =+D4-1 -> 2025 | L4: =+D4 -> 2026 | M4: =+E4 -> 2026 | O4: =+G4 -> 2026 | Q4: =+I4 -> 2025
D5: =+Parameters!$B$9 -> Jul | E5: =+Parameters!$B$9 -> Jul | G5: =+Parameters!$B$9 -> Jul | I5: =+E5 -> Jul | L5: =CONCATENATE(D5," ","YTD") -> Jul YTD | M5: =CONCATENATE(E5," ","YTD") -> Jul YTD | O5: =CONCATENATE(G5," ","YTD") -> Jul YTD | Q5: =CONCATENATE(I5," ","YTD") -> Jul YTD
D6: =+Parameters!B5 -> Actual | E6: =+Parameters!$B$6 -> Target Budget | G6: =+Parameters!$B$7 -> Forecast Current | I6: =+D6 -> Actual | L6: =+D6 -> Actual | M6: =+E6 -> Target Budget | O6: =+G6 -> Forecast Current | Q6: =+I6 -> Actual
D7: =+Lists!G1 -> IS_SOUTH BU | E7: =+D7 -> IS_SOUTH BU | F7: =+E7 -> IS_SOUTH BU | G7: =+F7 -> IS_SOUTH BU | H7: =+G7 -> IS_SOUTH BU | I7: =+H7 -> IS_SOUTH BU | J7: =+I7 -> IS_SOUTH BU | K7: =+J7 -> IS_SOUTH BU | L7: =+K7 -> IS_SOUTH BU | ... R7: =+Q7 -> IS_SOUTH BU
C8: =+Group!$C$8 -> FINANCIAL YEAR 2027 | D8: South - Industrial Solutions
D10: =CONCATENATE($D$5," ","MTD") -> Jul MTD | L10: =CONCATENATE($D$5," ","YTD") -> Jul YTD
D11: Actual | E11: Budget | F11: Var Bud | G11: Forecast | H11: Var Forecast | I11: Last Year | J11: Var LY | L11: Actual | M11: Budget | N11: Var Bud | O11: Forecast | P11: Var Forecast | Q11: Last Year | R11: Var LY
A12: Hire Revenue | B12: -1 | C12: Hire Revenue | D12: 824679.96 | E12: 928423.12 | F12: =+D12-E12 -> -103743.16 | G12: 0 | H12: =+D12-G12 -> 824679.96 | I12: 941618.68 | J12: =+D12-I12 -> -116938.72 | L12: 824679.96 | M12: 928423.12 | N12: =+L12-M12 -> -103743.16 | O12: 0 | P12: =+L12-O12 -> 824679.96 | Q12: 941618.68 | R12: =+L12-Q12 -> -116938.72
A13: Rehire Revenue | B13: -1 | C13: Rehire Revenue | D13: 25414.28 | E13: 15249.781 | F13: =+D13-E13 -> 10164.499 | G13: 0 | H13: =+D13-G13 -> 25414.28 | I13: 15579.96 | J13: =+D13-I13 -> 9834.32 | L13: 25414.28 | M13: 15249.781 | N13: =+L13-M13 -> 10164.499 | O13: 0 | P13: =+L13-O13 -> 25414.28 | Q13: 15579.96 | R13: =+L13-Q13 -> 9834.32
A14: Transport | B14: -1 | C14: Transport Revenue | D14: 38125.82 | E14: 25604.925 | F14: =+D14-E14 -> 12520.895 | G14: 0 | H14: =+D14-G14 -> 38125.82 | I14: 26907.12 | J14: =+D14-I14 -> 11218.7 | L14: 38125.82 | M14: 25604.925 | N14: =+L14-M14 -> 12520.895 | O14: 0 | P14: =+L14-O14 -> 38125.82 | Q14: 26907.12 | R14: =+L14-Q14 -> 11218.7
A15: Other Revenue. | B15: -1 | C15: Other Revenue | D15: 85649.64 | E15: 110444.17 | F15: =+D15-E15 -> -24794.534 | G15: 0 | H15: =+D15-G15 -> 85649.64 | I15: 108997.81 | J15: =+D15-I15 -> -23348.17 | L15: 85649.64 | M15: 110444.17 | N15: =+L15-M15 -> -24794.534 | O15: 0 | P15: =+L15-O15 -> 85649.64 | Q15: 108997.81 | R15: =+L15-Q15 -> -23348.17
A16: Total Combined Revenue | B16: -1 | C16: Total Revenue | D16: 973869.7 | E16: 1079722 | F16: =+D16-E16 -> -105852.3 | G16: 0 | H16: =+D16-G16 -> 973869.7 | I16: 1093103.6 | J16: =+D16-I16 -> -119233.87 | L16: 973869.7 | M16: 1079722 | N16: =+L16-M16 -> -105852.3 | O16: 0 | P16: =+L16-O16 -> 973869.7 | Q16: 1093103.6 | R16: =+L16-Q16 -> -119233.87 | T16: =D16/E16 -> 0.90196338
A17: Total Repairs & Maintenance | B17: 1 | C17: Total Repairs & Maint | D17: 321364.07 | E17: 235825.48 | F17: =+D17-E17 -> 85538.588 | G17: 0 | H17: =+D17-G17 -> 321364.07 | I17: 243428.84 | J17: =+D17-I17 -> 77935.23 | L17: 321364.07 | M17: 235825.48 | N17: =+L17-M17 -> 85538.588 | O17: 0 | P17: =+L17-O17 -> 321364.07 | Q17: 243428.84 | R17: =+L17-Q17 -> 77935.23
A18: Transport Expenses (Stat) | B18: 1 | C18: Transport | D18: 57764.2 | E18: 32342.034 | F18: =+D18-E18 -> 25422.166 | G18: 0 | H18: =+D18-G18 -> 57764.2 | I18: 46775.47 | J18: =+D18-I18 -> 10988.73 | L18: 57764.2 | M18: 32342.034 | N18: =+L18-M18 -> 25422.166 | O18: 0 | P18: =+L18-O18 -> 57764.2 | Q18: 46775.47 | R18: =+L18-Q18 -> 10988.73
A19: Rehire Expenses | B19: 1 | C19: Rehire | D19: 25105.97 | E19: 10971.066 | F19: =+D19-E19 -> 14134.904 | G19: 0 | H19: =+D19-G19 -> 25105.97 | I19: 15787.35 | J19: =+D19-I19 -> 9318.62 | L19: 25105.97 | M19: 10971.066 | N19: =+L19-M19 -> 14134.904 | O19: 0 | P19: =+L19-O19 -> 25105.97 | Q19: 15787.35 | R19: =+L19-Q19 -> 9318.62
A20: Profit/Loss on Sale of Asset | B20: 1 | C20: POSA | D20: 0 | E20: 0 | F20: =+D20-E20 -> 0 | G20: 0 | H20: =+D20-G20 -> 0 | I20: 0 | J20: =+D20-I20 -> 0 | L20: 0 | M20: 0 | N20: =+L20-M20 -> 0 | O20: 0 | P20: =+L20-O20 -> 0 | Q20: 0 | R20: =+L20-Q20 -> 0
A21: Other Direct Costs | B21: 1 | C21: Other Direct Costs | D21: 92383.08 | E21: 127395.25 | F21: =+D21-E21 -> -35012.172 | G21: 0 | H21: =+D21-G21 -> 92383.08 | I21: 128953.87 | J21: =+D21-I21 -> -36570.79 | L21: 92383.08 | M21: 127395.25 | N21: =+L21-M21 -> -35012.172 | O21: 0 | P21: =+L21-O21 -> 92383.08 | Q21: 128953.87 | R21: =+L21-Q21 -> -36570.79
A22: Total Combined Direct Costs (Stat) | B22: 1 | C22: Total Direct Costs | D22: 496617.32 | E22: 406533.83 | F22: =+D22-E22 -> 90083.486 | G22: 0 | H22: =+D22-G22 -> 496617.32 | I22: 434945.53 | J22: =+D22-I22 -> 61671.79 | L22: 496617.32 | M22: 406533.83 | N22: =+L22-M22 -> 90083.486 | O22: 0 | P22: =+L22-O22 -> 496617.32 | Q22: 434945.53 | R22: =+L22-Q22 -> 61671.79 | T22: =D22/E22 -> 1.2215891
A23: Gross Margin - Post Allocations (Stat) | B23: -1 | C23: Gross Margin | D23: 477252.38 | E23: 673188.17 | F23: =+D23-E23 -> -195935.79 | G23: 0 | H23: =+D23-G23 -> 477252.38 | I23: 658158.04 | J23: =+D23-I23 -> -180905.66 | L23: 477252.38 | M23: 673188.17 | N23: =+L23-M23 -> -195935.79 | O23: 0 | P23: =+L23-O23 -> 477252.38 | Q23: 658158.04 | R23: =+L23-Q23 -> -180905.66 | T23: =+D23/D16 -> 0.49005774 | U23: =+E23/E16 -> 0.62348287
A24: Property (Stat) | B24: 1 | C24: Property | D24: 34298.88 | E24: 32353.32 | F24: =+D24-E24 -> 1945.5596 | G24: 0 | H24: =+D24-G24 -> 34298.88 | I24: 27915.87 | J24: =+D24-I24 -> 6383.01 | L24: 34298.88 | M24: 32353.32 | N24: =+L24-M24 -> 1945.5596 | O24: 0 | P24: =+L24-O24 -> 34298.88 | Q24: 27915.87 | R24: =+L24-Q24 -> 6383.01
A25: Direct Staff Costs (Stat) | B25: 1 | C25: Direct Staff | D25: 73980.57 | E25: 89233.636 | F25: =+D25-E25 -> -15253.066 | G25: 0 | H25: =+D25-G25 -> 73980.57 | I25: 94503.34 | J25: =+D25-I25 -> -20522.77 | L25: 73980.57 | M25: 89233.636 | N25: =+L25-M25 -> -15253.066 | O25: 0 | P25: =+L25-O25 -> 73980.57 | Q25: 94503.34 | R25: =+L25-Q25 -> -20522.77
A26: Indirect Staff Costs | B26: 1 | C26: Indirect Staff | D26: 3320.59 | E26: 4567.68 | F26: =+D26-E26 -> -1247.09 | G26: 0 | H26: =+D26-G26 -> 3320.59 | I26: 4102.79 | J26: =+D26-I26 -> -782.2 | L26: 3320.59 | M26: 4567.68 | N26: =+L26-M26 -> -1247.09 | O26: 0 | P26: =+L26-O26 -> 3320.59 | Q26: 4102.79 | R26: =+L26-Q26 -> -782.2
A27: Marketing and Entertainment (BUFR) | B27: 1 | C27: Marketing/Entertainment | D27: 0 | E27: 255.73 | F27: =+D27-E27 -> -255.73 | G27: 0 | H27: =+D27-G27 -> 0 | I27: 0 | J27: =+D27-I27 -> 0 | L27: 0 | M27: 255.73 | N27: =+L27-M27 -> -255.73 | O27: 0 | P27: =+L27-O27 -> 0 | Q27: 0 | R27: =+L27-Q27 -> 0
A28: Telecommunications | B28: 1 | C28: Telecommunications | D28: 1530.83 | E28: 1755.07 | F28: =+D28-E28 -> -224.24 | G28: 0 | H28: =+D28-G28 -> 1530.83 | I28: 1588.42 | J28: =+D28-I28 -> -57.59 | L28: 1530.83 | M28: 1755.07 | N28: =+L28-M28 -> -224.24 | O28: 0 | P28: =+L28-O28 -> 1530.83 | Q28: 1588.42 | R28: =+L28-Q28 -> -57.59
A29: IT & EDP Expenses | B29: 1 | C29: IT&EDP | D29: 1377 | E29: 1436.32 | F29: =+D29-E29 -> -59.32 | G29: 0 | H29: =+D29-G29 -> 1377 | I29: 1392.72 | J29: =+D29-I29 -> -15.72 | L29: 1377 | M29: 1436.32 | N29: =+L29-M29 -> -59.32 | O29: 0 | P29: =+L29-O29 -> 1377 | Q29: 1392.72 | R29: =+L29-Q29 -> -15.72
A30: Travel & Accomodation Expense | B30: 1 | C30: Travel & Accommodation | D30: 12721 | E30: 670.15 | F30: =+D30-E30 -> 12050.85 | G30: 0 | H30: =+D30-G30 -> 12721 | I30: 0 | J30: =+D30-I30 -> 12721 | L30: 12721 | M30: 670.15 | N30: =+L30-M30 -> 12050.85 | O30: 0 | P30: =+L30-O30 -> 12721 | Q30: 0 | R30: =+L30-Q30 -> 12721
A31: Bad Debts | B31: 1 | C31: Bad Debts | D31: 1774.38 | E31: 2030.35 | F31: =+D31-E31 -> -255.97 | G31: 0 | H31: =+D31-G31 -> 1774.38 | I31: 1880.55 | J31: =+D31-I31 -> -106.17 | L31: 1774.38 | M31: 2030.35 | N31: =+L31-M31 -> -255.97 | O31: 0 | P31: =+L31-O31 -> 1774.38 | Q31: 1880.55 | R31: =+L31-Q31 -> -106.17
A32: Branch Admin (Stat) | B32: 1 | C32: Total Branch Administration | D32: 6617.51 | E32: 5384.2677 | F32: =+D32-E32 -> 1233.2423 | G32: 0 | H32: =+D32-G32 -> 6617.51 | I32: 11382.3 | J32: =+D32-I32 -> -4764.79 | L32: 6617.51 | M32: 5384.2677 | N32: =+L32-M32 -> 1233.2423 | O32: 0 | P32: =+L32-O32 -> 6617.51 | Q32: 11382.3 | R32: =+L32-Q32 -> -4764.79
A33: Statutory Cost | B33: 1 | C33: Statutory | D33: 2433.33 | E33: 2433.33 | F33: =+D33-E33 -> 0 | G33: 0 | H33: =+D33-G33 -> 2433.33 | I33: 2358.07 | J33: =+D33-I33 -> 75.26 | L33: 2433.33 | M33: 2433.33 | N33: =+L33-M33 -> 0 | O33: 0 | P33: =+L33-O33 -> 2433.33 | Q33: 2358.07 | R33: =+L33-Q33 -> 75.26
A34: Shared services & Allocated Costs | B34: 1 | C34: Shared services & Allocated Costs | D34: 168871.03 | E34: 158575.28 | F34: =+D34-E34 -> 10295.752 | G34: 0 | H34: =+D34-G34 -> 168871.03 | I34: 204888.91 | J34: =+D34-I34 -> -36017.88 | L34: 168871.03 | M34: 158575.28 | N34: =+L34-M34 -> 10295.752 | O34: 0 | P34: =+L34-O34 -> 168871.03 | Q34: 204888.91 | R34: =+L34-Q34 -> -36017.88
A35: Total Combined Overheads (Stat) | B35: 1 | C35: Total Overheads | D35: 306925.12 | E35: 298695.13 | F35: =+D35-E35 -> 8229.9873 | G35: 0 | H35: =+D35-G35 -> 306925.12 | I35: 350012.97 | J35: =+D35-I35 -> -43087.85 | L35: 306925.12 | M35: 298695.13 | N35: =+L35-M35 -> 8229.9873 | O35: 0 | P35: =+L35-O35 -> 306925.12 | Q35: 350012.97 | R35: =+L35-Q35 -> -43087.85
... A38: EBIT - Post Allocations (Stat) | B38: -1 | C38: EBIT | D38: -24976.05 | E38: 170851.93 | F38: =+D38-E38 -> -195827.98 | G38: 0 | H38: =+D38-G38 -> -24976.05 | I38: 105226.99 | J38: =+D38-I38 -> -130203.04 | L38: -24976.05 | M38: 170851.93 | N38: =+L38-M38 -> -195827.98 | O38: 0 | P38: =+L38-O38 -> -24976.05 | Q38: 105226.99 | R38: =+L38-Q38 -> -130203.04
P39: =+L39-O39 -> 0
B40: 1 | C40: Profit and Loss KPI Ratios | P40: =+L40-O40 -> 0
A41: Rehire Recovery % | B41: 1 | C41: Rehire Recovery | D41: 1.0122803 | E41: 1.39 | F41: =+D41-E41 -> -0.37771965 | G41: 0 | H41: =+D41-G41 -> 1.0122803 | I41: 0.98686353 | J41: =+D41-I41 -> 0.025416813 | L41: 1.0122803 | M41: 1.39 | N41: =+L41-M41 -> -0.37771965 | O41: 0 | P41: =+L41-O41 -> 1.0122803 | Q41: 0.98686353 | R41: =+L41-Q41 -> 0.025416813
A42: Transport Recovery % | B42: 1 | C42: Transport Recovery | D42: 0.66002507 | E42: 0.79169184 | F42: =+D42-E42 -> -0.13166677 | G42: 0 | H42: =+D42-G42 -> 0.66002507 | I42: 0.57523997 | J42: =+D42-I42 -> 0.084785097 | L42: 0.66002507 | M42: 0.79169184 | N42: =+L42-M42 -> -0.13166677 | O42: 0 | P42: =+L42-O42 -> 0.66002507 | Q42: 0.57523997 | R42: =+L42-Q42 -> 0.084785097
A43: Installation Recovery% | B43: 1 | C43: Labour Recovery - Installation | D43: -531201555169280 | E43: 1.255 | F43: =+D43-E43 -> -5.3120156e+14 | G43: 0 | H43: =+D43-G43 -> -531201555169280 | I43: 0 | J43: =+D43-I43 -> -531201555169280 | L43: -531201555169280 | M43: 1.255 | N43: =+L43-M43 -> -5.3120156e+14 | O43: 0 | P43: =+L43-O43 -> -531201555169280 | Q43: 0 | R43: =+L43-Q43 -> -531201555169280
A44: Consumables Recovery% | B44: 1 | C44: Consumable Recovery | D44: 1.5781437 | E44: 1.255 | F44: =+D44-E44 -> 0.3231437 | G44: 0 | H44: =+D44-G44 -> 1.5781437 | I44: 1.2247514 | J44: =+D44-I44 -> 0.35339231 | L44: 1.5781437 | M44: 1.255 | N44: =+L44-M44 -> 0.3231437 | O44: 0 | P44: =+L44-O44 -> 1.5781437 | Q44: 1.2247514 | R44: =+L44-Q44 -> 0.35339231
A45: GM % | B45: 1 | C45: Gross Margin % | D45: 0.49005774 | E45: 0.62348287 | F45: =+D45-E45 -> -0.13342513 | G45: 0 | H45: =+D45-G45 -> 0.49005774 | I45: 0.60210035 | J45: =+D45-I45 -> -0.11204261 | L45: 0.49005774 | M45: 0.62348287 | N45: =+L45-M45 -> -0.13342513 | O45: 0 | P45: =+L45-O45 -> 0.49005774 | Q45: 0.60210035 | R45: =+L45-Q45 -> -0.11204261
A46: R&M % | B46: 1 | C46: R&M / Hire Revenue | D46: 0.38952569 | E46: 0.25389186 | F46: =+D46-E46 -> 0.13563383 | G46: 0 | H46: =+D46-G46 -> 0.38952569 | I46: 0.2583879 | J46: =+D46-I46 -> 0.13113778 | L46: 0.38952569 | M46: 0.25389186 | N46: =+L46-M46 -> 0.13563383 | O46: 0 | P46: =+L46-O46 -> 0.38952569 | Q46: 0.2583879 | R46: =+L46-Q46 -> 0.13113778
A47: EBITDA % | B47: 1 | C47: EBITDA / Revenue | D47: 0.17489738 | E47: 0.34684209 | F47: =+D47-E47 -> -0.17194471 | G47: 0 | H47: =+D47-G47 -> 0.17489738 | I47: 0.28189924 | J47: =+D47-I47 -> -0.10700186 | L47: 0.17489738 | M47: 0.34684209 | N47: =+L47-M47 -> -0.17194471 | O47: 0 | P47: =+L47-O47 -> 0.17489738 | Q47: 0.28189924 | R47: =+L47-Q47 -> -0.10700186
A48: EBIT % | B48: 1 | C48: EBIT / Revenue | D48: -0.025646193 | E48: 0.15823696 | F48: =+D48-E48 -> -0.18388315 | G48: 0 | H48: =+D48-G48 -> -0.025646193 | I48: 0.096264428 | J48: =+D48-I48 -> -0.12191062 | L48: -0.025646193 | M48: 0.15823696 | N48: =+L48-M48 -> -0.18388315 | O48: 0 | P48: =+L48-O48 -> -0.025646193 | Q48: 0.096264428 | R48: =+L48-Q48 -> -0.12191062
B49: 1
C50: TU | D50: =+'IS South'!E414 -> 0.5813282 | I50: =+'IS South'!J414 -> 0.58137083 | J50: =+D50-I50 -> -4.2630847e-05 | L50: =+'IS South'!M414 -> 0.5813282 | Q50: =+'IS South'!R414 -> 0.58137083 | R50: =+L50-Q50 -> -4.2630847e-05
C51: ROC | D51: =+'IS South'!E412 -> -0.01412281 | I51: =+'IS South'!J412 -> 0.058864489 | J51: =+D51-I51 -> -0.0729873 | L51: =+'IS South'!M412 -> -0.01412281 | Q51: =+'IS South'!R412 -> 0.058864489 | R51: =+L51-Q51 -> -0.0729873
C52: Redline | D52: =+'IS South'!E415 -> 0.28342001 | I52: =+'IS South'!J415 -> 0.16546929 | J52: =+D52-I52 -> 0.11795072 | L52: =+'IS South'!M415 -> 0.28342001 | Q52: =+'IS South'!R415 -> 0.16546929 | R52: =+L52-Q52 -> 0.11795072
C53: Fleet Original Cost | D53: =+'IS South'!E416 -> 21087.608 | I53: =+'IS South'!J416 -> 21054.093 | J53: =+D53-I53 -> 33.514924 | L53: =+'IS South'!M416 -> 21087.608 | Q53: =+'IS South'!R416 -> 21054.093 | R53: =+L53-Q53 -> 33.514924
C58: Check | D58: =D38-'IS South'!E410 -> 0 | E58: =E38-'IS South'!F410 -> 0 | F58: =F38-'IS South'!G410 -> 0 | G58: =G38-'IS South'!H410 -> 0 | H58: =H38-'IS South'!I410 -> 0 | I58: =I38-'IS South'!J410 -> 0 | J58: =J38-'IS South'!K410 -> 0 | K58: =K38-'IS South'!L410 -> 0 | ... R58: =R38-'IS South'!S410 -> 0

Sheet West
A1: CUBE: | C1: Coates:General Ledger | E1: Target Budget FY25 Copy
A2: Financial Entity | C2: All Financial Entities
A3: Plan Measure | C3: Total
D4: =+Parameters!$B$10 -> 2026 | E4: =+Parameters!$B$10 -> 2026 | G4: =+Parameters!$B$10 -> 2026 | I4: =+D4-1 -> 2025 | L4: =+D4 -> 2026 | M4: =+E4 -> 2026 | O4: =+G4 -> 2026 | Q4: =+I4 -> 2025
D5: =+Parameters!$B$9 -> Jul | E5: =+Parameters!$B$9 -> Jul | G5: =+Parameters!$B$9 -> Jul | I5: =+E5 -> Jul | L5: =CONCATENATE(D5," ","YTD") -> Jul YTD | M5: =CONCATENATE(E5," ","YTD") -> Jul YTD | O5: =CONCATENATE(G5," ","YTD") -> Jul YTD | Q5: =CONCATENATE(I5," ","YTD") -> Jul YTD
D6: =+Parameters!B5 -> Actual | E6: =+Parameters!$B$6 -> Target Budget | G6: =+Parameters!$B$7 -> Forecast Current | I6: =+D6 -> Actual | L6: =+D6 -> Actual | M6: =+E6 -> Target Budget | O6: =+G6 -> Forecast Current | Q6: =+I6 -> Actual
D7: =+Lists!I1 -> IS_WEST BU | E7: =+D7 -> IS_WEST BU | F7: =+E7 -> IS_WEST BU | G7: =+F7 -> IS_WEST BU | H7: =+G7 -> IS_WEST BU | I7: =+H7 -> IS_WEST BU | J7: =+I7 -> IS_WEST BU | K7: =+J7 -> IS_WEST BU | L7: =+K7 -> IS_WEST BU | ... R7: =+Q7 -> IS_WEST BU
C8: =+Group!$C$8 -> FINANCIAL YEAR 2027 | D8: West - Industrial Solutions
D10: =CONCATENATE($D$5," ","MTD") -> Jul MTD | L10: =CONCATENATE($D$5," ","YTD") -> Jul YTD
D11: Actual | E11: Budget | F11: Var Bud | G11: Forecast | H11: Var Forecast | I11: Last Year | J11: Var LY | L11: Actual | M11: Budget | N11: Var Bud | O11: Forecast | P11: Var Forecast | Q11: Last Year | R11: Var LY
A12: Hire Revenue | B12: -1 | C12: Hire Revenue | D12: 1207307.5 | E12: 1368532.3 | F12: =+D12-E12 -> -161224.84 | G12: 0 | H12: =+D12-G12 -> 1207307.5 | I12: 983381.41 | J12: =+D12-I12 -> 223926.09 | L12: 1207307.5 | M12: 1368532.3 | N12: =+L12-M12 -> -161224.84 | O12: 0 | P12: =+L12-O12 -> 1207307.5 | Q12: 983381.41 | R12: =+L12-Q12 -> 223926.09
A13: Rehire Revenue | B13: -1 | C13: Rehire Revenue | D13: 899605.44 | E13: 426735.14 | F13: =+D13-E13 -> 472870.3 | G13: 0 | H13: =+D13-G13 -> 899605.44 | I13: 337729.88 | J13: =+D13-I13 -> 561875.56 | L13: 899605.44 | M13: 426735.14 | N13: =+L13-M13 -> 472870.3 | O13: 0 | P13: =+L13-O13 -> 899605.44 | Q13: 337729.88 | R13: =+L13-Q13 -> 561875.56
A14: Transport | B14: -1 | C14: Transport Revenue | D14: 174264.93 | E14: 134573 | F14: =+D14-E14 -> 39691.933 | G14: 0 | H14: =+D14-G14 -> 174264.93 | I14: 92540.49 | J14: =+D14-I14 -> 81724.44 | L14: 174264.93 | M14: 134573 | N14: =+L14-M14 -> 39691.933 | O14: 0 | P14: =+L14-O14 -> 174264.93 | Q14: 92540.49 | R14: =+L14-Q14 -> 81724.44
A15: Other Revenue. | B15: -1 | C15: Other Revenue | D15: 656002.38 | E15: 952243.52 | F15: =+D15-E15 -> -296241.14 | G15: 0 | H15: =+D15-G15 -> 656002.38 | I15: 575410.84 | J15: =+D15-I15 -> 80591.54 | L15: 656002.38 | M15: 952243.52 | N15: =+L15-M15 -> -296241.14 | O15: 0 | P15: =+L15-O15 -> 656002.38 | Q15: 575410.84 | R15: =+L15-Q15 -> 80591.54
A16: Total Combined Revenue | B16: -1 | C16: Total Revenue | D16: 2937180.2 | E16: 2882084 | F16: =+D16-E16 -> 55096.25 | G16: 0 | H16: =+D16-G16 -> 2937180.2 | I16: 1989062.6 | J16: =+D16-I16 -> 948117.63 | L16: 2937180.2 | M16: 2882084 | N16: =+L16-M16 -> 55096.25 | O16: 0 | P16: =+L16-O16 -> 2937180.2 | Q16: 1989062.6 | R16: =+L16-Q16 -> 948117.63 | T16: =D16/E16 -> 1.0191168
A17: Total Repairs & Maintenance | B17: 1 | C17: Total Repairs & Maint | D17: 239713.13 | E17: 206675.14 | F17: =+D17-E17 -> 33037.994 | G17: 0 | H17: =+D17-G17 -> 239713.13 | I17: 178152.33 | J17: =+D17-I17 -> 61560.8 | L17: 239713.13 | M17: 206675.14 | N17: =+L17-M17 -> 33037.994 | O17: 0 | P17: =+L17-O17 -> 239713.13 | Q17: 178152.33 | R17: =+L17-Q17 -> 61560.8
A18: Transport Expenses (Stat) | B18: 1 | C18: Transport | D18: 150100.24 | E18: 104709.07 | F18: =+D18-E18 -> 45391.174 | G18: 0 | H18: =+D18-G18 -> 150100.24 | I18: 88634.83 | J18: =+D18-I18 -> 61465.41 | L18: 150100.24 | M18: 104709.07 | N18: =+L18-M18 -> 45391.174 | O18: 0 | P18: =+L18-O18 -> 150100.24 | Q18: 88634.83 | R18: =+L18-Q18 -> 61465.41
A19: Rehire Expenses | B19: 1 | C19: Rehire | D19: 697268.29 | E19: 379231.45 | F19: =+D19-E19 -> 318036.84 | G19: 0 | H19: =+D19-G19 -> 697268.29 | I19: 307029.18 | J19: =+D19-I19 -> 390239.11 | L19: 697268.29 | M19: 379231.45 | N19: =+L19-M19 -> 318036.84 | O19: 0 | P19: =+L19-O19 -> 697268.29 | Q19: 307029.18 | R19: =+L19-Q19 -> 390239.11
A20: Profit/Loss on Sale of Asset | B20: 1 | C20: POSA | D20: 0 | E20: 0 | F20: =+D20-E20 -> 0 | G20: 0 | H20: =+D20-G20 -> 0 | I20: 0 | J20: =+D20-I20 -> 0 | L20: 0 | M20: 0 | N20: =+L20-M20 -> 0 | O20: 0 | P20: =+L20-O20 -> 0 | Q20: 0 | R20: =+L20-Q20 -> 0
A21: Other Direct Costs | B21: 1 | C21: Other Direct Costs | D21: 565377.24 | E21: 784046.36 | F21: =+D21-E21 -> -218669.12 | G21: 0 | H21: =+D21-G21 -> 565377.24 | I21: 507255.48 | J21: =+D21-I21 -> 58121.76 | L21: 565377.24 | M21: 784046.36 | N21: =+L21-M21 -> -218669.12 | O21: 0 | P21: =+L21-O21 -> 565377.24 | Q21: 507255.48 | R21: =+L21-Q21 -> 58121.76
A22: Total Combined Direct Costs (Stat) | B22: 1 | C22: Total Direct Costs | D22: 1652458.9 | E22: 1474662 | F22: =+D22-E22 -> 177796.89 | G22: 0 | H22: =+D22-G22 -> 1652458.9 | I22: 1081071.8 | J22: =+D22-I22 -> 571387.08 | L22: 1652458.9 | M22: 1474662 | N22: =+L22-M22 -> 177796.89 | O22: 0 | P22: =+L22-O22 -> 1652458.9 | Q22: 1081071.8 | R22: =+L22-Q22 -> 571387.08 | T22: =D22/E22 -> 1.1205679
A23: Gross Margin - Post Allocations (Stat) | B23: -1 | C23: Gross Margin | D23: 1284721.4 | E23: 1407422 | F23: =+D23-E23 -> -122700.64 | G23: 0 | H23: =+D23-G23 -> 1284721.4 | I23: 907990.8 | J23: =+D23-I23 -> 376730.55 | L23: 1284721.4 | M23: 1407422 | N23: =+L23-M23 -> -122700.64 | O23: 0 | P23: =+L23-O23 -> 1284721.4 | Q23: 907990.8 | R23: =+L23-Q23 -> 376730.55 | T23: =+D23/D16 -> 0.43739956 | U23: =+E23/E16 -> 0.48833483
A24: Property (Stat) | B24: 1 | C24: Property | D24: 52313.87 | E24: 40452.74 | F24: =+D24-E24 -> 11861.13 | G24: 0 | H24: =+D24-G24 -> 52313.87 | I24: 33238.5 | J24: =+D24-I24 -> 19075.37 | L24: 52313.87 | M24: 40452.74 | N24: =+L24-M24 -> 11861.13 | O24: 0 | P24: =+L24-O24 -> 52313.87 | Q24: 33238.5 | R24: =+L24-Q24 -> 19075.37
A25: Direct Staff Costs (Stat) | B25: 1 | C25: Direct Staff | D25: 163515.44 | E25: 160692.2 | F25: =+D25-E25 -> 2823.2387 | G25: 0 | H25: =+D25-G25 -> 163515.44 | I25: 162840.73 | J25: =+D25-I25 -> 674.71 | L25: 163515.44 | M25: 160692.2 | N25: =+L25-M25 -> 2823.2387 | O25: 0 | P25: =+L25-O25 -> 163515.44 | Q25: 162840.73 | R25: =+L25-Q25 -> 674.71
A26: Indirect Staff Costs | B26: 1 | C26: Indirect Staff | D26: 9527.61 | E26: 8407.0342 | F26: =+D26-E26 -> 1120.5758 | G26: 0 | H26: =+D26-G26 -> 9527.61 | I26: 16321.23 | J26: =+D26-I26 -> -6793.62 | L26: 9527.61 | M26: 8407.0342 | N26: =+L26-M26 -> 1120.5758 | O26: 0 | P26: =+L26-O26 -> 9527.61 | Q26: 16321.23 | R26: =+L26-Q26 -> -6793.62
A27: Marketing and Entertainment (BUFR) | B27: 1 | C27: Marketing/Entertainment | D27: 0 | E27: 44.5525 | F27: =+D27-E27 -> -44.5525 | G27: 0 | H27: =+D27-G27 -> 0 | I27: 15.68 | J27: =+D27-I27 -> -15.68 | L27: 0 | M27: 44.5525 | N27: =+L27-M27 -> -44.5525 | O27: 0 | P27: =+L27-O27 -> 0 | Q27: 15.68 | R27: =+L27-Q27 -> -15.68
A28: Telecommunications | B28: 1 | C28: Telecommunications | D28: 3528.76 | E28: 3268.3283 | F28: =+D28-E28 -> 260.43167 | G28: 0 | H28: =+D28-G28 -> 3528.76 | I28: 3847.22 | J28: =+D28-I28 -> -318.46 | L28: 3528.76 | M28: 3268.3283 | N28: =+L28-M28 -> 260.43167 | O28: 0 | P28: =+L28-O28 -> 3528.76 | Q28: 3847.22 | R28: =+L28-Q28 -> -318.46
A29: IT & EDP Expenses | B29: 1 | C29: IT&EDP | D29: 1027 | E29: 780.69083 | F29: =+D29-E29 -> 246.30917 | G29: 0 | H29: =+D29-G29 -> 1027 | I29: 570 | J29: =+D29-I29 -> 457 | L29: 1027 | M29: 780.69083 | N29: =+L29-M29 -> 246.30917 | O29: 0 | P29: =+L29-O29 -> 1027 | Q29: 570 | R29: =+L29-Q29 -> 457
A30: Travel & Accomodation Expense | B30: 1 | C30: Travel & Accommodation | D30: 2402.01 | E30: 4771.6225 | F30: =+D30-E30 -> -2369.6125 | G30: 0 | H30: =+D30-G30 -> 2402.01 | I30: 5165.94 | J30: =+D30-I30 -> -2763.93 | L30: 2402.01 | M30: 4771.6225 | N30: =+L30-M30 -> -2369.6125 | O30: 0 | P30: =+L30-O30 -> 2402.01 | Q30: 5165.94 | R30: =+L30-Q30 -> -2763.93
A31: Bad Debts | B31: 1 | C31: Bad Debts | D31: 5115.35 | E31: 4481.5981 | F31: =+D31-E31 -> 633.7519 | G31: 0 | H31: =+D31-G31 -> 5115.35 | I31: 3420.47 | J31: =+D31-I31 -> 1694.88 | L31: 5115.35 | M31: 4481.5981 | N31: =+L31-M31 -> 633.7519 | O31: 0 | P31: =+L31-O31 -> 5115.35 | Q31: 3420.47 | R31: =+L31-Q31 -> 1694.88
A32: Branch Admin (Stat) | B32: 1 | C32: Total Branch Administration | D32: 8287.91 | E32: 7335.9809 | F32: =+D32-E32 -> 951.92913 | G32: 0 | H32: =+D32-G32 -> 8287.91 | I32: 10464.9 | J32: =+D32-I32 -> -2176.99 | L32: 8287.91 | M32: 7335.9809 | N32: =+L32-M32 -> 951.92913 | O32: 0 | P32: =+L32-O32 -> 8287.91 | Q32: 10464.9 | R32: =+L32-Q32 -> -2176.99
A33: Statutory Cost | B33: 1 | C33: Statutory | D33: 1398.1 | E33: 1398.0992 | F33: =+D33-E33 -> 0.00083333333 | G33: 0 | H33: =+D33-G33 -> 1398.1 | I33: 1399.47 | J33: =+D33-I33 -> -1.37 | L33: 1398.1 | M33: 1398.0992 | N33: =+L33-M33 -> 0.00083333333 | O33: 0 | P33: =+L33-O33 -> 1398.1 | Q33: 1399.47 | R33: =+L33-Q33 -> -1.37
A34: Shared services & Allocated Costs | B34: 1 | C34: Shared services & Allocated Costs | D34: 334577.21 | E34: 333025.91 | F34: =+D34-E34 -> 1551.3 | G34: 0 | H34: =+D34-G34 -> 334577.21 | I34: 261188 | J34: =+D34-I34 -> 73389.21 | L34: 334577.21 | M34: 333025.91 | N34: =+L34-M34 -> 1551.3 | O34: 0 | P34: =+L34-O34 -> 334577.21 | Q34: 261188 | R34: =+L34-Q34 -> 73389.21
A35: Total Combined Overheads (Stat) | B35: 1 | C35: Total Overheads | D35: 581693.26 | E35: 564658.76 | F35: =+D35-E35 -> 17034.502 | G35: 0 | H35: =+D35-G35 -> 581693.26 | I35: 498472.14 | J35: =+D35-I35 -> 83221.12 | L35: 581693.26 | M35: 564658.76 | N35: =+L35-M35 -> 17034.502 | O35: 0 | P35: =+L35-O35 -> 581693.26 | Q35: 498472.14 | R35: =+L35-Q35 -> 83221.12
... A38: EBIT - Post Allocations (Stat) | B38: -1 | C38: EBIT | D38: 401398.93 | E38: 522809.95 | F38: =+D38-E38 -> -121411.02 | G38: 0 | H38: =+D38-G38 -> 401398.93 | I38: 145222.38 | J38: =+D38-I38 -> 256176.55 | L38: 401398.93 | M38: 522809.95 | N38: =+L38-M38 -> -121411.02 | O38: 0 | P38: =+L38-O38 -> 401398.93 | Q38: 145222.38 | R38: =+L38-Q38 -> 256176.55
P39: =+L39-O39 -> 0
B40: 1 | C40: Profit and Loss KPI Ratios | P40: =+L40-O40 -> 0
A41: Rehire Recovery % | B41: 1 | C41: Rehire Recovery | D41: 1.2901855 | E41: 1.125263 | F41: =+D41-E41 -> 0.16492245 | G41: 0 | H41: =+D41-G41 -> 1.2901855 | I41: 1.0999928 | J41: =+D41-I41 -> 0.19019273 | L41: 1.2901855 | M41: 1.125263 | N41: =+L41-M41 -> 0.16492245 | O41: 0 | P41: =+L41-O41 -> 1.2901855 | Q41: 1.0999928 | R41: =+L41-Q41 -> 0.19019273
A42: Transport Recovery % | B42: 1 | C42: Transport Recovery | D42: 1.1609903 | E42: 1.2852086 | F42: =+D42-E42 -> -0.12421829 | G42: 0 | H42: =+D42-G42 -> 1.1609903 | I42: 1.0403906 | J42: =+D42-I42 -> 0.12059971 | L42: 1.1609903 | M42: 1.2852086 | N42: =+L42-M42 -> -0.12421829 | O42: 0 | P42: =+L42-O42 -> 1.1609903 | Q42: 1.0403906 | R42: =+L42-Q42 -> 0.12059971
A43: Installation Recovery% | B43: 1 | C43: Labour Recovery - Installation | D43: 1.1990694 | E43: 1.1014435 | F43: =+D43-E43 -> 0.097625895 | G43: 0 | H43: =+D43-G43 -> 1.1990694 | I43: 0.9914883 | J43: =+D43-I43 -> 0.20758108 | L43: 1.1990694 | M43: 1.1014435 | N43: =+L43-M43 -> 0.097625895 | O43: 0 | P43: =+L43-O43 -> 1.1990694 | Q43: 0.9914883 | R43: =+L43-Q43 -> 0.20758108
A44: Consumables Recovery% | B44: 1 | C44: Consumable Recovery | D44: 1.0992629 | E44: 1.2323388 | F44: =+D44-E44 -> -0.13307588 | G44: 0 | H44: =+D44-G44 -> 1.0992629 | I44: 1.2582291 | J44: =+D44-I44 -> -0.15896619 | L44: 1.0992629 | M44: 1.2323388 | N44: =+L44-M44 -> -0.13307588 | O44: 0 | P44: =+L44-O44 -> 1.0992629 | Q44: 1.2582291 | R44: =+L44-Q44 -> -0.15896619
A45: GM % | B45: 1 | C45: Gross Margin % | D45: 0.43739956 | E45: 0.48833483 | F45: =+D45-E45 -> -0.050935265 | G45: 0 | H45: =+D45-G45 -> 0.43739956 | I45: 0.45649181 | J45: =+D45-I45 -> -0.019092252 | L45: 0.43739956 | M45: 0.48833483 | N45: =+L45-M45 -> -0.050935265 | O45: 0 | P45: =+L45-O45 -> 0.43739956 | Q45: 0.45649181 | R45: =+L45-Q45 -> -0.019092252
A46: R&M % | B46: 1 | C46: R&M / Hire Revenue | D46: 0.19746599 | E46: 0.15093617 | F46: =+D46-E46 -> 0.046529822 | G46: 0 | H46: =+D46-G46 -> 0.19746599 | I46: 0.18104749 | J46: =+D46-I46 -> 0.016418499 | L46: 0.19746599 | M46: 0.15093617 | N46: =+L46-M46 -> 0.046529822 | O46: 0 | P46: =+L46-O46 -> 0.19746599 | Q46: 0.18104749 | R46: =+L46-Q46 -> 0.016418499
A47: EBITDA % | B47: 1 | C47: EBITDA / Revenue | D47: 0.23935477 | E47: 0.29241453 | F47: =+D47-E47 -> -0.053059761 | G47: 0 | H47: =+D47-G47 -> 0.23935477 | I47: 0.20588525 | J47: =+D47-I47 -> 0.033469513 | L47: 0.23935477 | M47: 0.29241453 | N47: =+L47-M47 -> -0.053059761 | O47: 0 | P47: =+L47-O47 -> 0.23935477 | Q47: 0.20588525 | R47: =+L47-Q47 -> 0.033469513
A48: EBIT % | B48: 1 | C48: EBIT / Revenue | D48: 0.13666132 | E48: 0.18139997 | F48: =+D48-E48 -> -0.044738651 | G48: 0 | H48: =+D48-G48 -> 0.13666132 | I48: 0.073010462 | J48: =+D48-I48 -> 0.063650858 | L48: 0.13666132 | M48: 0.18139997 | N48: =+L48-M48 -> -0.044738651 | O48: 0 | P48: =+L48-O48 -> 0.13666132 | Q48: 0.073010462 | R48: =+L48-Q48 -> 0.063650858
B49: 1
C50: TU | D50: ='IS West'!E414 -> 0.77334334 | I50: ='IS West'!J414 -> 0.81010638 | J50: =+D50-I50 -> -0.036763044 | L50: ='IS West'!M414 -> 0.77334334 | Q50: ='IS West'!R414 -> 0.81010638 | R50: =+L50-Q50 -> -0.036763044
C51: ROC | D51: ='IS West'!E412 -> 0.14241071 | I51: ='IS West'!J412 -> 0.054355711 | J51: =+D51-I51 -> 0.088055002 | L51: ='IS West'!M412 -> 0.14241071 | Q51: ='IS West'!R412 -> 0.054355711 | R51: =+L51-Q51 -> 0.088055002
C52: Redline | D52: ='IS West'!E415 -> 0.12668332 | I52: ='IS West'!J415 -> 0.14505191 | J52: =+D52-I52 -> -0.018368594 | L52: ='IS West'!M415 -> 0.12668332 | Q52: ='IS West'!R415 -> 0.14505191 | R52: =+L52-Q52 -> -0.018368594
C53: Fleet Original Cost | D53: ='IS West'!E416 -> 34665.535 | I53: ='IS West'!J416 -> 31519.372 | J53: =+D53-I53 -> 3146.1631 | L53: ='IS West'!M416 -> 34665.535 | Q53: ='IS West'!R416 -> 31519.372 | R53: =+L53-Q53 -> 3146.1631
C58: Check | D58: =D38-'IS West'!E410 -> 0 | E58: =E38-'IS West'!F410 -> 0 | F58: =F38-'IS West'!G410 -> 0 | G58: =G38-'IS West'!H410 -> 0 | H58: =H38-'IS West'!I410 -> 0 | I58: =I38-'IS West'!J410 -> 0 | J58: =J38-'IS West'!K410 -> 0 | K58: =K38-'IS West'!L410 -> 0 | ... R58: =R38-'IS West'!S410 -> 0

Sheet BU MTD YTD
A8: =+Group!$C$8 -> FINANCIAL YEAR 2027 | B8: North | D8: South | F8: West | H8: East | K8: =+Group!$C$8 -> FINANCIAL YEAR 2027 | L8: North | N8: South | P8: West | R8: East
B10: =+Group!D10 -> Jul MTD | L10: =+Group!L10 -> Jul YTD
B11: Actual | C11: Variance | D11: Actual | E11: Variance | F11: Actual | G11: Variance | H11: Actual | I11: Variance | L11: Actual | M11: Variance | N11: Actual | O11: Variance | P11: Actual | Q11: Variance | R11: Actual | S11: Variance
A12: Hire Revenue | B12: =+North!D12 -> 792502.63 | C12: =+North!F12 -> 32008.65 | D12: =+South!D12 -> 824679.96 | E12: =+South!F12 -> -103743.16 | F12: =+West!D12 -> 1207307.5 | G12: =+West!F12 -> -161224.84 | H12: =+East!D12 -> 295833.71 | I12: =+East!F12 -> -46564.423 | K12: Hire Revenue | L12: =+North!L12 -> 792502.63 | M12: =+North!N12 -> 32008.65 | N12: =+South!L12 -> 824679.96 | O12: =+South!N12 -> -103743.16 | P12: =+West!L12 -> 1207307.5 | Q12: =+West!N12 -> -161224.84 | R12: =+East!L12 -> 295833.71 | S12: =+East!N12 -> -46564.423
A13: Rehire Revenue | B13: =+North!D13 -> 164876.21 | C13: =+North!F13 -> 41931.4 | D13: =+South!D13 -> 25414.28 | E13: =+South!F13 -> 10164.499 | F13: =+West!D13 -> 899605.44 | G13: =+West!F13 -> 472870.3 | H13: =+East!D13 -> 31460.19 | I13: =+East!F13 -> -26733.028 | K13: Rehire Revenue | L13: =+North!L13 -> 164876.21 | M13: =+North!N13 -> 41931.4 | N13: =+South!L13 -> 25414.28 | O13: =+South!N13 -> 10164.499 | P13: =+West!L13 -> 899605.44 | Q13: =+West!N13 -> 472870.3 | R13: =+East!L13 -> 31460.19 | S13: =+East!N13 -> -26733.028
A14: Transport Revenue | B14: =+North!D14 -> 196906.03 | C14: =+North!F14 -> 93595.829 | D14: =+South!D14 -> 38125.82 | E14: =+South!F14 -> 12520.895 | F14: =+West!D14 -> 174264.93 | G14: =+West!F14 -> 39691.933 | H14: =+East!D14 -> 34016.74 | I14: =+East!F14 -> -16401.944 | K14: Transport Revenue | L14: =+North!L14 -> 196906.03 | M14: =+North!N14 -> 93595.829 | N14: =+South!L14 -> 38125.82 | O14: =+South!N14 -> 12520.895 | P14: =+West!L14 -> 174264.93 | Q14: =+West!N14 -> 39691.933 | R14: =+East!L14 -> 34016.74 | S14: =+East!N14 -> -16401.944
A15: Other Revenue | B15: =+North!D15 -> 225330.46 | C15: =+North!F15 -> 52256.119 | D15: =+South!D15 -> 85649.64 | E15: =+South!F15 -> -24794.534 | F15: =+West!D15 -> 656002.38 | G15: =+West!F15 -> -296241.14 | H15: =+East!D15 -> 39410.3 | I15: =+East!F15 -> -45166.844 | K15: Other Revenue | L15: =+North!L15 -> 225330.46 | M15: =+North!N15 -> 52256.119 | N15: =+South!L15 -> 85649.64 | O15: =+South!N15 -> -24794.534 | P15: =+West!L15 -> 656002.38 | Q15: =+West!N15 -> -296241.14 | R15: =+East!L15 -> 39410.3 | S15: =+East!N15 -> -45166.844
A16: Total Revenue | B16: =+North!D16 -> 1379615.3 | C16: =+North!F16 -> 219792 | D16: =+South!D16 -> 973869.7 | E16: =+South!F16 -> -105852.3 | F16: =+West!D16 -> 2937180.2 | G16: =+West!F16 -> 55096.25 | H16: =+East!D16 -> 400720.94 | I16: =+East!F16 -> -134866.24 | K16: Total Revenue | L16: =+North!L16 -> 1379615.3 | M16: =+North!N16 -> 219792 | N16: =+South!L16 -> 973869.7 | O16: =+South!N16 -> -105852.3 | P16: =+West!L16 -> 2937180.2 | Q16: =+West!N16 -> 55096.25 | R16: =+East!L16 -> 400720.94 | S16: =+East!N16 -> -134866.24
A17: Total Repairs & Maint | B17: =+North!D17 -> 188830.04 | C17: =+North!F17 -> 39464.864 | D17: =+South!D17 -> 321364.07 | E17: =+South!F17 -> 85538.588 | F17: =+West!D17 -> 239713.13 | G17: =+West!F17 -> 33037.994 | H17: =+East!D17 -> 83582.93 | I17: =+East!F17 -> 21277.967 | K17: Total Repairs & Maint | L17: =+North!L17 -> 188830.04 | M17: =+North!N17 -> 39464.864 | N17: =+South!L17 -> 321364.07 | O17: =+South!N17 -> 85538.588 | P17: =+West!L17 -> 239713.13 | Q17: =+West!N17 -> 33037.994 | R17: =+East!L17 -> 83582.93 | S17: =+East!N17 -> 21277.967
A18: Transport | B18: =+North!D18 -> 177517.12 | C18: =+North!F18 -> 87038.238 | D18: =+South!D18 -> 57764.2 | E18: =+South!F18 -> 25422.166 | F18: =+West!D18 -> 150100.24 | G18: =+West!F18 -> 45391.174 | H18: =+East!D18 -> 32645.06 | I18: =+East!F18 -> -14001.347 | K18: Transport | L18: =+North!L18 -> 177517.12 | M18: =+North!N18 -> 87038.238 | N18: =+South!L18 -> 57764.2 | O18: =+South!N18 -> 25422.166 | P18: =+West!L18 -> 150100.24 | Q18: =+West!N18 -> 45391.174 | R18: =+East!L18 -> 32645.06 | S18: =+East!N18 -> -14001.347
A19: Rehire | B19: =+North!D19 -> 140650.11 | C19: =+North!F19 -> 45961.955 | D19: =+South!D19 -> 25105.97 | E19: =+South!F19 -> 14134.904 | F19: =+West!D19 -> 697268.29 | G19: =+West!F19 -> 318036.84 | H19: =+East!D19 -> 32658.08 | I19: =+East!F19 -> -12452.942 | K19: Rehire | L19: =+North!L19 -> 140650.11 | M19: =+North!N19 -> 45961.955 | N19: =+South!L19 -> 25105.97 | O19: =+South!N19 -> 14134.904 | P19: =+West!L19 -> 697268.29 | Q19: =+West!N19 -> 318036.84 | R19: =+East!L19 -> 32658.08 | S19: =+East!N19 -> -12452.942
A20: POSA | B20: =+North!D20 -> 0 | C20: =+North!F20 -> 0 | D20: =+South!D20 -> 0 | E20: =+South!F20 -> 0 | F20: =+West!D20 -> 0 | G20: =+West!F20 -> 0 | H20: =+East!D20 -> 0 | I20: =+East!F20 -> 0 | K20: POSA | L20: =+North!L20 -> 0 | M20: =+North!N20 -> 0 | N20: =+South!L20 -> 0 | O20: =+South!N20 -> 0 | P20: =+West!L20 -> 0 | Q20: =+West!N20 -> 0 | R20: =+East!L20 -> 0 | S20: =+East!N20 -> 0
A21: Other Direct Costs | B21: =+North!D21 -> 140188.56 | C21: =+North!F21 -> 18559.574 | D21: =+South!D21 -> 92383.08 | E21: =+South!F21 -> -35012.172 | F21: =+West!D21 -> 565377.24 | G21: =+West!F21 -> -218669.12 | H21: =+East!D21 -> 39481.51 | I21: =+East!F21 -> -33993.086 | K21: Other Direct Costs | L21: =+North!L21 -> 140188.56 | M21: =+North!N21 -> 18559.574 | N21: =+South!L21 -> 92383.08 | O21: =+South!N21 -> -35012.172 | P21: =+West!L21 -> 565377.24 | Q21: =+West!N21 -> -218669.12 | R21: =+East!L21 -> 39481.51 | S21: =+East!N21 -> -33993.086
A22: Total Direct Costs | B22: =+North!D22 -> 647185.83 | C22: =+North!F22 -> 191024.63 | D22: =+South!D22 -> 496617.32 | E22: =+South!F22 -> 90083.486 | F22: =+West!D22 -> 1652458.9 | G22: =+West!F22 -> 177796.89 | H22: =+East!D22 -> 188367.58 | I22: =+East!F22 -> -39169.408 | K22: Total Direct Costs | L22: =+North!L22 -> 647185.83 | M22: =+North!N22 -> 191024.63 | N22: =+South!L22 -> 496617.32 | O22: =+South!N22 -> 90083.486 | P22: =+West!L22 -> 1652458.9 | Q22: =+West!N22 -> 177796.89 | R22: =+East!L22 -> 188367.58 | S22: =+East!N22 -> -39169.408
A23: Gross Margin | B23: =+North!D23 -> 732429.5 | C23: =+North!F23 -> 28767.366 | D23: =+South!D23 -> 477252.38 | E23: =+South!F23 -> -195935.79 | F23: =+West!D23 -> 1284721.4 | G23: =+West!F23 -> -122700.64 | H23: =+East!D23 -> 212353.36 | I23: =+East!F23 -> -95696.83 | K23: Gross Margin | L23: =+North!L23 -> 732429.5 | M23: =+North!N23 -> 28767.366 | N23: =+South!L23 -> 477252.38 | O23: =+South!N23 -> -195935.79 | P23: =+West!L23 -> 1284721.4 | Q23: =+West!N23 -> -122700.64 | R23: =+East!L23 -> 212353.36 | S23: =+East!N23 -> -95696.83
... A38: EBIT | B38: =+North!D38 -> 297551.26 | C38: =+North!F38 -> 59716.882 | D38: =+South!D38 -> -24976.05 | E38: =+South!F38 -> -195827.98 | F38: =+West!D38 -> 401398.93 | G38: =+West!F38 -> -121411.02 | H38: =+East!D38 -> 36854.15 | I38: =+East!F38 -> -70503.393 | K38: EBIT | L38: =+North!L38 -> 297551.26 | M38: =+North!N38 -> 59716.882 | N38: =+South!L38 -> -24976.05 | O38: =+South!N38 -> -195827.98 | P38: =+West!L38 -> 401398.93 | Q38: =+West!N38 -> -121411.02 | R38: =+East!L38 -> 36854.15 | S38: =+East!N38 -> -70503.393
A40: Profit and Loss KPI Ratios | K40: Profit and Loss KPI Ratios
A41: Rehire Recovery | B41: =+North!D41 -> 1.1722437 | C41: =+North!F41 -> -0.12617433 | D41: =+South!D41 -> 1.0122803 | E41: =+South!F41 -> -0.37771965 | F41: =+West!D41 -> 1.2901855 | G41: =+West!F41 -> 0.16492245 | H41: =+East!D41 -> 0.96332026 | I41: =+East!F41 -> -0.32667974 | K41: Rehire Recovery | L41: =+North!L41 -> 1.1722437 | M41: =+North!N41 -> -0.12617433 | N41: =+South!L41 -> 1.0122803 | O41: =+South!N41 -> -0.37771965 | P41: =+West!L41 -> 1.2901855 | Q41: =+West!N41 -> 0.16492245 | R41: =+East!L41 -> 0.96332026 | S41: =+East!N41 -> -0.32667974
A42: Transport Recovery | B42: =+North!D42 -> 1.1092228 | C42: =+North!F42 -> -0.032592853 | D42: =+South!D42 -> 0.66002507 | E42: =+South!F42 -> -0.13166677 | F42: =+West!D42 -> 1.1609903 | G42: =+West!F42 -> -0.12421829 | H42: =+East!D42 -> 1.042018 | I42: =+East!F42 -> -0.038851604 | K42: Transport Recovery | L42: =+North!L42 -> 1.1092228 | M42: =+North!N42 -> -0.032592853 | N42: =+South!L42 -> 0.66002507 | O42: =+South!N42 -> -0.13166677 | P42: =+West!L42 -> 1.1609903 | Q42: =+West!N42 -> -0.12421829 | R42: =+East!L42 -> 1.042018 | S42: =+East!N42 -> -0.038851604
A43: Labour Recovery - Installation | B43: =+North!D43 -> 1.2454228 | C43: =+North!F43 -> -0.055136995 | D43: =+South!D43 -> -531201555169280 | E43: =+South!F43 -> -5.3120156e+14 | F43: =+West!D43 -> 1.1990694 | G43: =+West!F43 -> 0.097625895 | H43: =+East!D43 -> 0 | I43: =+East!F43 -> -1.28 | K43: Labour Recovery - Installation | L43: =+North!L43 -> 1.2454228 | M43: =+North!N43 -> -0.055136995 | N43: =+South!L43 -> -531201555169280 | O43: =+South!N43 -> -5.3120156e+14 | P43: =+West!L43 -> 1.1990694 | Q43: =+West!N43 -> 0.097625895 | R43: =+East!L43 -> 0 | S43: =+East!N43 -> -1.28
A44: Consumable Recovery | B44: =+North!D44 -> 1.1759449 | C44: =+North!F44 -> -0.023601812 | D44: =+South!D44 -> 1.5781437 | E44: =+South!F44 -> 0.3231437 | F44: =+West!D44 -> 1.0992629 | G44: =+West!F44 -> -0.13307588 | H44: =+East!D44 -> 0.65410447 | I44: =+East!F44 -> -0.61589553 | K44: Consumable Recovery | L44: =+North!L44 -> 1.1759449 | M44: =+North!N44 -> -0.023601812 | N44: =+South!L44 -> 1.5781437 | O44: =+South!N44 -> 0.3231437 | P44: =+West!L44 -> 1.0992629 | Q44: =+West!N44 -> -0.13307588 | R44: =+East!L44 -> 0.65410447 | S44: =+East!N44 -> -0.61589553
A45: Gross Margin % | B45: =+North!D45 -> 0.530894 | C45: =+North!F45 -> -0.075803688 | D45: =+South!D45 -> 0.49005774 | E45: =+South!F45 -> -0.13342513 | F45: =+West!D45 -> 0.43739956 | G45: =+West!F45 -> -0.050935265 | H45: =+East!D45 -> 0.52992828 | I45: =+East!F45 -> -0.045235205 | K45: Gross Margin % | L45: =+North!L45 -> 0.530894 | M45: =+North!N45 -> -0.075803688 | N45: =+South!L45 -> 0.49005774 | O45: =+South!N45 -> -0.13342513 | P45: =+West!L45 -> 0.43739956 | Q45: =+West!N45 -> -0.050935265 | R45: =+East!L45 -> 0.52992828 | S45: =+East!N45 -> -0.045235205
A46: R&M / Hire Revenue | B46: =+North!D46 -> 0.23767438 | C46: =+North!F46 -> 0.041975577 | D46: =+South!D46 -> 0.38952569 | E46: =+South!F46 -> 0.13563383 | F46: =+West!D46 -> 0.19746599 | G46: =+West!F46 -> 0.046529822 | H46: =+East!D46 -> 0.28114579 | I46: =+East!F46 -> 0.099834811 | K46: R&M / Hire Revenue | L46: =+North!L46 -> 0.23767438 | M46: =+North!N46 -> 0.041975577 | N46: =+South!L46 -> 0.38952569 | O46: =+South!N46 -> 0.13563383 | P46: =+West!L46 -> 0.19746599 | Q46: =+West!N46 -> 0.046529822 | R46: =+East!L46 -> 0.28114579 | S46: =+East!N46 -> 0.099834811
A47: EBITDA / Revenue | B47: =+North!D47 -> 0.3355579 | C47: =+North!F47 -> -0.010149854 | D47: =+South!D47 -> 0.17489738 | E47: =+South!F47 -> -0.17194471 | F47: =+West!D47 -> 0.23935477 | G47: =+West!F47 -> -0.053059761 | H47: =+East!D47 -> 0.15809096 | I47: =+East!F47 -> -0.1198984 | K47: EBITDA / Revenue | L47: =+North!L47 -> 0.3355579 | M47: =+North!N47 -> -0.010149854 | N47: =+South!L47 -> 0.17489738 | O47: =+South!N47 -> -0.17194471 | P47: =+West!L47 -> 0.23935477 | Q47: =+West!N47 -> -0.053059761 | R47: =+East!L47 -> 0.15809096 | S47: =+East!N47 -> -0.1198984
A48: EBIT / Revenue | B48: =+North!D48 -> 0.21567697 | C48: =+North!F48 -> 0.010616108 | D48: =+South!D48 -> -0.025646193 | E48: =+South!F48 -> -0.18388315 | F48: =+West!D48 -> 0.13666132 | G48: =+West!F48 -> -0.044738651 | H48: =+East!D48 -> 0.091969614 | I48: =+East!F48 -> -0.10847869 | K48: EBIT / Revenue | L48: =+North!L48 -> 0.21567697 | M48: =+North!N48 -> 0.010616108 | N48: =+South!L48 -> -0.025646193 | O48: =+South!N48 -> -0.18388315 | P48: =+West!L48 -> 0.13666132 | Q48: =+West!N48 -> -0.044738651 | R48: =+East!L48 -> 0.091969614 | S48: =+East!N48 -> -0.10847869
A50: TU | B50: =+North!D50 -> 0.68116805 | D50: =+South!D50 -> 0.5813282 | F50: =+West!D50 -> 0.77334334 | H50: =+East!D50 -> 0.16807618 | K50: TU | L50: =+North!L50 -> 0.68116805 | N50: =+South!L50 -> 0.5813282 | P50: =+West!L50 -> 0.77334334 | R50: =+East!L50 -> 0.16807618
A51: ROC | B51: =+North!D51 -> 0.16050758 | D51: =+South!D51 -> -0.01412281 | F51: =+West!D51 -> 0.14241071 | H51: =+East!D51 -> 0.10760836 | K51: ROC | L51: =+North!L51 -> 0.16050758 | N51: =+South!L51 -> -0.01412281 | P51: =+West!L51 -> 0.14241071 | R51: =+East!L51 -> 0.10760836
A52: Redline | B52: =+North!D52 -> 0.1550612 | D52: =+South!D52 -> 0.28342001 | F52: =+West!D52 -> 0.12668332 | H52: =+East!D52 -> 0.26044046 | K52: Redline | L52: =+North!L52 -> 0.1550612 | N52: =+South!L52 -> 0.28342001 | P52: =+West!L52 -> 0.12668332 | R52: =+East!L52 -> 0.26044046
A53: Fleet Original Cost | B53: =+North!D53 -> 22830.997 | D53: =+South!D53 -> 21087.608 | F53: =+West!D53 -> 34665.535 | H53: =+East!D53 -> 3930.661 | K53: Fleet Original Cost | L53: =+North!L53 -> 22830.997 | N53: =+South!L53 -> 21087.608 | P53: =+West!L53 -> 34665.535 | R53: =+East!L53 -> 3930.661
A56: check>> | B56: =+Group!D38-East!D38-North!D38-South!D38-West!D38 -> 8.1490725e-10 | C56: =+Group!F38-East!F38-North!F38-South!F38-West!F38 -> -6.4028427e-10 | L56: =+Group!L38-East!L38-North!L38-South!L38-West!L38 -> 8.1490725e-10 | M56: =+Group!N38-East!N38-North!N38-South!N38-West!N38 -> -6.4028427e-10

Sheet Detailed P&L>>

Sheet IS Total
E1: 2 | F1: 2 | J1: 1
E2: =+Lists!A1 -> IS | F2: =+E2 -> IS | G2: =+F2 -> IS | H2: =+G2 -> IS | I2: =+H2 -> IS | J2: =+G2 -> IS | K2: =+J2 -> IS | L2: =+K2 -> IS | M2: =+L2 -> IS | N2: =+M2 -> IS | O2: =+N2 -> IS | P2: =+O2 -> IS | Q2: =+N2 -> IS | R2: =+Q2 -> IS | S2: =+R2 -> IS
A3: Total Add-On Revenue | E3: =+Parameters!$B$5 -> Actual | F3: =+Parameters!$B$6 -> Target Budget | H3: =+Parameters!$B$7 -> Forecast Current | J3: =+Parameters!$B$5 -> Actual | M3: =+Parameters!$B$5 -> Actual | N3: =+Parameters!$B$6 -> Target Budget | P3: =+Parameters!$B$7 -> Forecast Current | R3: =+Parameters!$B$5 -> Actual | U3: =+Parameters!$B$5 -> Actual | V3: =+Parameters!$B$6 -> Target Budget | X3: =+Parameters!$B$5 -> Actual | AA3: =+Parameters!$B$5 -> Actual | AB3: =+Parameters!$B$6 -> Target Budget | AD3: =+Parameters!$B$5 -> Actual | AG3: =+Parameters!$B$5 -> Actual | AH3: =+Parameters!$B$6 -> Target Budget | AJ3: =+Parameters!$B$5 -> Actual | AM3: =+Parameters!$B$5 -> Actual | AN3: =+Parameters!$B$6 -> Target Budget | AP3: =+Parameters!$B$5 -> Actual | AS3: =+Parameters!$B$5 -> Actual | AT3: =+Parameters!$B$6 -> Target Budget | AV3: =+Parameters!$B$5 -> Actual | AY3: =+Parameters!$B$5 -> Actual | AZ3: =+Parameters!$B$6 -> Target Budget | BB3: =+Parameters!$B$5 -> Actual | BE3: =+Parameters!$B$5 -> Actual | BF3: =+Parameters!$B$6 -> Target Budget | BH3: =+Parameters!$B$5 -> Actual | BK3: =+Parameters!$B$5 -> Actual | BL3: =+Parameters!$B$6 -> Target Budget | BN3: =+Parameters!$B$5 -> Actual
A4: EBIT - Branch | E4: =+Parameters!$B$10 -> 2026 | F4: =+Parameters!$B$10 -> 2026 | H4: =+Parameters!$B$10 -> 2026 | J4: =+E4-1 -> 2025 | M4: =+E4 -> 2026 | N4: =+F4 -> 2026 | P4: =+H4 -> 2026 | R4: =+J4 -> 2025
A5: EBIT - Post Allocations | E5: =+Parameters!$B$9 -> Jul | F5: =+Parameters!$B$9 -> Jul | H5: =+Month -> Jul | J5: =+F5 -> Jul | M5: =CONCATENATE(E5," ","YTD") -> Jul YTD | N5: =CONCATENATE(F5," ","YTD") -> Jul YTD | P5: =CONCATENATE(H5," ","YTD") -> Jul YTD | R5: =CONCATENATE(J5," ","YTD") -> Jul YTD
E6: Industrial Solutions | M6: Industrial Solutions
E7: =+"MTD "&E5&" "&E4 -> MTD Jul 2026 | M7: =+"YTD "&E5&" "&YEAR -> YTD Jul 2026
E8: ACTUALS | F8: BUDGET | G8: VAR BUD | H8: FORECAST | I8: VAR FORECAST | J8: LAST YEAR | K8: VAR LY | M8: ACTUALS | N8: BUDGET | O8: VAR BUD | P8: FORECAST | Q8: VAR FORECAST | R8: LAST YEAR | S8: VAR LY
A9: Total Add-On Expenses | D9: REVENUE
A10: Gross Margin - Branch | B10: =IF(SUM(T10:T10)<>0,"Show","Hide") -> Hide | C10: -1 | D10: 1005 - Hire Revenue - Hire Fleet | E10: 3095392.1 | F10: 3586497.2 | G10: =+E10-F10 -> -491105.11 | J10: 3179280.4 | K10: =+E10-J10 -> -83888.28 | M10: 3095392.1 | N10: 3586497.2 | Q10: =+M10-N10 -> -491105.11 | R10: 3179280.4 | S10: =+M10-R10 -> -83888.28
A11: Gross Margin - Post Allocations | B11: =IF(SUM(T11:T11)<>0,"Show","Hide") -> Hide | C11: -1 | D11: 1007 - Cash Sales Contra | E11: 0 | F11: 0 | G11: =+E11-F11 -> 0 | J11: 0 | K11: =+E11-J11 -> 0 | M11: 0 | N11: 0 | Q11: =+M11-N11 -> 0 | R11: 0 | S11: =+M11-R11 -> 0
A12: Interest - Branch | B12: =IF(SUM(T12:T12)<>0,"Show","Hide") -> Hide | C12: -1 | D12: 1008 - Hire Revenue - Accrual | E12: 35352.51 | F12: -181490.61 | G12: =+E12-F12 -> 216843.12 | J12: -204146.74 | K12: =+E12-J12 -> 239499.25 | M12: 35352.51 | N12: -181490.61 | Q12: =+M12-N12 -> 216843.12 | R12: -204146.74 | S12: =+M12-R12 -> 239499.25
A13: Interest - Post Allocations | B13: =IF(SUM(T13:T13)<>0,"Show","Hide") -> Hide | C13: -1 | D13: 1054 - Hire Rebates | E13: -10420.84 | F13: -5159.0502 | G13: =+E13-F13 -> -5261.7898 | J13: -6764.91 | K13: =+E13-J13 -> -3655.93 | M13: -10420.84 | N13: -5159.0502 | Q13: =+M13-N13 -> -5261.7898 | R13: -6764.91 | S13: =+M13-R13 -> -3655.93
A14: PBT - Branch | B14: =IF(SUM(T14:T14)<>0,"Show","Hide") -> Hide | C14: -1 | D14: Hire Revenue | E14: 3120323.8 | F14: 3399847.6 | G14: =+E14-F14 -> -279523.78 | H14: 0 | I14: =+E14-H14 -> 3120323.8 | J14: 2968368.8 | K14: =+E14-J14 -> 151955.04 | M14: 3120323.8 | N14: 3399847.6 | O14: =+M14-N14 -> -279523.78 | P14: 0 | Q14: =+M14-P14 -> 3120323.8 | R14: 2968368.8 | S14: =+M14-R14 -> 151955.04
A15: PBT - Post Allocations | B15: =IF(SUM(T15:T15)<>0,"Show","Hide") -> Hide | C15: -1 | D15: 1010 - Hire Revenue - Rehire | E15: 1121356.1 | F15: 623122.95 | G15: =+E15-F15 -> 498233.17 | H15: 0 | J15: 462803.51 | K15: =+E15-J15 -> 658552.61 | M15: 1121356.1 | N15: 623122.95 | O15: =+M15-N15 -> 498233.17 | P15: 0 | Q15: =+M15-P15 -> 1121356.1 | R15: 462803.51 | S15: =+M15-R15 -> 658552.61
A16: Depreciation - Hire Fleet | B16: =IF(SUM(T16:T16)<>0,"Show","Hide") -> Hide | C16: -1 | D16: 1011 - Hire Revenue - Rehire Internal | E16: 0 | F16: 0 | G16: =+E16-F16 -> 0 | H16: 0 | J16: 0 | K16: =+E16-J16 -> 0 | M16: 0 | N16: 0 | O16: =+M16-N16 -> 0 | P16: 0 | Q16: =+M16-P16 -> 0 | R16: 0 | S16: =+M16-R16 -> 0
A17: Depreciation - Other | B17: =IF(SUM(T17:T17)<>0,"Show","Hide") -> Hide | C17: -1 | D17: Rehire Revenue | E17: 1121356.1 | F17: 623122.95 | G17: =+E17-F17 -> 498233.17 | H17: 0 | I17: =+E17-H17 -> 1121356.1 | J17: 462803.51 | K17: =+E17-J17 -> 658552.61 | M17: 1121356.1 | N17: 623122.95 | O17: =+M17-N17 -> 498233.17 | P17: 0 | Q17: =+M17-P17 -> 1121356.1 | R17: 462803.51 | S17: =+M17-R17 -> 658552.61
A18: EBITDA - Branch | B18: =IF(SUM(T18:T18)<>0,"Show","Hide") -> Hide | C18: -1 | D18: Total Hire Revenue | E18: 4241679.9 | F18: 4022970.5 | G18: =+E18-F18 -> 218709.39 | H18: 0 | I18: =+E18-H18 -> 4241679.9 | J18: 3431172.3 | K18: =+E18-J18 -> 810507.65 | M18: 4241679.9 | N18: 4022970.5 | O18: =+M18-N18 -> 218709.39 | P18: 0 | Q18: =+M18-P18 -> 4241679.9 | R18: 3431172.3 | S18: =+M18-R18 -> 810507.65
A19: EBITDA - Post Allocations | B19: =IF(SUM(T19:T19)<>0,"Show","Hide") -> Hide | C19: -1 | D19: 1030 - Hire Revenue - Cartage Internal | E19: 299610.88 | F19: 159289.99 | G19: =+E19-F19 -> 140320.89 | H19: 0 | I19: =+E19-H19 -> 299610.88 | J19: 132099.53 | K19: =+E19-J19 -> 167511.35 | M19: 299610.88 | N19: 159289.99 | O19: =+M19-N19 -> 140320.89 | P19: 0 | Q19: =+M19-P19 -> 299610.88 | R19: 132099.53 | S19: =+M19-R19 -> 167511.35
B20: =IF(SUM(T20:T20)<>0,"Show","Hide") -> Hide | C20: -1 | D20: 1031 - Hire Revenue - Cartage External | E20: 128387.68 | F20: 150795.14 | G20: =+E20-F20 -> -22407.462 | H20: 0 | I20: =+E20-H20 -> 128387.68 | J20: 86710.55 | K20: =+E20-J20 -> 41677.13 | M20: 128387.68 | N20: 150795.14 | O20: =+M20-N20 -> -22407.462 | P20: 0 | Q20: =+M20-P20 -> 128387.68 | R20: 86710.55 | S20: =+M20-R20 -> 41677.13
B21: =IF(SUM(T21:T21)<>0,"Show","Hide") -> Hide | C21: -1 | D21: 1032 - Hire Revenue - Toilet Pumpouts | E21: 15314.96 | F21: 3821.6716 | G21: =+E21-F21 -> 11493.288 | H21: 0 | I21: =+E21-H21 -> 15314.96 | J21: 1250 | K21: =+E21-J21 -> 14064.96 | M21: 15314.96 | N21: 3821.6716 | O21: =+M21-N21 -> 11493.288 | P21: 0 | Q21: =+M21-P21 -> 15314.96 | R21: 1250 | S21: =+M21-R21 -> 14064.96
B22: =IF(SUM(T22:T22)<>0,"Show","Hide") -> Hide | C22: -1 | D22: Transport | E22: 443313.52 | F22: 313906.81 | G22: =+E22-F22 -> 129406.71 | H22: 0 | I22: =+E22-H22 -> 443313.52 | J22: 220060.08 | K22: =+E22-J22 -> 223253.44 | M22: 443313.52 | N22: 313906.81 | O22: =+M22-N22 -> 129406.71 | P22: 0 | Q22: =+M22-P22 -> 443313.52 | R22: 220060.08 | S22: =+M22-R22 -> 223253.44
B23: =IF(SUM(T23:T23)<>0,"Show","Hide") -> Hide | C23: -1 | D23: 1020 - Hire Revenue - Consumables | E23: 166020.11 | F23: 241557.91 | G23: =+E23-F23 -> -75537.8 | H23: 0 | I23: =+E23-H23 -> 166020.11 | J23: 155915.73 | K23: =+E23-J23 -> 10104.38 | M23: 166020.11 | N23: 241557.91 | O23: =+M23-N23 -> -75537.8 | P23: 0 | Q23: =+M23-P23 -> 166020.11 | R23: 155915.73 | S23: =+M23-R23 -> 10104.38
B24: =IF(SUM(T24:T24)<>0,"Show","Hide") -> Hide | C24: -1 | D24: Consumables | E24: 166020.11 | F24: 241557.91 | G24: =+E24-F24 -> -75537.8 | H24: 0 | I24: =+E24-H24 -> 166020.11 | J24: 155915.73 | K24: =+E24-J24 -> 10104.38 | M24: 166020.11 | N24: 241557.91 | O24: =+M24-N24 -> -75537.8 | P24: 0 | Q24: =+M24-P24 -> 166020.11 | R24: 155915.73 | S24: =+M24-R24 -> 10104.38
B25: =IF(SUM(T25:T25)<>0,"Show","Hide") -> Hide | C25: -1 | D25: 1047 - Hire Revenue - Installation | E25: 592875.32 | F25: 787350.25 | G25: =+E25-F25 -> -194474.93 | H25: 0 | I25: =+E25-H25 -> 592875.32 | J25: 413127.9 | K25: =+E25-J25 -> 179747.42 | M25: 592875.32 | N25: 787350.25 | O25: =+M25-N25 -> -194474.93 | P25: 0 | Q25: =+M25-P25 -> 592875.32 | R25: 413127.9 | S25: =+M25-R25 -> 179747.42
B26: =IF(SUM(T26:T26)<>0,"Show","Hide") -> Hide | C26: -1 | D26: Installation | E26: 592875.32 | F26: 787350.25 | G26: =+E26-F26 -> -194474.93 | H26: 0 | I26: =+E26-H26 -> 592875.32 | J26: 413127.9 | K26: =+E26-J26 -> 179747.42 | M26: 592875.32 | N26: 787350.25 | O26: =+M26-N26 -> -194474.93 | P26: 0 | Q26: =+M26-P26 -> 592875.32 | R26: 413127.9 | S26: =+M26-R26 -> 179747.42
B27: =IF(SUM(T27:T27)<>0,"Show","Hide") -> Hide | C27: -1 | D27: 1045 - Hire Revenue - Fuel | E27: 8930 | F27: 12541.087 | G27: =+E27-F27 -> -3611.0869 | H27: 0 | I27: =+E27-H27 -> 8930 | J27: 8128 | K27: =+E27-J27 -> 802 | M27: 8930 | N27: 12541.087 | O27: =+M27-N27 -> -3611.0869 | P27: 0 | Q27: =+M27-P27 -> 8930 | R27: 8128 | S27: =+M27-R27 -> 802
B28: =IF(SUM(T28:T28)<>0,"Show","Hide") -> Hide | C28: -1 | D28: Fuel and Oil | E28: 8930 | F28: 12541.087 | G28: =+E28-F28 -> -3611.0869 | H28: 0 | I28: =+E28-H28 -> 8930 | J28: 8128 | K28: =+E28-J28 -> 802 | M28: 8930 | N28: 12541.087 | O28: =+M28-N28 -> -3611.0869 | P28: 0 | Q28: =+M28-P28 -> 8930 | R28: 8128 | S28: =+M28-R28 -> 802
B29: =IF(SUM(T29:T29)<>0,"Show","Hide") -> Hide | C29: -1 | D29: 1015 - Hire Revenue - Damage Waiver | E29: 61050.53 | F29: 50688.913 | G29: =+E29-F29 -> 10361.617 | H29: 0 | I29: =+E29-H29 -> 61050.53 | J29: 45483.65 | K29: =+E29-J29 -> 15566.88 | M29: 61050.53 | N29: 50688.913 | O29: =+M29-N29 -> 10361.617 | P29: 0 | Q29: =+M29-P29 -> 61050.53 | R29: 45483.65 | S29: =+M29-R29 -> 15566.88
B30: =IF(SUM(T30:T30)<>0,"Show","Hide") -> Hide | C30: -1 | D30: 1041 - Hire Revenue - Damage Costs Recovered | E30: 71838.8 | F30: 69123.369 | G30: =+E30-F30 -> 2715.431 | H30: 0 | I30: =+E30-H30 -> 71838.8 | J30: 53139.42 | K30: =+E30-J30 -> 18699.38 | M30: 71838.8 | N30: 69123.369 | O30: =+M30-N30 -> 2715.431 | P30: 0 | Q30: =+M30-P30 -> 71838.8 | R30: 53139.42 | S30: =+M30-R30 -> 18699.38
B31: =IF(SUM(T31:T31)<>0,"Show","Hide") -> Hide | C31: -1 | D31: Damage Revenue | E31: 132889.33 | F31: 119812.28 | G31: =+E31-F31 -> 13077.048 | H31: 0 | I31: =+E31-H31 -> 132889.33 | J31: 98623.07 | K31: =+E31-J31 -> 34266.26 | M31: 132889.33 | N31: 119812.28 | O31: =+M31-N31 -> 13077.048 | P31: 0 | Q31: =+M31-P31 -> 132889.33 | R31: 98623.07 | S31: =+M31-R31 -> 34266.26
... B66: =IF(SUM(T66:T66)<>0,"Show","Hide") -> Hide | C66: -1 | D66: Total Combined Revenue | E66: 5691386.2 | F66: 5657216.5 | G66: =+E66-F66 -> 34169.709 | H66: 0 | I66: =+E66-H66 -> 5691386.2 | J66: 4443217.6 | K66: =+E66-J66 -> 1248168.6 | M66: 5691386.2 | N66: 5657216.5 | O66: =+M66-N66 -> 34169.709 | P66: 0 | Q66: =+M66-P66 -> 5691386.2 | R66: 4443217.6 | S66: =+M66-R66 -> 1248168.6
B67: SHOW | D67: REPAIRS & MAINTENANCE | E67: 0 | F67: 0 | G67: =+E67-F67 -> 0 | H67: 0 | I67: =+E67-H67 -> 0 | J67: 0 | K67: =+E67-J67 -> 0 | M67: 0 | N67: 0 | O67: =+M67-N67 -> 0 | P67: 0 | Q67: =+M67-P67 -> 0 | R67: 0 | S67: =+M67-R67 -> 0
B68: =IF(SUM(T68:T68)<>0,"Show","Hide") -> Hide | C68: 1 | D68: 2376 - Not Specified | E68: 0 | F68: 0 | G68: =+E68-F68 -> 0 | H68: 0 | I68: =+E68-H68 -> 0 | J68: 0 | K68: =+E68-J68 -> 0 | M68: 0 | N68: 0 | O68: =+M68-N68 -> 0 | P68: 0 | Q68: =+M68-P68 -> 0 | R68: 0 | S68: =+M68-R68 -> 0
B69: =IF(SUM(T69:T69)<>0,"Show","Hide") -> Hide | C69: 1 | D69: 3217 - R&M Labour - Internal Service Jobs | E69: 19962.7 | F69: 10444.815 | G69: =+E69-F69 -> 9517.8853 | H69: 0 | I69: =+E69-H69 -> 19962.7 | J69: 6233.15 | K69: =+E69-J69 -> 13729.55 | M69: 19962.7 | N69: 10444.815 | O69: =+M69-N69 -> 9517.8853 | P69: 0 | Q69: =+M69-P69 -> 19962.7 | R69: 6233.15 | S69: =+M69-R69 -> 13729.55
B70: =IF(SUM(T70:T70)<>0,"Show","Hide") -> Hide | C70: 1 | D70: 2110 - R&M Parts - Internal Service Jobs | E70: 205418.78 | F70: 89920.698 | G70: =+E70-F70 -> 115498.08 | H70: 0 | I70: =+E70-H70 -> 205418.78 | J70: 47188.18 | K70: =+E70-J70 -> 158230.6 | M70: 205418.78 | N70: 89920.698 | O70: =+M70-N70 -> 115498.08 | P70: 0 | Q70: =+M70-P70 -> 205418.78 | R70: 47188.18 | S70: =+M70-R70 -> 158230.6
B71: =IF(SUM(T71:T71)<>0,"Show","Hide") -> Hide | C71: 1 | D71: 3217 - R&M Labour - Internal Service Jobs | E71: 19962.7 | F71: 10444.815 | G71: =+E71-F71 -> 9517.8853 | H71: 0 | I71: =+E71-H71 -> 19962.7 | J71: 6233.15 | K71: =+E71-J71 -> 13729.55 | M71: 19962.7 | N71: 10444.815 | O71: =+M71-N71 -> 9517.8853 | P71: 0 | Q71: =+M71-P71 -> 19962.7 | R71: 6233.15 | S71: =+M71-R71 -> 13729.55
B72: =IF(SUM(T72:T72)<>0,"Show","Hide") -> Hide | C72: 1 | D72: 2357 - R&M Parts | E72: 13288.47 | F72: 4793.6439 | G72: =+E72-F72 -> 8494.8261 | H72: 0 | I72: =+E72-H72 -> 13288.47 | J72: 15428.79 | K72: =+E72-J72 -> -2140.32 | M72: 13288.47 | N72: 4793.6439 | O72: =+M72-N72 -> 8494.8261 | P72: 0 | Q72: =+M72-P72 -> 13288.47 | R72: 15428.79 | S72: =+M72-R72 -> -2140.32
B73: =IF(SUM(T73:T73)<>0,"Show","Hide") -> Hide | C73: 1 | D73: 2370 - Outside Repairs | E73: 1368.89 | F73: 2112.2099 | G73: =+E73-F73 -> -743.3199 | H73: 0 | I73: =+E73-H73 -> 1368.89 | J73: 0 | K73: =+E73-J73 -> 1368.89 | M73: 1368.89 | N73: 2112.2099 | O73: =+M73-N73 -> -743.3199 | P73: 0 | Q73: =+M73-P73 -> 1368.89 | R73: 0 | S73: =+M73-R73 -> 1368.89
B74: =IF(SUM(T74:T74)<>0,"Show","Hide") -> Hide | C74: 1 | D74: 2371 - R&M - External Labour | E74: 82391.88 | F74: 43130.37 | G74: =+E74-F74 -> 39261.51 | H74: 0 | I74: =+E74-H74 -> 82391.88 | J74: 98843.64 | K74: =+E74-J74 -> -16451.76 | M74: 82391.88 | N74: 43130.37 | O74: =+M74-N74 -> 39261.51 | P74: 0 | Q74: =+M74-P74 -> 82391.88 | R74: 98843.64 | S74: =+M74-R74 -> -16451.76
B75: =IF(SUM(T75:T75)<>0,"Show","Hide") -> Hide | C75: 1 | D75: 2372 - R&M - External Parts | E75: 10800.93 | F75: 17921.724 | G75: =+E75-F75 -> -7120.7943 | H75: 0 | I75: =+E75-H75 -> 10800.93 | J75: 26545.89 | K75: =+E75-J75 -> -15744.96 | M75: 10800.93 | N75: 17921.724 | O75: =+M75-N75 -> -7120.7943 | P75: 0 | Q75: =+M75-P75 -> 10800.93 | R75: 26545.89 | S75: =+M75-R75 -> -15744.96
B76: =IF(SUM(T76:T76)<>0,"Show","Hide") -> Hide | C76: 1 | D76: 2374 - R&M - Rented & Operating Leased Fleet | E76: 0 | F76: 0 | G76: =+E76-F76 -> 0 | H76: 0 | I76: =+E76-H76 -> 0 | J76: 0 | K76: =+E76-J76 -> 0 | M76: 0 | N76: 0 | O76: =+M76-N76 -> 0 | P76: 0 | Q76: =+M76-P76 -> 0 | R76: 0 | S76: =+M76-R76 -> 0
B77: =IF(SUM(T77:T77)<>0,"Show","Hide") -> Hide | C77: 1 | D77: 2378 - Testing and Tagging | E77: 4945.31 | F77: 8867.4529 | G77: =+E77-F77 -> -3922.1429 | H77: 0 | I77: =+E77-H77 -> 4945.31 | J77: 5402.36 | K77: =+E77-J77 -> -457.05 | M77: 4945.31 | N77: 8867.4529 | O77: =+M77-N77 -> -3922.1429 | P77: 0 | Q77: =+M77-P77 -> 4945.31 | R77: 5402.36 | S77: =+M77-R77 -> -457.05
B78: =IF(SUM(T78:T78)<>0,"Show","Hide") -> Hide | C78: 1 | D78: 2150 - Consumables - Internal/Workshops | E78: 8940.44 | F78: 8151.7571 | G78: =+E78-F78 -> 788.68293 | H78: 0 | I78: =+E78-H78 -> 8940.44 | J78: 32926.46 | K78: =+E78-J78 -> -23986.02 | M78: 8940.44 | N78: 8151.7571 | O78: =+M78-N78 -> 788.68293 | P78: 0 | Q78: =+M78-P78 -> 8940.44 | R78: 32926.46 | S78: =+M78-R78 -> -23986.02
B79: =IF(SUM(T79:T79)<>0,"Show","Hide") -> Hide | C79: 1 | D79: R&M Parts and External Labour | E79: 347117.4 | F79: 185342.67 | G79: =+E79-F79 -> 161774.73 | H79: 0 | I79: =+E79-H79 -> 347117.4 | J79: 232568.47 | K79: =+E79-J79 -> 114548.93 | M79: 347117.4 | N79: 185342.67 | O79: =+M79-N79 -> 161774.73 | P79: 0 | Q79: =+M79-P79 -> 347117.4 | R79: 232568.47 | S79: =+M79-R79 -> 114548.93
... B102: =IF(SUM(T102:T102)<>0,"Show","Hide") -> Hide | C102: 1 | D102: 5236 - R&M - Rewards and Recognition | E102: 1000 | F102: 1000 | G102: =+E102-F102 -> 0 | H102: 0 | I102: =+E102-H102 -> 1000 | J102: 0 | K102: =+E102-J102 -> 1000 | M102: 1000 | N102: 1000 | O102: =+M102-N102 -> 0 | P102: 0 | Q102: =+M102-P102 -> 1000 | R102: 0 | S102: =+M102-R102 -> 1000
B103: =IF(SUM(T103:T103)<>0,"Show","Hide") -> Hide | C103: 1 | D103: 3219 - DO NOT USE | E103: #NUM! | F103: #NUM! | G103: =+E103-F103 -> #NUM! | H103: #NUM! | I103: =+E103-H103 -> #NUM! | J103: #NUM! | K103: =+E103-J103 -> #NUM! | M103: #NUM! | N103: #NUM! | O103: =+M103-N103 -> #NUM! | P103: #NUM! | Q103: =+M103-P103 -> #NUM! | R103: #NUM! | S103: =+M103-R103 -> #NUM!
B104: =IF(SUM(T104:T104)<>0,"Show","Hide") -> Hide | C104: 1 | D104: R&M Chargeable Wages | E104: 327069.63 | F104: 299437.09 | G104: =+E104-F104 -> 27632.541 | H104: 0 | I104: =+E104-H104 -> 327069.63 | J104: 287306.27 | K104: =+E104-J104 -> 39763.36 | M104: 327069.63 | N104: 299437.09 | O104: =+M104-N104 -> 27632.541 | P104: 0 | Q104: =+M104-P104 -> 327069.63 | R104: 287306.27 | S104: =+M104-R104 -> 39763.36
B105: =IF(SUM(T105:T105)<>0,"Show","Hide") -> Hide | C105: 1 | D105: 5410 - R&M NC - Salaries & Wages | E105: 220141.35 | F105: 193423.87 | G105: =+E105-F105 -> 26717.484 | H105: 0 | I105: =+E105-H105 -> 220141.35 | J105: 166262.34 | K105: =+E105-J105 -> 53879.01 | M105: 220141.35 | N105: 193423.87 | O105: =+M105-N105 -> 26717.484 | P105: 0 | Q105: =+M105-P105 -> 220141.35 | R105: 166262.34 | S105: =+M105-R105 -> 53879.01
B106: =IF(SUM(T106:T106)<>0,"Show","Hide") -> Hide | C106: 1 | D106: 5413 - R&M NC - Payroll Offset | E106: -387032.39 | F106: -266879.11 | G106: =+E106-F106 -> -120153.28 | H106: 0 | I106: =+E106-H106 -> -387032.39 | J106: -318425.74 | K106: =+E106-J106 -> -68606.65 | M106: -387032.39 | N106: -266879.11 | O106: =+M106-N106 -> -120153.28 | P106: 0 | Q106: =+M106-P106 -> -387032.39 | R106: -318425.74 | S106: =+M106-R106 -> -68606.65
B107: =IF(SUM(T107:T107)<>0,"Show","Hide") -> Hide | C107: 1 | D107: 5412 - R&M NC - Overtime | E107: 191518.84 | F107: 175442.96 | G107: =+E107-F107 -> 16075.877 | H107: 0 | I107: =+E107-H107 -> 191518.84 | J107: 117671.53 | K107: =+E107-J107 -> 73847.31 | M107: 191518.84 | N107: 175442.96 | O107: =+M107-N107 -> 16075.877 | P107: 0 | Q107: =+M107-P107 -> 191518.84 | R107: 117671.53 | S107: =+M107-R107 -> 73847.31
B108: =IF(SUM(T108:T108)<>0,"Show","Hide") -> Hide | C108: 1 | D108: 5415 - R&M NC Incentives | E108: 0 | F108: 0 | G108: =+E108-F108 -> 0 | H108: 0 | I108: =+E108-H108 -> 0 | J108: 0 | K108: =+E108-J108 -> 0 | M108: 0 | N108: 0 | O108: =+M108-N108 -> 0 | P108: 0 | Q108: =+M108-P108 -> 0 | R108: 0 | S108: =+M108-R108 -> 0
B109: =IF(SUM(T109:T109)<>0,"Show","Hide") -> Hide | C109: 1 | D109: 5416 - R&M NC - Fixed Allowance with super | E109: 13264.57 | F109: 5195.711 | G109: =+E109-F109 -> 8068.859 | H109: 0 | I109: =+E109-H109 -> 13264.57 | J109: 35801.2 | K109: =+E109-J109 -> -22536.63 | M109: 13264.57 | N109: 5195.711 | O109: =+M109-N109 -> 8068.859 | P109: 0 | Q109: =+M109-P109 -> 13264.57 | R109: 35801.2 | S109: =+M109-R109 -> -22536.63
B110: =IF(SUM(T110:T110)<>0,"Show","Hide") -> Hide | C110: 1 | D110: 5417 - R&M NC - Variable Allowance with super | E110: 31832.08 | F110: 2231.67 | G110: =+E110-F110 -> 29600.41 | H110: 0 | I110: =+E110-H110 -> 31832.08 | J110: 0 | K110: =+E110-J110 -> 31832.08 | M110: 31832.08 | N110: 2231.67 | O110: =+M110-N110 -> 29600.41 | P110: 0 | Q110: =+M110-P110 -> 31832.08 | R110: 0 | S110: =+M110-R110 -> 31832.08
B111: =IF(SUM(T111:T111)<>0,"Show","Hide") -> Hide | C111: 1 | D111: 5419 - R&M NC Allowance no super | E111: 3490.73 | F111: 768.65 | G111: =+E111-F111 -> 2722.08 | H111: 0 | I111: =+E111-H111 -> 3490.73 | J111: 5946.39 | K111: =+E111-J111 -> -2455.66 | M111: 3490.73 | N111: 768.65 | O111: =+M111-N111 -> 2722.08 | P111: 0 | Q111: =+M111-P111 -> 3490.73 | R111: 5946.39 | S111: =+M111-R111 -> -2455.66
B112: =IF(SUM(T112:T112)<>0,"Show","Hide") -> Hide | C112: 1 | D112: 5425 - R&M NC - Annual Leave Expense | E112: 5242.86 | F112: 2512.2753 | G112: =+E112-F112 -> 2730.5847 | H112: 0 | I112: =+E112-H112 -> 5242.86 | J112: -5826.51 | K112: =+E112-J112 -> 11069.37 | M112: 5242.86 | N112: 2512.2753 | O112: =+M112-N112 -> 2730.5847 | P112: 0 | Q112: =+M112-P112 -> 5242.86 | R112: -5826.51 | S112: =+M112-R112 -> 11069.37
B113: =IF(SUM(T113:T113)<>0,"Show","Hide") -> Hide | C113: 1 | D113: 5426 - R&M NC - Long Service Leave | E113: 3598.16 | F113: 9103.486 | G113: =+E113-F113 -> -5505.326 | H113: 0 | I113: =+E113-H113 -> 3598.16 | J113: 3553.37 | K113: =+E113-J113 -> 44.79 | M113: 3598.16 | N113: 9103.486 | O113: =+M113-N113 -> -5505.326 | P113: 0 | Q113: =+M113-P113 -> 3598.16 | R113: 3553.37 | S113: =+M113-R113 -> 44.79
B114: =IF(SUM(T114:T114)<>0,"Show","Hide") -> Hide | C114: 1 | D114: 5427 - R&M NC - Sick Leave Expense | E114: 0 | F114: 0 | G114: =+E114-F114 -> 0 | H114: 0 | I114: =+E114-H114 -> 0 | J114: 0 | K114: =+E114-J114 -> 0 | M114: 0 | N114: 0 | O114: =+M114-N114 -> 0 | P114: 0 | Q114: =+M114-P114 -> 0 | R114: 0 | S114: =+M114-R114 -> 0
B115: =IF(SUM(T115:T115)<>0,"Show","Hide") -> Hide | C115: 1 | D115: 5428 - R&M NC - EBA Severance | E115: 0 | F115: 0 | G115: =+E115-F115 -> 0 | H115: 0 | I115: =+E115-H115 -> 0 | J115: 0 | K115: =+E115-J115 -> 0 | M115: 0 | N115: 0 | O115: =+M115-N115 -> 0 | P115: 0 | Q115: =+M115-P115 -> 0 | R115: 0 | S115: =+M115-R115 -> 0
... B124: =IF(SUM(T124:T124)<>0,"Show","Hide") -> Hide | C124: 1 | D124: 3528 - Travel R&M | E124: 8356.94 | F124: 2602.1238 | G124: =+E124-F124 -> 5754.8162 | H124: 0 | I124: =+E124-H124 -> 8356.94 | J124: 5401.74 | K124: =+E124-J124 -> 2955.2 | M124: 8356.94 | N124: 2602.1238 | O124: =+M124-N124 -> 5754.8162 | P124: 0 | Q124: =+M124-P124 -> 8356.94 | R124: 5401.74 | S124: =+M124-R124 -> 2955.2
B125: =IF(SUM(T125:T125)<>0,"Show","Hide") -> Hide | D125: R&M Other | E125: 0 | F125: 0 | G125: =+E125-F125 -> 0 | H125: 0 | I125: =+E125-H125 -> 0 | J125: 0 | K125: =+E125-J125 -> 0 | M125: 0 | N125: 0 | O125: =+M125-N125 -> 0 | P125: 0 | Q125: =+M125-P125 -> 0 | R125: 0 | S125: =+M125-R125 -> 0
B126: =IF(SUM(T126:T126)<>0,"Show","Hide") -> Hide | C126: 1 | D126: Total Repairs & Maintenance | E126: 833490.17 | F126: 654170.76 | G126: =+E126-F126 -> 179319.41 | H126: 0 | I126: =+E126-H126 -> 833490.17 | J126: 588110.85 | K126: =+E126-J126 -> 245379.32 | M126: 833490.17 | N126: 654170.76 | O126: =+M126-N126 -> 179319.41 | P126: 0 | Q126: =+M126-P126 -> 833490.17 | R126: 588110.85 | S126: =+M126-R126 -> 245379.32
B127: Show | D127: EQUIPMENT OWNERSHIP COSTS (EXCL DEPN) | E127: 0 | F127: 0 | G127: =+E127-F127 -> 0 | H127: 0 | I127: =+E127-H127 -> 0 | J127: 0 | K127: =+E127-J127 -> 0 | M127: 0 | N127: 0 | O127: =+M127-N127 -> 0 | P127: 0 | Q127: =+M127-P127 -> 0 | R127: 0 | S127: =+M127-R127 -> 0
B128: =IF(SUM(T128:T128)<>0,"Show","Hide") -> Hide | C128: 1 | D128: 3575 - Rego & On Road - Hire Fleet | E128: 15350.76 | F128: 14158.95 | G128: =+E128-F128 -> 1191.81 | H128: 0 | I128: =+E128-H128 -> 15350.76 | J128: 14158.95 | K128: =+E128-J128 -> 1191.81 | M128: 15350.76 | N128: 14158.95 | O128: =+M128-N128 -> 1191.81 | P128: 0 | Q128: =+M128-P128 -> 15350.76 | R128: 14158.95 | S128: =+M128-R128 -> 1191.81
B129: =IF(SUM(T129:T129)<>0,"Show","Hide") -> Hide | C129: 1 | D129: 3580 - Insurance - Hire Fleet | E129: 12112.49 | F129: 12112.49 | G129: =+E129-F129 -> 0 | H129: 0 | I129: =+E129-H129 -> 12112.49 | J129: 12112.49 | K129: =+E129-J129 -> 0 | M129: 12112.49 | N129: 12112.49 | O129: =+M129-N129 -> 0 | P129: 0 | Q129: =+M129-P129 -> 12112.49 | R129: 12112.49 | S129: =+M129-R129 -> 0
B130: =IF(SUM(T130:T130)<>0,"Show","Hide") -> Hide | C130: 1 | D130: 3581 - Insurance Excess - Hire Fleet | E130: 0 | F130: 0 | G130: =+E130-F130 -> 0 | H130: 0 | I130: =+E130-H130 -> 0 | J130: 0 | K130: =+E130-J130 -> 0 | M130: 0 | N130: 0 | O130: =+M130-N130 -> 0 | P130: 0 | Q130: =+M130-P130 -> 0 | R130: 0 | S130: =+M130-R130 -> 0
B131: =IF(SUM(T131:T131)<>0,"Show","Hide") -> Hide | C131: 1 | D131: Registration & Insurance | E131: 27463.25 | F131: 26271.44 | G131: =+E131-F131 -> 1191.81 | H131: 0 | I131: =+E131-H131 -> 27463.25 | J131: 26271.44 | K131: =+E131-J131 -> 1191.81 | M131: 27463.25 | N131: 26271.44 | O131: =+M131-N131 -> 1191.81 | P131: 0 | Q131: =+M131-P131 -> 27463.25 | R131: 26271.44 | S131: =+M131-R131 -> 1191.81
B132: =IF(SUM(T132:T132)<>0,"Show","Hide") -> Hide | C132: -1 | D132: 1125 - Disposal Proceeds - Hire Fleet | E132: 0 | F132: 0 | G132: =+E132-F132 -> 0 | H132: 0 | I132: =+E132-H132 -> 0 | J132: 0 | K132: =+E132-J132 -> 0 | M132: 0 | N132: 0 | O132: =+M132-N132 -> 0 | P132: 0 | Q132: =+M132-P132 -> 0 | R132: 0 | S132: =+M132-R132 -> 0
B133: =IF(SUM(T133:T133)<>0,"Show","Hide") -> Hide | C133: -1 | D133: 1126 - Disposal Proceeds - Land/Buildings | E133: 0 | F133: 0 | G133: =+E133-F133 -> 0 | H133: 0 | I133: =+E133-H133 -> 0 | J133: 0 | K133: =+E133-J133 -> 0 | M133: 0 | N133: 0 | O133: =+M133-N133 -> 0 | P133: 0 | Q133: =+M133-P133 -> 0 | R133: 0 | S133: =+M133-R133 -> 0
B134: =IF(SUM(T134:T134)<>0,"Show","Hide") -> Hide | C134: -1 | D134: 1127 - Disposal Proceeds - P&E | E134: 0 | F134: 0 | G134: =+E134-F134 -> 0 | H134: 0 | I134: =+E134-H134 -> 0 | J134: 0 | K134: =+E134-J134 -> 0 | M134: 0 | N134: 0 | O134: =+M134-N134 -> 0 | P134: 0 | Q134: =+M134-P134 -> 0 | R134: 0 | S134: =+M134-R134 -> 0
B135: =IF(SUM(T135:T135)<>0,"Show","Hide") -> Hide | C135: -1 | D135: 1128 - Disposal Proceeds - Non serialised | E135: 0 | F135: 0 | G135: =+E135-F135 -> 0 | H135: 0 | I135: =+E135-H135 -> 0 | J135: 0 | K135: =+E135-J135 -> 0 | M135: 0 | N135: 0 | O135: =+M135-N135 -> 0 | P135: 0 | Q135: =+M135-P135 -> 0 | R135: 0 | S135: =+M135-R135 -> 0
B136: =IF(SUM(T136:T136)<>0,"Show","Hide") -> Hide | C136: -1 | D136: 1130 - Disposal Proceeds - Contra | E136: 0 | F136: 0 | G136: =+E136-F136 -> 0 | H136: 0 | I136: =+E136-H136 -> 0 | J136: 0 | K136: =+E136-J136 -> 0 | M136: 0 | N136: 0 | O136: =+M136-N136 -> 0 | P136: 0 | Q136: =+M136-P136 -> 0 | R136: 0 | S136: =+M136-R136 -> 0
B137: =IF(SUM(T137:T137)<>0,"Show","Hide") -> Hide | C137: 1 | D137: 2115 - Disposal WDV - Hire Fleet | E137: 0 | F137: 0 | G137: =+E137-F137 -> 0 | H137: 0 | I137: =+E137-H137 -> 0 | J137: 0 | K137: =+E137-J137 -> 0 | M137: 0 | N137: 0 | O137: =+M137-N137 -> 0 | P137: 0 | Q137: =+M137-P137 -> 0 | R137: 0 | S137: =+M137-R137 -> 0
B138: =IF(SUM(T138:T138)<>0,"Show","Hide") -> Hide | C138: 1 | D138: 2117 - Disposal WDV - Land/Buildings | E138: 0 | F138: 0 | G138: =+E138-F138 -> 0 | H138: 0 | I138: =+E138-H138 -> 0 | J138: 0 | K138: =+E138-J138 -> 0 | M138: 0 | N138: 0 | O138: =+M138-N138 -> 0 | P138: 0 | Q138: =+M138-P138 -> 0 | R138: 0 | S138: =+M138-R138 -> 0
B139: =IF(SUM(T139:T139)<>0,"Show","Hide") -> Hide | C139: 1 | D139: 2118 - Disposal WDV - P&E | E139: 0 | F139: 0 | G139: =+E139-F139 -> 0 | H139: 0 | I139: =+E139-H139 -> 0 | J139: 0 | K139: =+E139-J139 -> 0 | M139: 0 | N139: 0 | O139: =+M139-N139 -> 0 | P139: 0 | Q139: =+M139-P139 -> 0 | R139: 0 | S139: =+M139-R139 -> 0
... B149: =IF(SUM(T149:T149)<>0,"Show","Hide") -> Hide | C149: 1 | D149: Rehire Expenses | E149: 895682.45 | F149: 530001.7 | G149: =+E149-F149 -> 365680.75 | H149: 0 | I149: =+E149-H149 -> 895682.45 | J149: 418146.33 | K149: =+E149-J149 -> 477536.12 | M149: 895682.45 | N149: 530001.7 | O149: =+M149-N149 -> 365680.75 | P149: 0 | Q149: =+M149-P149 -> 895682.45 | R149: 418146.33 | S149: =+M149-R149 -> 477536.12
B150: =IF(SUM(T150:T150)<>0,"Show","Hide") -> Hide | D150: ADD ON EXPENSES | E150: 0 | F150: 0 | G150: =+E150-F150 -> 0 | H150: 0 | I150: =+E150-H150 -> 0 | J150: 0 | K150: =+E150-J150 -> 0 | M150: 0 | N150: 0 | O150: =+M150-N150 -> 0 | P150: 0 | Q150: =+M150-P150 -> 0 | R150: 0 | S150: =+M150-R150 -> 0
B151: =IF(SUM(T151:T151)<>0,"Show","Hide") -> Hide | C151: 1 | D151: 2120 - Cartage - Recoverable | E151: 323226.56 | F151: 222493.28 | G151: =+E151-F151 -> 100733.28 | H151: 0 | I151: =+E151-H151 -> 323226.56 | J151: 175582.89 | K151: =+E151-J151 -> 147643.67 | M151: 323226.56 | N151: 222493.28 | O151: =+M151-N151 -> 100733.28 | P151: 0 | Q151: =+M151-P151 -> 323226.56 | R151: 175582.89 | S151: =+M151-R151 -> 147643.67
B152: =IF(SUM(T152:T152)<>0,"Show","Hide") -> Hide | C152: 1 | D152: 2140 - Cartage - Not Recovered | E152: 16180.39 | F152: 2953.6439 | G152: =+E152-F152 -> 13226.746 | H152: 0 | I152: =+E152-H152 -> 16180.39 | J152: 11406.12 | K152: =+E152-J152 -> 4774.27 | M152: 16180.39 | N152: 2953.6439 | O152: =+M152-N152 -> 13226.746 | P152: 0 | Q152: =+M152-P152 -> 16180.39 | R152: 11406.12 | S152: =+M152-R152 -> 4774.27
B153: =IF(SUM(T153:T153)<>0,"Show","Hide") -> Hide | C153: 1 | D153: 2145 - Cartage - Equipment Breakdown | E153: 21485.25 | F153: 3576.9504 | G153: =+E153-F153 -> 17908.3 | H153: 0 | I153: =+E153-H153 -> 21485.25 | J153: 6765.44 | K153: =+E153-J153 -> 14719.81 | M153: 21485.25 | N153: 3576.9504 | O153: =+M153-N153 -> 17908.3 | P153: 0 | Q153: =+M153-P153 -> 21485.25 | R153: 6765.44 | S153: =+M153-R153 -> 14719.81
B154: =IF(SUM(T154:T154)<>0,"Show","Hide") -> Hide | C154: 1 | D154: 2146 - Cartage - Fleet Disposals | E154: 0 | F154: 151.74628 | G154: =+E154-F154 -> -151.74628 | H154: 0 | I154: =+E154-H154 -> 0 | J154: 0 | K154: =+E154-J154 -> 0 | M154: 0 | N154: 151.74628 | O154: =+M154-N154 -> -151.74628 | P154: 0 | Q154: =+M154-P154 -> 0 | R154: 0 | S154: =+M154-R154 -> 0
B155: =IF(SUM(T155:T155)<>0,"Show","Hide") -> Hide | C155: 1 | D155: 2147 - Cartage - Branch to Branch | E155: 4303.34 | F155: 5150.1513 | G155: =+E155-F155 -> -846.81127 | H155: 0 | I155: =+E155-H155 -> 4303.34 | J155: 11347.82 | K155: =+E155-J155 -> -7044.48 | M155: 4303.34 | N155: 5150.1513 | O155: =+M155-N155 -> -846.81127 | P155: 0 | Q155: =+M155-P155 -> 4303.34 | R155: 11347.82 | S155: =+M155-R155 -> -7044.48
B156: =IF(SUM(T156:T156)<>0,"Show","Hide") -> Hide | C156: 1 | D156: 2148 - External Transport - Project Hawthorn | E156: 0 | F156: 0 | G156: =+E156-F156 -> 0 | H156: 0 | I156: =+E156-H156 -> 0 | J156: 0 | K156: =+E156-J156 -> 0 | M156: 0 | N156: 0 | O156: =+M156-N156 -> 0 | P156: 0 | Q156: =+M156-P156 -> 0 | R156: 0 | S156: =+M156-R156 -> 0
B157: =IF(SUM(T157:T157)<>0,"Show","Hide") -> Hide | C157: 1 | D157: 3325 - Toilet Pumpout Costs | E157: 12455.8 | F157: 271.00848 | G157: =+E157-F157 -> 12184.792 | H157: 0 | I157: =+E157-H157 -> 12455.8 | J157: 345.76 | K157: =+E157-J157 -> 12110.04 | M157: 12455.8 | N157: 271.00848 | O157: =+M157-N157 -> 12184.792 | P157: 0 | Q157: =+M157-P157 -> 12455.8 | R157: 345.76 | S157: =+M157-R157 -> 12110.04
B158: =IF(SUM(T158:T158)<>0,"Show","Hide") -> Hide | C158: 1 | D158: External Transport | E158: 377651.34 | F158: 234596.78 | G158: =+E158-F158 -> 143054.56 | H158: 0 | I158: =+E158-H158 -> 377651.34 | J158: 205448.03 | K158: =+E158-J158 -> 172203.31 | M158: 377651.34 | N158: 234596.78 | O158: =+M158-N158 -> 143054.56 | P158: 0 | Q158: =+M158-P158 -> 377651.34 | R158: 205448.03 | S158: =+M158-R158 -> 172203.31
B159: =IF(SUM(T159:T159)<>0,"Show","Hide") -> Hide | C159: 1 | D159: 5310 - Transport Salaries and Wages | E159: 0 | F159: 0 | G159: =+E159-F159 -> 0 | H159: 0 | I159: =+E159-H159 -> 0 | J159: 13686.47 | K159: =+E159-J159 -> -13686.47 | M159: 0 | N159: 0 | O159: =+M159-N159 -> 0 | P159: 0 | Q159: =+M159-P159 -> 0 | R159: 13686.47 | S159: =+M159-R159 -> -13686.47
B160: =IF(SUM(T160:T160)<>0,"Show","Hide") -> Hide | C160: 1 | D160: 5311 - Transport - Salaries and Wages - Project Hawthorn | E160: 0 | F160: 0 | G160: =+E160-F160 -> 0 | H160: 0 | I160: =+E160-H160 -> 0 | J160: 0 | K160: =+E160-J160 -> 0 | M160: 0 | N160: 0 | O160: =+M160-N160 -> 0 | P160: 0 | Q160: =+M160-P160 -> 0 | R160: 0 | S160: =+M160-R160 -> 0
B161: =IF(SUM(T161:T161)<>0,"Show","Hide") -> Hide | C161: 1 | D161: 5313 - Transport - Payroll Offset | E161: 0 | F161: 0 | G161: =+E161-F161 -> 0 | H161: 0 | I161: =+E161-H161 -> 0 | J161: 0 | K161: =+E161-J161 -> 0 | M161: 0 | N161: 0 | O161: =+M161-N161 -> 0 | P161: 0 | Q161: =+M161-P161 -> 0 | R161: 0 | S161: =+M161-R161 -> 0
B162: =IF(SUM(T162:T162)<>0,"Show","Hide") -> Hide | C162: 1 | D162: 5312 - Transport Overtime | E162: 0 | F162: 0 | G162: =+E162-F162 -> 0 | H162: 0 | I162: =+E162-H162 -> 0 | J162: 162.23 | K162: =+E162-J162 -> -162.23 | M162: 0 | N162: 0 | O162: =+M162-N162 -> 0 | P162: 0 | Q162: =+M162-P162 -> 0 | R162: 162.23 | S162: =+M162-R162 -> -162.23
... B235: =IF(SUM(T235:T235)<>0,"Show","Hide") -> Hide | C235: -1 | D235: Gross Margin - Post Allocations (Stat) | E235: 2706756.6 | F235: 3092322.5 | G235: =+E235-F235 -> -385565.89 | H235: 0 | I235: =+E235-H235 -> 2706756.6 | J235: 2495736.9 | K235: =+E235-J235 -> 211019.68 | M235: 2706756.6 | N235: 3092322.5 | O235: =+M235-N235 -> -385565.89 | P235: 0 | Q235: =+M235-P235 -> 2706756.6 | R235: 2495736.9 | S235: =+M235-R235 -> 211019.68
B236: Show | D236: OVERHEADS | E236: 0 | F236: 0 | G236: =+E236-F236 -> 0 | H236: 0 | I236: =+E236-H236 -> 0 | J236: 0 | K236: =+E236-J236 -> 0 | M236: 0 | N236: 0 | O236: =+M236-N236 -> 0 | P236: 0 | Q236: =+M236-P236 -> 0 | R236: 0 | S236: =+M236-R236 -> 0
B237: =IF(SUM(T237:T237)<>0,"Show","Hide") -> Hide | C237: 1 | D237: 3350 - Property Rent - External | E237: 107345.44 | F237: 98413.6 | G237: =+E237-F237 -> 8931.8402 | H237: 0 | I237: =+E237-H237 -> 107345.44 | J237: 92342.46 | K237: =+E237-J237 -> 15002.98 | M237: 107345.44 | N237: 98413.6 | O237: =+M237-N237 -> 8931.8402 | P237: 0 | Q237: =+M237-P237 -> 107345.44 | R237: 92342.46 | S237: =+M237-R237 -> 15002.98
B238: =IF(SUM(T238:T238)<>0,"Show","Hide") -> Hide | C238: 1 | D238: 3354 - Leased Land & Buildings CONTRA | E238: 0 | F238: 0 | G238: =+E238-F238 -> 0 | H238: 0 | I238: =+E238-H238 -> 0 | J238: 0 | K238: =+E238-J238 -> 0 | M238: 0 | N238: 0 | O238: =+M238-N238 -> 0 | P238: 0 | Q238: =+M238-P238 -> 0 | R238: 0 | S238: =+M238-R238 -> 0
B239: =IF(SUM(T239:T239)<>0,"Show","Hide") -> Hide | C239: 1 | D239: 3351 - Property Rent - Internal | E239: 0 | F239: 0 | G239: =+E239-F239 -> 0 | H239: 0 | I239: =+E239-H239 -> 0 | J239: 0 | K239: =+E239-J239 -> 0 | M239: 0 | N239: 0 | O239: =+M239-N239 -> 0 | P239: 0 | Q239: =+M239-P239 -> 0 | R239: 0 | S239: =+M239-R239 -> 0
B240: =IF(SUM(T240:T240)<>0,"Show","Hide") -> Hide | C240: 1 | D240: 3352 - Utilities | E240: 5241.86 | F240: 6428.2706 | G240: =+E240-F240 -> -1186.4106 | H240: 0 | I240: =+E240-H240 -> 5241.86 | J240: 6734.27 | K240: =+E240-J240 -> -1492.41 | M240: 5241.86 | N240: 6428.2706 | O240: =+M240-N240 -> -1186.4106 | P240: 0 | Q240: =+M240-P240 -> 5241.86 | R240: 6734.27 | S240: =+M240-R240 -> -1492.41
B241: =IF(SUM(T241:T241)<>0,"Show","Hide") -> Hide | C241: 1 | D241: 3355 - Rates & Taxes | E241: 30937.26 | F241: 31845.356 | G241: =+E241-F241 -> -908.09637 | H241: 0 | I241: =+E241-H241 -> 30937.26 | J241: 24679.53 | K241: =+E241-J241 -> 6257.73 | M241: 30937.26 | N241: 31845.356 | O241: =+M241-N241 -> -908.09637 | P241: 0 | Q241: =+M241-P241 -> 30937.26 | R241: 24679.53 | S241: =+M241-R241 -> 6257.73
B242: =IF(SUM(T242:T242)<>0,"Show","Hide") -> Hide | C242: 1 | D242: 3360 - Building & Office Maintenance | E242: 8607.19 | F242: 7035.1057 | G242: =+E242-F242 -> 1572.0843 | H242: 0 | I242: =+E242-H242 -> 8607.19 | J242: 3174.12 | K242: =+E242-J242 -> 5433.07 | M242: 8607.19 | N242: 7035.1057 | O242: =+M242-N242 -> 1572.0843 | P242: 0 | Q242: =+M242-P242 -> 8607.19 | R242: 3174.12 | S242: =+M242-R242 -> 5433.07
B243: =IF(SUM(T243:T243)<>0,"Show","Hide") -> Hide | C243: 1 | D243: 3368 - Premises Cleaning | E243: 1121.05 | F243: 1518.9076 | G243: =+E243-F243 -> -397.85756 | H243: 0 | I243: =+E243-H243 -> 1121.05 | J243: 870.61 | K243: =+E243-J243 -> 250.44 | M243: 1121.05 | N243: 1518.9076 | O243: =+M243-N243 -> -397.85756 | P243: 0 | Q243: =+M243-P243 -> 1121.05 | R243: 870.61 | S243: =+M243-R243 -> 250.44
B244: =IF(SUM(T244:T244)<>0,"Show","Hide") -> Hide | C244: 1 | D244: 3560 - Security | E244: 1450.86 | F244: 1475.2947 | G244: =+E244-F244 -> -24.434662 | H244: 0 | I244: =+E244-H244 -> 1450.86 | J244: 3786.03 | K244: =+E244-J244 -> -2335.17 | M244: 1450.86 | N244: 1475.2947 | O244: =+M244-N244 -> -24.434662 | P244: 0 | Q244: =+M244-P244 -> 1450.86 | R244: 3786.03 | S244: =+M244-R244 -> -2335.17
B245: =IF(SUM(T245:T245)<>0,"Show","Hide") -> Hide | C245: 1 | D245: 4357 - Environmental Costs | E245: 8701.14 | F245: 7929.0875 | G245: =+E245-F245 -> 772.05245 | H245: 0 | I245: =+E245-H245 -> 8701.14 | J245: 12158.32 | K245: =+E245-J245 -> -3457.18 | M245: 8701.14 | N245: 7929.0875 | O245: =+M245-N245 -> 772.05245 | P245: 0 | Q245: =+M245-P245 -> 8701.14 | R245: 12158.32 | S245: =+M245-R245 -> -3457.18
...

Sheet IS East
E1: 1 | F1: 1 | G1: 1 | J1: 1 | K1: 1 | L1: 1 | M1: 1 | N1: 1 | Q1: 1 | R1: 1 | S1: 1 | U1: 2 | V1: =+U1 -> 2 | W1: =+V1 -> 2 | X1: =+W1 -> 2 | Y1: =+X1 -> 2 | Z1: =+Y1 -> 2 | AA1: =+Z1 -> 2 | AB1: =+AA1 -> 2 | AC1: =+AB1 -> 2 | ... AI1: =+AH1 -> 2 | AK1: 3 | AL1: =+AK1 -> 3 | AM1: =+AL1 -> 3 | AN1: =+AM1 -> 3 | AO1: =+AN1 -> 3 | AP1: =+AO1 -> 3 | AQ1: =+AP1 -> 3 | AR1: =+AQ1 -> 3 | AS1: =+AR1 -> 3 | ... AY1: =+AX1 -> 3 | BA1: 4 | BB1: =+BA1 -> 4 | BC1: =+BB1 -> 4 | BD1: =+BC1 -> 4 | BE1: =+BD1 -> 4 | BF1: =+BE1 -> 4 | BG1: =+BF1 -> 4 | BH1: =+BG1 -> 4 | BI1: =+BH1 -> 4 | ... BO1: =+BN1 -> 4
E2: {=INDEX(East_List,E1)} -> IS_EAST BU | F2: =+E2 -> IS_EAST BU | G2: =+F2 -> IS_EAST BU | H2: =+G2 -> IS_EAST BU | I2: =+H2 -> IS_EAST BU | J2: =+I2 -> IS_EAST BU | K2: =+J2 -> IS_EAST BU | L2: {=INDEX(East_List,L1)} -> IS_EAST BU | M2: =+E2 -> IS_EAST BU | N2: =+M2 -> IS_EAST BU | O2: =+N2 -> IS_EAST BU | P2: =+O2 -> IS_EAST BU | Q2: =+P2 -> IS_EAST BU | R2: =+Q2 -> IS_EAST BU | S2: =+R2 -> IS_EAST BU | U2: {=INDEX(East_List,U1)} -> EAIS | V2: =+U2 -> EAIS | W2: =+V2 -> EAIS | X2: =+W2 -> EAIS | Y2: =+X2 -> EAIS | Z2: =+Y2 -> EAIS | AA2: =+Z2 -> EAIS | AB2: {=INDEX(East_List,AB1)} -> EAIS | AC2: =+U2 -> EAIS | AD2: =+AC2 -> EAIS | AE2: =+AD2 -> EAIS | AF2: =+AE2 -> EAIS | AG2: =+AF2 -> EAIS | AH2: =+AG2 -> EAIS | AI2: =+AH2 -> EAIS | AK2: {=INDEX(East_List,AK1)} -> THOR | AL2: =+AK2 -> THOR | AM2: =+AL2 -> THOR | AN2: =+AM2 -> THOR | AO2: =+AN2 -> THOR | AP2: =+AO2 -> THOR | AQ2: =+AP2 -> THOR | AR2: {=INDEX(East_List,AR1)} -> THOR | AS2: =+AK2 -> THOR | AT2: =+AS2 -> THOR | AU2: =+AT2 -> THOR | AV2: =+AU2 -> THOR | AW2: =+AV2 -> THOR | AX2: =+AW2 -> THOR | AY2: =+AX2 -> THOR | BA2: {=INDEX(East_List,BA1)} -> ISNS | BB2: =+BA2 -> ISNS | BC2: =+BB2 -> ISNS | BD2: =+BC2 -> ISNS | BE2: =+BD2 -> ISNS | BF2: =+BE2 -> ISNS | BG2: =+BF2 -> ISNS | BH2: {=INDEX(East_List,BH1)} -> ISNS | BI2: =+BA2 -> ISNS | BJ2: =+BI2 -> ISNS | BK2: =+BJ2 -> ISNS | BL2: =+BK2 -> ISNS | BM2: =+BL2 -> ISNS | BN2: =+BM2 -> ISNS | BO2: =+BN2 -> ISNS
A3: Total Add-On Revenue | E3: =+Parameters!$B$5 -> Actual | F3: =+Parameters!$B$6 -> Target Budget | H3: =+Parameters!$B$7 -> Forecast Current | J3: =+Parameters!$B$5 -> Actual | M3: =+Parameters!$B$5 -> Actual | N3: =+Parameters!$B$6 -> Target Budget | P3: =+Parameters!$B$7 -> Forecast Current | R3: =+Parameters!$B$5 -> Actual | U3: =+Parameters!$B$5 -> Actual | V3: =+Parameters!$B$6 -> Target Budget | X3: =+Parameters!$B$7 -> Forecast Current | Z3: =+Parameters!$B$5 -> Actual | AC3: =+Parameters!$B$5 -> Actual | AD3: =+Parameters!$B$6 -> Target Budget | AF3: =+Parameters!$B$7 -> Forecast Current | AH3: =+Parameters!$B$5 -> Actual | AK3: =+Parameters!$B$5 -> Actual | AL3: =+Parameters!$B$6 -> Target Budget | AN3: =+Parameters!$B$7 -> Forecast Current | AP3: =+Parameters!$B$5 -> Actual | AS3: =+Parameters!$B$5 -> Actual | AT3: =+Parameters!$B$6 -> Target Budget | AV3: =+Parameters!$B$7 -> Forecast Current | AX3: =+Parameters!$B$5 -> Actual | BA3: =+Parameters!$B$5 -> Actual | BB3: =+Parameters!$B$6 -> Target Budget | BD3: =+Parameters!$B$7 -> Forecast Current | BF3: =+Parameters!$B$5 -> Actual | BI3: =+Parameters!$B$5 -> Actual | BJ3: =+Parameters!$B$6 -> Target Budget | BL3: =+Parameters!$B$7 -> Forecast Current | BN3: =+Parameters!$B$5 -> Actual
A4: EBIT - Branch | E4: =+Parameters!$B$10 -> 2026 | F4: =+Parameters!$B$10 -> 2026 | H4: =+Parameters!$B$10 -> 2026 | J4: =+E4-1 -> 2025 | M4: =+E4 -> 2026 | N4: =+F4 -> 2026 | P4: =+H4 -> 2026 | R4: =+J4 -> 2025 | U4: =+Parameters!$B$10 -> 2026 | V4: =+Parameters!$B$10 -> 2026 | X4: =+Parameters!$B$10 -> 2026 | Z4: =+U4-1 -> 2025 | AC4: =+U4 -> 2026 | AD4: =+V4 -> 2026 | AF4: =+X4 -> 2026 | AH4: =+Z4 -> 2025 | AK4: =+Parameters!$B$10 -> 2026 | AL4: =+Parameters!$B$10 -> 2026 | AN4: =+Parameters!$B$10 -> 2026 | AP4: =+AK4-1 -> 2025 | AS4: =+AK4 -> 2026 | AT4: =+AL4 -> 2026 | AV4: =+AN4 -> 2026 | AX4: =+AP4 -> 2025 | BA4: =+Parameters!$B$10 -> 2026 | BB4: =+Parameters!$B$10 -> 2026 | BD4: =+Parameters!$B$10 -> 2026 | BF4: =+BA4-1 -> 2025 | BI4: =+BA4 -> 2026 | BJ4: =+BB4 -> 2026 | BL4: =+BD4 -> 2026 | BN4: =+BF4 -> 2025
A5: EBIT - Post Allocations | E5: =+Parameters!$B$9 -> Jul | F5: =+Parameters!$B$9 -> Jul | H5: =+Month -> Jul | J5: =+F5 -> Jul | M5: =CONCATENATE(E5," ","YTD") -> Jul YTD | N5: =CONCATENATE(F5," ","YTD") -> Jul YTD | P5: =CONCATENATE(H5," ","YTD") -> Jul YTD | R5: =CONCATENATE(J5," ","YTD") -> Jul YTD | U5: =+Parameters!$B$9 -> Jul | V5: =+Parameters!$B$9 -> Jul | X5: =+Month -> Jul | Z5: =+V5 -> Jul | AC5: =CONCATENATE(U5," ","YTD") -> Jul YTD | AD5: =CONCATENATE(V5," ","YTD") -> Jul YTD | AF5: =CONCATENATE(X5," ","YTD") -> Jul YTD | AH5: =CONCATENATE(Z5," ","YTD") -> Jul YTD | AK5: =+Parameters!$B$9 -> Jul | AL5: =+Parameters!$B$9 -> Jul | AN5: =+Month -> Jul | AP5: =+AL5 -> Jul | AS5: =CONCATENATE(AK5," ","YTD") -> Jul YTD | AT5: =CONCATENATE(AL5," ","YTD") -> Jul YTD | AV5: =CONCATENATE(AN5," ","YTD") -> Jul YTD | AX5: =CONCATENATE(AP5," ","YTD") -> Jul YTD | BA5: =+Parameters!$B$9 -> Jul | BB5: =+Parameters!$B$9 -> Jul | BD5: =+Month -> Jul | BF5: =+BB5 -> Jul | BI5: =CONCATENATE(BA5," ","YTD") -> Jul YTD | BJ5: =CONCATENATE(BB5," ","YTD") -> Jul YTD | BL5: =CONCATENATE(BD5," ","YTD") -> Jul YTD | BN5: =CONCATENATE(BF5," ","YTD") -> Jul YTD
E6: East - Industrial Solutions | M6: =+E6 -> East - Industrial Solutions | U6: =+U2 -> EAIS | AC6: =+U6 -> EAIS | AK6: =+AK2 -> THOR | AS6: =+AK6 -> THOR | BA6: =+BA2 -> ISNS | BI6: =+BA6 -> ISNS
E7: =+"MTD "&E5&" "&YEAR -> MTD Jul 2026 | M7: =+"YTD "&E5&" "&YEAR -> YTD Jul 2026 | U7: =+"MTD "&E5&" "&YEAR -> MTD Jul 2026 | AC7: =+"YTD "&E5&" "&YEAR -> YTD Jul 2026 | AK7: =+"MTD "&E5&" "&YEAR -> MTD Jul 2026 | AS7: =+"YTD "&E5&" "&YEAR -> YTD Jul 2026 | BA7: =+"MTD "&E5&" "&YEAR -> MTD Jul 2026 | BI7: =+"YTD "&E5&" "&YEAR -> YTD Jul 2026
E8: ACTUALS | F8: BUDGET | G8: VAR BUD | H8: FORECAST | I8: VAR FORECAST | J8: LAST YEAR | K8: VAR LY | M8: ACTUALS | N8: BUDGET | O8: VAR BUD | P8: FORECAST | Q8: VAR FORECAST | R8: LAST YEAR | S8: VAR LY | U8: ACTUALS | V8: BUDGET | W8: VAR BUD | X8: FORECAST | Y8: VAR FORECAST | Z8: LAST YEAR | AA8: VAR LY | AC8: ACTUALS | AD8: BUDGET | AE8: VAR BUD | AF8: FORECAST | AG8: VAR FORECAST | AH8: LAST YEAR | AI8: VAR LY | AK8: ACTUALS | AL8: BUDGET | AM8: VAR BUD | AN8: FORECAST | AO8: VAR FORECAST | AP8: LAST YEAR | AQ8: VAR LY | AS8: ACTUALS | AT8: BUDGET | AU8: VAR BUD | AV8: FORECAST | AW8: VAR FORECAST | AX8: LAST YEAR | AY8: VAR LY | BA8: ACTUALS | BB8: BUDGET | BC8: VAR BUD | BD8: FORECAST | BE8: VAR FORECAST | BF8: LAST YEAR | BG8: VAR LY | BI8: ACTUALS | BJ8: BUDGET | BK8: VAR BUD | BL8: FORECAST | BM8: VAR FORECAST | BN8: LAST YEAR | BO8: VAR LY
A9: Total Add-On Expenses | D9: REVENUE
A10: Gross Margin - Branch | B10: =IF(SUM(T10:T10)<>0,"Show","Hide") -> Hide | C10: -1 | D10: 1005 - Hire Revenue - Hire Fleet | E10: 305395.29 | F10: 335272.03 | G10: =+E10-F10 -> -29876.738 | J10: 369272.43 | K10: =+E10-J10 -> -63877.14 | M10: 305395.29 | N10: 335272.03 | Q10: =+M10-N10 -> -29876.738 | R10: 369272.43 | S10: =+M10-R10 -> -63877.14 | U10: 214936.26 | V10: 245640.64 | W10: =+U10-V10 -> -30704.376 | Z10: 234459.03 | AA10: =+U10-Z10 -> -19522.77 | AC10: 214936.26 | AD10: 245640.64 | AG10: =+AC10-AD10 -> -30704.376 | AH10: 234459.03 | AI10: =+AC10-AH10 -> -19522.77 | AK10: 70943.42 | AL10: 80295.746 | AM10: =+AK10-AL10 -> -9352.3258 | AP10: 106648.37 | AQ10: =+AK10-AP10 -> -35704.95 | AS10: 70943.42 | AT10: 80295.746 | AW10: =+AS10-AT10 -> -9352.3258 | AX10: 106648.37 | AY10: =+AS10-AX10 -> -35704.95 | BA10: 19515.61 | BB10: 9335.6462 | BC10: =+BA10-BB10 -> 10179.964 | BF10: 28165.03 | BG10: =+BA10-BF10 -> -8649.42 | BI10: 19515.61 | BJ10: 9335.6462 | BM10: =+BI10-BJ10 -> 10179.964 | BN10: 28165.03 | BO10: =+BI10-BN10 -> -8649.42
A11: Gross Margin - Post Allocations | B11: =IF(SUM(T11:T11)<>0,"Show","Hide") -> Hide | C11: -1 | D11: 1007 - Cash Sales Contra | E11: 0 | F11: 0 | G11: =+E11-F11 -> 0 | J11: 0 | K11: =+E11-J11 -> 0 | M11: 0 | N11: 0 | Q11: =+M11-N11 -> 0 | R11: 0 | S11: =+M11-R11 -> 0 | U11: 0 | V11: 0 | W11: =+U11-V11 -> 0 | Z11: 0 | AA11: =+U11-Z11 -> 0 | AC11: 0 | AD11: 0 | AG11: =+AC11-AD11 -> 0 | AH11: 0 | AI11: =+AC11-AH11 -> 0 | AK11: 0 | AL11: 0 | AM11: =+AK11-AL11 -> 0 | AP11: 0 | AQ11: =+AK11-AP11 -> 0 | AS11: 0 | AT11: 0 | AW11: =+AS11-AT11 -> 0 | AX11: 0 | AY11: =+AS11-AX11 -> 0 | BA11: 0 | BB11: 0 | BC11: =+BA11-BB11 -> 0 | BF11: 0 | BG11: =+BA11-BF11 -> 0 | BI11: 0 | BJ11: 0 | BM11: =+BI11-BJ11 -> 0 | BN11: 0 | BO11: =+BI11-BN11 -> 0
A12: Interest - Branch | B12: =IF(SUM(T12:T12)<>0,"Show","Hide") -> Hide | C12: -1 | D12: 1008 - Hire Revenue - Accrual | E12: -8101.38 | F12: 8363.8914 | G12: =+E12-F12 -> -16465.271 | J12: -26179.86 | K12: =+E12-J12 -> 18078.48 | M12: -8101.38 | N12: 8363.8914 | Q12: =+M12-N12 -> -16465.271 | R12: -26179.86 | S12: =+M12-R12 -> 18078.48 | U12: -10782.86 | V12: 6381.9408 | W12: =+U12-V12 -> -17164.801 | Z12: -35430.62 | AA12: =+U12-Z12 -> 24647.76 | AC12: -10782.86 | AD12: 6381.9408 | AG12: =+AC12-AD12 -> -17164.801 | AH12: -35430.62 | AI12: =+AC12-AH12 -> 24647.76 | AK12: 906.48 | AL12: 2268.2216 | AM12: =+AK12-AL12 -> -1361.7416 | AP12: 805.46 | AQ12: =+AK12-AP12 -> 101.02 | AS12: 906.48 | AT12: 2268.2216 | AW12: =+AS12-AT12 -> -1361.7416 | AX12: 805.46 | AY12: =+AS12-AX12 -> 101.02 | BA12: 1775 | BB12: -286.27103 | BC12: =+BA12-BB12 -> 2061.271 | BF12: 8445.3 | BG12: =+BA12-BF12 -> -6670.3 | BI12: 1775 | BJ12: -286.27103 | BM12: =+BI12-BJ12 -> 2061.271 | BN12: 8445.3 | BO12: =+BI12-BN12 -> -6670.3
A13: Interest - Post Allocations | B13: =IF(SUM(T13:T13)<>0,"Show","Hide") -> Hide | C13: -1 | D13: 1054 - Hire Rebates | E13: -1460.2 | F13: -1237.7867 | G13: =+E13-F13 -> -222.41333 | J13: -3195.37 | K13: =+E13-J13 -> 1735.17 | M13: -1460.2 | N13: -1237.7867 | Q13: =+M13-N13 -> -222.41333 | R13: -3195.37 | S13: =+M13-R13 -> 1735.17 | U13: -1085.5 | V13: -765.00862 | W13: =+U13-V13 -> -320.49138 | Z13: -1475.14 | AA13: =+U13-Z13 -> 389.64 | AC13: -1085.5 | AD13: -765.00862 | AG13: =+AC13-AD13 -> -320.49138 | AH13: -1475.14 | AI13: =+AC13-AH13 -> 389.64 | AK13: -374.7 | AL13: -176.0971 | AM13: =+AK13-AL13 -> -198.6029 | AP13: -118.39 | AQ13: =+AK13-AP13 -> -256.31 | AS13: -374.7 | AT13: -176.0971 | AW13: =+AS13-AT13 -> -198.6029 | AX13: -118.39 | AY13: =+AS13-AX13 -> -256.31 | BA13: 0 | BB13: -296.68094 | BC13: =+BA13-BB13 -> 296.68094 | BF13: -1601.84 | BG13: =+BA13-BF13 -> 1601.84 | BI13: 0 | BJ13: -296.68094 | BM13: =+BI13-BJ13 -> 296.68094 | BN13: -1601.84 | BO13: =+BI13-BN13 -> 1601.84
A14: PBT - Branch | B14: =IF(SUM(T14:T14)<>0,"Show","Hide") -> Hide | C14: -1 | D14: Hire Revenue | E14: 295833.71 | F14: 342398.13 | G14: =+E14-F14 -> -46564.423 | H14: 0 | I14: =+E14-H14 -> 295833.71 | J14: 339897.2 | K14: =+E14-J14 -> -44063.49 | M14: 295833.71 | N14: 342398.13 | O14: =+M14-N14 -> -46564.423 | P14: 0 | Q14: =+M14-P14 -> 295833.71 | R14: 339897.2 | S14: =+M14-R14 -> -44063.49 | U14: 203067.9 | V14: 251257.57 | W14: =+U14-V14 -> -48189.668 | X14: 0 | Y14: =+U14-X14 -> 203067.9 | Z14: 197553.27 | AA14: =+U14-Z14 -> 5514.63 | AC14: 203067.9 | AD14: 251257.57 | AE14: =+AC14-AD14 -> -48189.668 | AF14: 0 | AG14: =+AC14-AF14 -> 203067.9 | AH14: 197553.27 | AI14: =+AC14-AH14 -> 5514.63 | AK14: 71475.2 | AL14: 82387.87 | AM14: =+AK14-AL14 -> -10912.67 | AN14: 0 | AO14: =+AK14-AN14 -> 71475.2 | AP14: 107335.44 | AQ14: =+AK14-AP14 -> -35860.24 | AS14: 71475.2 | AT14: 82387.87 | AU14: =+AS14-AT14 -> -10912.67 | AV14: 0 | AW14: =+AS14-AV14 -> 71475.2 | AX14: 107335.44 | AY14: =+AS14-AX14 -> -35860.24 | BA14: 21290.61 | BB14: 8752.6942 | BC14: =+BA14-BB14 -> 12537.916 | BD14: 0 | BE14: =+BA14-BD14 -> 21290.61 | BF14: 35008.49 | BG14: =+BA14-BF14 -> -13717.88 | BI14: 21290.61 | BJ14: 8752.6942 | BK14: =+BI14-BJ14 -> 12537.916 | BL14: 0 | BM14: =+BI14-BL14 -> 21290.61 | BN14: 35008.49 | BO14: =+BI14-BN14 -> -13717.88
A15: PBT - Post Allocations | B15: =IF(SUM(T15:T15)<>0,"Show","Hide") -> Hide | C15: -1 | D15: 1010 - Hire Revenue - Rehire | E15: 31460.19 | F15: 58193.218 | G15: =+E15-F15 -> -26733.028 | H15: 0 | J15: 12448.17 | K15: =+E15-J15 -> 19012.02 | M15: 31460.19 | N15: 58193.218 | O15: =+M15-N15 -> -26733.028 | P15: 0 | Q15: =+M15-P15 -> 31460.19 | R15: 12448.17 | S15: =+M15-R15 -> 19012.02 | U15: 21744.05 | V15: 38502.698 | W15: =+U15-V15 -> -16758.648 | X15: 0 | Z15: 8535.86 | AA15: =+U15-Z15 -> 13208.19 | AC15: 21744.05 | AD15: 38502.698 | AE15: =+AC15-AD15 -> -16758.648 | AF15: 0 | AG15: =+AC15-AF15 -> 21744.05 | AH15: 8535.86 | AI15: =+AC15-AH15 -> 13208.19 | AK15: 9716.14 | AL15: 19690.52 | AM15: =+AK15-AL15 -> -9974.3796 | AN15: 0 | AP15: 3912.31 | AQ15: =+AK15-AP15 -> 5803.83 | AS15: 9716.14 | AT15: 19690.52 | AU15: =+AS15-AT15 -> -9974.3796 | AV15: 0 | AW15: =+AS15-AV15 -> 9716.14 | AX15: 3912.31 | AY15: =+AS15-AX15 -> 5803.83 | BA15: 0 | BB15: 0 | BC15: =+BA15-BB15 -> 0 | BD15: 0 | BF15: 0 | BG15: =+BA15-BF15 -> 0 | BI15: 0 | BJ15: 0 | BK15: =+BI15-BJ15 -> 0 | BL15: 0 | BM15: =+BI15-BL15 -> 0 | BN15: 0 | BO15: =+BI15-BN15 -> 0
A16: Depreciation - Hire Fleet | B16: =IF(SUM(T16:T16)<>0,"Show","Hide") -> Hide | C16: -1 | D16: 1011 - Hire Revenue - Rehire Internal | E16: 0 | F16: 0 | G16: =+E16-F16 -> 0 | H16: 0 | J16: 0 | K16: =+E16-J16 -> 0 | M16: 0 | N16: 0 | O16: =+M16-N16 -> 0 | P16: 0 | Q16: =+M16-P16 -> 0 | R16: 0 | S16: =+M16-R16 -> 0 | U16: 0 | V16: 0 | W16: =+U16-V16 -> 0 | X16: 0 | Z16: 0 | AA16: =+U16-Z16 -> 0 | AC16: 0 | AD16: 0 | AE16: =+AC16-AD16 -> 0 | AF16: 0 | AG16: =+AC16-AF16 -> 0 | AH16: 0 | AI16: =+AC16-AH16 -> 0 | AK16: 0 | AL16: 0 | AM16: =+AK16-AL16 -> 0 | AN16: 0 | AP16: 0 | AQ16: =+AK16-AP16 -> 0 | AS16: 0 | AT16: 0 | AU16: =+AS16-AT16 -> 0 | AV16: 0 | AW16: =+AS16-AV16 -> 0 | AX16: 0 | AY16: =+AS16-AX16 -> 0 | BA16: 0 | BB16: 0 | BC16: =+BA16-BB16 -> 0 | BD16: 0 | BF16: 0 | BG16: =+BA16-BF16 -> 0 | BI16: 0 | BJ16: 0 | BK16: =+BI16-BJ16 -> 0 | BL16: 0 | BM16: =+BI16-BL16 -> 0 | BN16: 0 | BO16: =+BI16-BN16 -> 0
A17: Depreciation - Other | B17: =IF(SUM(T17:T17)<>0,"Show","Hide") -> Hide | C17: -1 | D17: Rehire Revenue | E17: 31460.19 | F17: 58193.218 | G17: =+E17-F17 -> -26733.028 | H17: 0 | I17: =+E17-H17 -> 31460.19 | J17: 12448.17 | K17: =+E17-J17 -> 19012.02 | M17: 31460.19 | N17: 58193.218 | O17: =+M17-N17 -> -26733.028 | P17: 0 | Q17: =+M17-P17 -> 31460.19 | R17: 12448.17 | S17: =+M17-R17 -> 19012.02 | U17: 21744.05 | V17: 38502.698 | W17: =+U17-V17 -> -16758.648 | X17: 0 | Y17: =+U17-X17 -> 21744.05 | Z17: 8535.86 | AA17: =+U17-Z17 -> 13208.19 | AC17: 21744.05 | AD17: 38502.698 | AE17: =+AC17-AD17 -> -16758.648 | AF17: 0 | AG17: =+AC17-AF17 -> 21744.05 | AH17: 8535.86 | AI17: =+AC17-AH17 -> 13208.19 | AK17: 9716.14 | AL17: 19690.52 | AM17: =+AK17-AL17 -> -9974.3796 | AN17: 0 | AO17: =+AK17-AN17 -> 9716.14 | AP17: 3912.31 | AQ17: =+AK17-AP17 -> 5803.83 | AS17: 9716.14 | AT17: 19690.52 | AU17: =+AS17-AT17 -> -9974.3796 | AV17: 0 | AW17: =+AS17-AV17 -> 9716.14 | AX17: 3912.31 | AY17: =+AS17-AX17 -> 5803.83 | BA17: 0 | BB17: 0 | BC17: =+BA17-BB17 -> 0 | BD17: 0 | BE17: =+BA17-BD17 -> 0 | BF17: 0 | BG17: =+BA17-BF17 -> 0 | BI17: 0 | BJ17: 0 | BK17: =+BI17-BJ17 -> 0 | BL17: 0 | BM17: =+BI17-BL17 -> 0 | BN17: 0 | BO17: =+BI17-BN17 -> 0
A18: EBITDA - Branch | B18: =IF(SUM(T18:T18)<>0,"Show","Hide") -> Hide | C18: -1 | D18: Total Hire Revenue | E18: 327293.9 | F18: 400591.35 | G18: =+E18-F18 -> -73297.451 | H18: 0 | I18: =+E18-H18 -> 327293.9 | J18: 352345.37 | K18: =+E18-J18 -> -25051.47 | M18: 327293.9 | N18: 400591.35 | O18: =+M18-N18 -> -73297.451 | P18: 0 | Q18: =+M18-P18 -> 327293.9 | R18: 352345.37 | S18: =+M18-R18 -> -25051.47 | U18: 224811.95 | V18: 289760.27 | W18: =+U18-V18 -> -64948.317 | X18: 0 | Y18: =+U18-X18 -> 224811.95 | Z18: 206089.13 | AA18: =+U18-Z18 -> 18722.82 | AC18: 224811.95 | AD18: 289760.27 | AE18: =+AC18-AD18 -> -64948.317 | AF18: 0 | AG18: =+AC18-AF18 -> 224811.95 | AH18: 206089.13 | AI18: =+AC18-AH18 -> 18722.82 | AK18: 81191.34 | AL18: 102078.39 | AM18: =+AK18-AL18 -> -20887.05 | AN18: 0 | AO18: =+AK18-AN18 -> 81191.34 | AP18: 111247.75 | AQ18: =+AK18-AP18 -> -30056.41 | AS18: 81191.34 | AT18: 102078.39 | AU18: =+AS18-AT18 -> -20887.05 | AV18: 0 | AW18: =+AS18-AV18 -> 81191.34 | AX18: 111247.75 | AY18: =+AS18-AX18 -> -30056.41 | BA18: 21290.61 | BB18: 8752.6942 | BC18: =+BA18-BB18 -> 12537.916 | BD18: 0 | BE18: =+BA18-BD18 -> 21290.61 | BF18: 35008.49 | BG18: =+BA18-BF18 -> -13717.88 | BI18: 21290.61 | BJ18: 8752.6942 | BK18: =+BI18-BJ18 -> 12537.916 | BL18: 0 | BM18: =+BI18-BL18 -> 21290.61 | BN18: 35008.49 | BO18: =+BI18-BN18 -> -13717.88
A19: EBITDA - Post Allocations | B19: =IF(SUM(T19:T19)<>0,"Show","Hide") -> Hide | C19: -1 | D19: 1030 - Hire Revenue - Cartage Internal | E19: 34016.74 | F19: 25090.627 | G19: =+E19-F19 -> 8926.113 | H19: 0 | I19: =+E19-H19 -> 34016.74 | J19: 37516.46 | K19: =+E19-J19 -> -3499.72 | M19: 34016.74 | N19: 25090.627 | O19: =+M19-N19 -> 8926.113 | P19: 0 | Q19: =+M19-P19 -> 34016.74 | R19: 37516.46 | S19: =+M19-R19 -> -3499.72 | U19: 23295.4 | V19: 13728.289 | W19: =+U19-V19 -> 9567.1107 | X19: 0 | Y19: =+U19-X19 -> 23295.4 | Z19: 23975.83 | AA19: =+U19-Z19 -> -680.43 | AC19: 23295.4 | AD19: 13728.289 | AE19: =+AC19-AD19 -> 9567.1107 | AF19: 0 | AG19: =+AC19-AF19 -> 23295.4 | AH19: 23975.83 | AI19: =+AC19-AH19 -> -680.43 | AK19: 9273.43 | AL19: 10480.851 | AM19: =+AK19-AL19 -> -1207.4213 | AN19: 0 | AO19: =+AK19-AN19 -> 9273.43 | AP19: 13160.63 | AQ19: =+AK19-AP19 -> -3887.2 | AS19: 9273.43 | AT19: 10480.851 | AU19: =+AS19-AT19 -> -1207.4213 | AV19: 0 | AW19: =+AS19-AV19 -> 9273.43 | AX19: 13160.63 | AY19: =+AS19-AX19 -> -3887.2 | BA19: 1447.91 | BB19: 881.48632 | BC19: =+BA19-BB19 -> 566.42368 | BD19: 0 | BE19: =+BA19-BD19 -> 1447.91 | BF19: 380 | BG19: =+BA19-BF19 -> 1067.91 | BI19: 1447.91 | BJ19: 881.48632 | BK19: =+BI19-BJ19 -> 566.42368 | BL19: 0 | BM19: =+BI19-BL19 -> 1447.91 | BN19: 380 | BO19: =+BI19-BN19 -> 1067.91
B20: =IF(SUM(T20:T20)<>0,"Show","Hide") -> Hide | C20: -1 | D20: 1031 - Hire Revenue - Cartage External | E20: 0 | F20: 25328.057 | G20: =+E20-F20 -> -25328.057 | H20: 0 | I20: =+E20-H20 -> 0 | J20: 0 | K20: =+E20-J20 -> 0 | M20: 0 | N20: 25328.057 | O20: =+M20-N20 -> -25328.057 | P20: 0 | Q20: =+M20-P20 -> 0 | R20: 0 | S20: =+M20-R20 -> 0 | U20: 0 | V20: 25328.057 | W20: =+U20-V20 -> -25328.057 | X20: 0 | Y20: =+U20-X20 -> 0 | Z20: 0 | AA20: =+U20-Z20 -> 0 | AC20: 0 | AD20: 25328.057 | AE20: =+AC20-AD20 -> -25328.057 | AF20: 0 | AG20: =+AC20-AF20 -> 0 | AH20: 0 | AI20: =+AC20-AH20 -> 0 | AK20: 0 | AL20: 0 | AM20: =+AK20-AL20 -> 0 | AN20: 0 | AO20: =+AK20-AN20 -> 0 | AP20: 0 | AQ20: =+AK20-AP20 -> 0 | AS20: 0 | AT20: 0 | AU20: =+AS20-AT20 -> 0 | AV20: 0 | AW20: =+AS20-AV20 -> 0 | AX20: 0 | AY20: =+AS20-AX20 -> 0 | BA20: 0 | BB20: 0 | BC20: =+BA20-BB20 -> 0 | BD20: 0 | BE20: =+BA20-BD20 -> 0 | BF20: 0 | BG20: =+BA20-BF20 -> 0 | BI20: 0 | BJ20: 0 | BK20: =+BI20-BJ20 -> 0 | BL20: 0 | BM20: =+BI20-BL20 -> 0 | BN20: 0 | BO20: =+BI20-BN20 -> 0
B21: =IF(SUM(T21:T21)<>0,"Show","Hide") -> Hide | C21: -1 | D21: 1032 - Hire Revenue - Toilet Pumpouts | E21: 0 | F21: 0 | G21: =+E21-F21 -> 0 | H21: 0 | I21: =+E21-H21 -> 0 | J21: 0 | K21: =+E21-J21 -> 0 | M21: 0 | N21: 0 | O21: =+M21-N21 -> 0 | P21: 0 | Q21: =+M21-P21 -> 0 | R21: 0 | S21: =+M21-R21 -> 0 | U21: 0 | V21: 0 | W21: =+U21-V21 -> 0 | X21: 0 | Y21: =+U21-X21 -> 0 | Z21: 0 | AA21: =+U21-Z21 -> 0 | AC21: 0 | AD21: 0 | AE21: =+AC21-AD21 -> 0 | AF21: 0 | AG21: =+AC21-AF21 -> 0 | AH21: 0 | AI21: =+AC21-AH21 -> 0 | AK21: 0 | AL21: 0 | AM21: =+AK21-AL21 -> 0 | AN21: 0 | AO21: =+AK21-AN21 -> 0 | AP21: 0 | AQ21: =+AK21-AP21 -> 0 | AS21: 0 | AT21: 0 | AU21: =+AS21-AT21 -> 0 | AV21: 0 | AW21: =+AS21-AV21 -> 0 | AX21: 0 | AY21: =+AS21-AX21 -> 0 | BA21: 0 | BB21: 0 | BC21: =+BA21-BB21 -> 0 | BD21: 0 | BE21: =+BA21-BD21 -> 0 | BF21: 0 | BG21: =+BA21-BF21 -> 0 | BI21: 0 | BJ21: 0 | BK21: =+BI21-BJ21 -> 0 | BL21: 0 | BM21: =+BI21-BL21 -> 0 | BN21: 0 | BO21: =+BI21-BN21 -> 0
B22: =IF(SUM(T22:T22)<>0,"Show","Hide") -> Hide | C22: -1 | D22: Transport | E22: 34016.74 | F22: 50418.684 | G22: =+E22-F22 -> -16401.944 | H22: 0 | I22: =+E22-H22 -> 34016.74 | J22: 37516.46 | K22: =+E22-J22 -> -3499.72 | M22: 34016.74 | N22: 50418.684 | O22: =+M22-N22 -> -16401.944 | P22: 0 | Q22: =+M22-P22 -> 34016.74 | R22: 37516.46 | S22: =+M22-R22 -> -3499.72 | U22: 23295.4 | V22: 39056.346 | W22: =+U22-V22 -> -15760.946 | X22: 0 | Y22: =+U22-X22 -> 23295.4 | Z22: 23975.83 | AA22: =+U22-Z22 -> -680.43 | AC22: 23295.4 | AD22: 39056.346 | AE22: =+AC22-AD22 -> -15760.946 | AF22: 0 | AG22: =+AC22-AF22 -> 23295.4 | AH22: 23975.83 | AI22: =+AC22-AH22 -> -680.43 | AK22: 9273.43 | AL22: 10480.851 | AM22: =+AK22-AL22 -> -1207.4213 | AN22: 0 | AO22: =+AK22-AN22 -> 9273.43 | AP22: 13160.63 | AQ22: =+AK22-AP22 -> -3887.2 | AS22: 9273.43 | AT22: 10480.851 | AU22: =+AS22-AT22 -> -1207.4213 | AV22: 0 | AW22: =+AS22-AV22 -> 9273.43 | AX22: 13160.63 | AY22: =+AS22-AX22 -> -3887.2 | BA22: 1447.91 | BB22: 881.48632 | BC22: =+BA22-BB22 -> 566.42368 | BD22: 0 | BE22: =+BA22-BD22 -> 1447.91 | BF22: 380 | BG22: =+BA22-BF22 -> 1067.91 | BI22: 1447.91 | BJ22: 881.48632 | BK22: =+BI22-BJ22 -> 566.42368 | BL22: 0 | BM22: =+BI22-BL22 -> 1447.91 | BN22: 380 | BO22: =+BI22-BN22 -> 1067.91
B23: =IF(SUM(T23:T23)<>0,"Show","Hide") -> Hide | C23: -1 | D23: 1020 - Hire Revenue - Consumables | E23: 9780 | F23: 22252.676 | G23: =+E23-F23 -> -12472.676 | H23: 0 | I23: =+E23-H23 -> 9780 | J23: 41056.81 | K23: =+E23-J23 -> -31276.81 | M23: 9780 | N23: 22252.676 | O23: =+M23-N23 -> -12472.676 | P23: 0 | Q23: =+M23-P23 -> 9780 | R23: 41056.81 | S23: =+M23-R23 -> -31276.81 | U23: 9780 | V23: 14668.456 | W23: =+U23-V23 -> -4888.4563 | X23: 0 | Y23: =+U23-X23 -> 9780 | Z23: 825.16 | AA23: =+U23-Z23 -> 8954.84 | AC23: 9780 | AD23: 14668.456 | AE23: =+AC23-AD23 -> -4888.4563 | AF23: 0 | AG23: =+AC23-AF23 -> 9780 | AH23: 825.16 | AI23: =+AC23-AH23 -> 8954.84 | AK23: 0 | AL23: 7584.2193 | AM23: =+AK23-AL23 -> -7584.2193 | AN23: 0 | AO23: =+AK23-AN23 -> 0 | AP23: 40231.65 | AQ23: =+AK23-AP23 -> -40231.65 | AS23: 0 | AT23: 7584.2193 | AU23: =+AS23-AT23 -> -7584.2193 | AV23: 0 | AW23: =+AS23-AV23 -> 0 | AX23: 40231.65 | AY23: =+AS23-AX23 -> -40231.65 | BA23: 0 | BB23: 0 | BC23: =+BA23-BB23 -> 0 | BD23: 0 | BE23: =+BA23-BD23 -> 0 | BF23: 0 | BG23: =+BA23-BF23 -> 0 | BI23: 0 | BJ23: 0 | BK23: =+BI23-BJ23 -> 0 | BL23: 0 | BM23: =+BI23-BL23 -> 0 | BN23: 0 | BO23: =+BI23-BN23 -> 0
B24: =IF(SUM(T24:T24)<>0,"Show","Hide") -> Hide | C24: -1 | D24: Consumables | E24: 9780 | F24: 22252.676 | G24: =+E24-F24 -> -12472.676 | H24: 0 | I24: =+E24-H24 -> 9780 | J24: 41056.81 | K24: =+E24-J24 -> -31276.81 | M24: 9780 | N24: 22252.676 | O24: =+M24-N24 -> -12472.676 | P24: 0 | Q24: =+M24-P24 -> 9780 | R24: 41056.81 | S24: =+M24-R24 -> -31276.81 | U24: 9780 | V24: 14668.456 | W24: =+U24-V24 -> -4888.4563 | X24: 0 | Y24: =+U24-X24 -> 9780 | Z24: 825.16 | AA24: =+U24-Z24 -> 8954.84 | AC24: 9780 | AD24: 14668.456 | AE24: =+AC24-AD24 -> -4888.4563 | AF24: 0 | AG24: =+AC24-AF24 -> 9780 | AH24: 825.16 | AI24: =+AC24-AH24 -> 8954.84 | AK24: 0 | AL24: 7584.2193 | AM24: =+AK24-AL24 -> -7584.2193 | AN24: 0 | AO24: =+AK24-AN24 -> 0 | AP24: 40231.65 | AQ24: =+AK24-AP24 -> -40231.65 | AS24: 0 | AT24: 7584.2193 | AU24: =+AS24-AT24 -> -7584.2193 | AV24: 0 | AW24: =+AS24-AV24 -> 0 | AX24: 40231.65 | AY24: =+AS24-AX24 -> -40231.65 | BA24: 0 | BB24: 0 | BC24: =+BA24-BB24 -> 0 | BD24: 0 | BE24: =+BA24-BD24 -> 0 | BF24: 0 | BG24: =+BA24-BF24 -> 0 | BI24: 0 | BJ24: 0 | BK24: =+BI24-BJ24 -> 0 | BL24: 0 | BM24: =+BI24-BL24 -> 0 | BN24: 0 | BO24: =+BI24-BN24 -> 0
B25: =IF(SUM(T25:T25)<>0,"Show","Hide") -> Hide | C25: -1 | D25: 1047 - Hire Revenue - Installation | E25: 15402 | F25: 50156.117 | G25: =+E25-F25 -> -34754.117 | H25: 0 | I25: =+E25-H25 -> 15402 | J25: -760 | K25: =+E25-J25 -> 16162 | M25: 15402 | N25: 50156.117 | O25: =+M25-N25 -> -34754.117 | P25: 0 | Q25: =+M25-P25 -> 15402 | R25: -760 | S25: =+M25-R25 -> 16162 | U25: 15402 | V25: 50111.831 | W25: =+U25-V25 -> -34709.831 | X25: 0 | Y25: =+U25-X25 -> 15402 | Z25: -760 | AA25: =+U25-Z25 -> 16162 | AC25: 15402 | AD25: 50111.831 | AE25: =+AC25-AD25 -> -34709.831 | AF25: 0 | AG25: =+AC25-AF25 -> 15402 | AH25: -760 | AI25: =+AC25-AH25 -> 16162 | AK25: 0 | AL25: 44.286133 | AM25: =+AK25-AL25 -> -44.286133 | AN25: 0 | AO25: =+AK25-AN25 -> 0 | AP25: 0 | AQ25: =+AK25-AP25 -> 0 | AS25: 0 | AT25: 44.286133 | AU25: =+AS25-AT25 -> -44.286133 | AV25: 0 | AW25: =+AS25-AV25 -> 0 | AX25: 0 | AY25: =+AS25-AX25 -> 0 | BA25: 0 | BB25: 0 | BC25: =+BA25-BB25 -> 0 | BD25: 0 | BE25: =+BA25-BD25 -> 0 | BF25: 0 | BG25: =+BA25-BF25 -> 0 | BI25: 0 | BJ25: 0 | BK25: =+BI25-BJ25 -> 0 | BL25: 0 | BM25: =+BI25-BL25 -> 0 | BN25: 0 | BO25: =+BI25-BN25 -> 0
B26: =IF(SUM(T26:T26)<>0,"Show","Hide") -> Hide | C26: -1 | D26: Installation | E26: 15402 | F26: 50156.117 | G26: =+E26-F26 -> -34754.117 | H26: 0 | I26: =+E26-H26 -> 15402 | J26: -760 | K26: =+E26-J26 -> 16162 | M26: 15402 | N26: 50156.117 | O26: =+M26-N26 -> -34754.117 | P26: 0 | Q26: =+M26-P26 -> 15402 | R26: -760 | S26: =+M26-R26 -> 16162 | U26: 15402 | V26: 50111.831 | W26: =+U26-V26 -> -34709.831 | X26: 0 | Y26: =+U26-X26 -> 15402 | Z26: -760 | AA26: =+U26-Z26 -> 16162 | AC26: 15402 | AD26: 50111.831 | AE26: =+AC26-AD26 -> -34709.831 | AF26: 0 | AG26: =+AC26-AF26 -> 15402 | AH26: -760 | AI26: =+AC26-AH26 -> 16162 | AK26: 0 | AL26: 44.286133 | AM26: =+AK26-AL26 -> -44.286133 | AN26: 0 | AO26: =+AK26-AN26 -> 0 | AP26: 0 | AQ26: =+AK26-AP26 -> 0 | AS26: 0 | AT26: 44.286133 | AU26: =+AS26-AT26 -> -44.286133 | AV26: 0 | AW26: =+AS26-AV26 -> 0 | AX26: 0 | AY26: =+AS26-AX26 -> 0 | BA26: 0 | BB26: 0 | BC26: =+BA26-BB26 -> 0 | BD26: 0 | BE26: =+BA26-BD26 -> 0 | BF26: 0 | BG26: =+BA26-BF26 -> 0 | BI26: 0 | BJ26: 0 | BK26: =+BI26-BJ26 -> 0 | BL26: 0 | BM26: =+BI26-BL26 -> 0 | BN26: 0 | BO26: =+BI26-BN26 -> 0
B27: =IF(SUM(T27:T27)<>0,"Show","Hide") -> Hide | C27: -1 | D27: 1045 - Hire Revenue - Fuel | E27: 9.5 | F27: 39.229166 | G27: =+E27-F27 -> -29.729166 | H27: 0 | I27: =+E27-H27 -> 9.5 | J27: 16 | K27: =+E27-J27 -> -6.5 | M27: 9.5 | N27: 39.229166 | O27: =+M27-N27 -> -29.729166 | P27: 0 | Q27: =+M27-P27 -> 9.5 | R27: 16 | S27: =+M27-R27 -> -6.5 | U27: 4.75 | V27: 37.618761 | W27: =+U27-V27 -> -32.868761 | X27: 0 | Y27: =+U27-X27 -> 4.75 | Z27: 16 | AA27: =+U27-Z27 -> -11.25 | AC27: 4.75 | AD27: 37.618761 | AE27: =+AC27-AD27 -> -32.868761 | AF27: 0 | AG27: =+AC27-AF27 -> 4.75 | AH27: 16 | AI27: =+AC27-AH27 -> -11.25 | AK27: 4.75 | AL27: 1.6104048 | AM27: =+AK27-AL27 -> 3.1395952 | AN27: 0 | AO27: =+AK27-AN27 -> 4.75 | AP27: 0 | AQ27: =+AK27-AP27 -> 4.75 | AS27: 4.75 | AT27: 1.6104048 | AU27: =+AS27-AT27 -> 3.1395952 | AV27: 0 | AW27: =+AS27-AV27 -> 4.75 | AX27: 0 | AY27: =+AS27-AX27 -> 4.75 | BA27: 0 | BB27: 0 | BC27: =+BA27-BB27 -> 0 | BD27: 0 | BE27: =+BA27-BD27 -> 0 | BF27: 0 | BG27: =+BA27-BF27 -> 0 | BI27: 0 | BJ27: 0 | BK27: =+BI27-BJ27 -> 0 | BL27: 0 | BM27: =+BI27-BL27 -> 0 | BN27: 0 | BO27: =+BI27-BN27 -> 0
B28: =IF(SUM(T28:T28)<>0,"Show","Hide") -> Hide | C28: -1 | D28: Fuel and Oil | E28: 9.5 | F28: 39.229166 | G28: =+E28-F28 -> -29.729166 | H28: 0 | I28: =+E28-H28 -> 9.5 | J28: 16 | K28: =+E28-J28 -> -6.5 | M28: 9.5 | N28: 39.229166 | O28: =+M28-N28 -> -29.729166 | P28: 0 | Q28: =+M28-P28 -> 9.5 | R28: 16 | S28: =+M28-R28 -> -6.5 | U28: 4.75 | V28: 37.618761 | W28: =+U28-V28 -> -32.868761 | X28: 0 | Y28: =+U28-X28 -> 4.75 | Z28: 16 | AA28: =+U28-Z28 -> -11.25 | AC28: 4.75 | AD28: 37.618761 | AE28: =+AC28-AD28 -> -32.868761 | AF28: 0 | AG28: =+AC28-AF28 -> 4.75 | AH28: 16 | AI28: =+AC28-AH28 -> -11.25 | AK28: 4.75 | AL28: 1.6104048 | AM28: =+AK28-AL28 -> 3.1395952 | AN28: 0 | AO28: =+AK28-AN28 -> 4.75 | AP28: 0 | AQ28: =+AK28-AP28 -> 4.75 | AS28: 4.75 | AT28: 1.6104048 | AU28: =+AS28-AT28 -> 3.1395952 | AV28: 0 | AW28: =+AS28-AV28 -> 4.75 | AX28: 0 | AY28: =+AS28-AX28 -> 4.75 | BA28: 0 | BB28: 0 | BC28: =+BA28-BB28 -> 0 | BD28: 0 | BE28: =+BA28-BD28 -> 0 | BF28: 0 | BG28: =+BA28-BF28 -> 0 | BI28: 0 | BJ28: 0 | BK28: =+BI28-BJ28 -> 0 | BL28: 0 | BM28: =+BI28-BL28 -> 0 | BN28: 0 | BO28: =+BI28-BN28 -> 0
B29: =IF(SUM(T29:T29)<>0,"Show","Hide") -> Hide | C29: -1 | D29: 1015 - Hire Revenue - Damage Waiver | E29: 11723.94 | F29: 9203.717 | G29: =+E29-F29 -> 2520.223 | H29: 0 | I29: =+E29-H29 -> 11723.94 | J29: 11191.09 | K29: =+E29-J29 -> 532.85 | M29: 11723.94 | N29: 9203.717 | O29: =+M29-N29 -> 2520.223 | P29: 0 | Q29: =+M29-P29 -> 11723.94 | R29: 11191.09 | S29: =+M29-R29 -> 532.85 | U29: 5631.23 | V29: 5172.4612 | W29: =+U29-V29 -> 458.7688 | X29: 0 | Y29: =+U29-X29 -> 5631.23 | Z29: 6788.62 | AA29: =+U29-Z29 -> -1157.39 | AC29: 5631.23 | AD29: 5172.4612 | AE29: =+AC29-AD29 -> 458.7688 | AF29: 0 | AG29: =+AC29-AF29 -> 5631.23 | AH29: 6788.62 | AI29: =+AC29-AH29 -> -1157.39 | AK29: 5384.36 | AL29: 3689.2426 | AM29: =+AK29-AL29 -> 1695.1174 | AN29: 0 | AO29: =+AK29-AN29 -> 5384.36 | AP29: 4402.47 | AQ29: =+AK29-AP29 -> 981.89 | AS29: 5384.36 | AT29: 3689.2426 | AU29: =+AS29-AT29 -> 1695.1174 | AV29: 0 | AW29: =+AS29-AV29 -> 5384.36 | AX29: 4402.47 | AY29: =+AS29-AX29 -> 981.89 | BA29: 708.35 | BB29: 342.01319 | BC29: =+BA29-BB29 -> 366.33681 | BD29: 0 | BE29: =+BA29-BD29 -> 708.35 | BF29: 0 | BG29: =+BA29-BF29 -> 708.35 | BI29: 708.35 | BJ29: 342.01319 | BK29: =+BI29-BJ29 -> 366.33681 | BL29: 0 | BM29: =+BI29-BL29 -> 708.35 | BN29: 0 | BO29: =+BI29-BN29 -> 708.35
B30: =IF(SUM(T30:T30)<>0,"Show","Hide") -> Hide | C30: -1 | D30: 1041 - Hire Revenue - Damage Costs Recovered | E30: 140 | F30: 505.55533 | G30: =+E30-F30 -> -365.55533 | H30: 0 | I30: =+E30-H30 -> 140 | J30: 238.4 | K30: =+E30-J30 -> -98.4 | M30: 140 | N30: 505.55533 | O30: =+M30-N30 -> -365.55533 | P30: 0 | Q30: =+M30-P30 -> 140 | R30: 238.4 | S30: =+M30-R30 -> -98.4 | U30: 140 | V30: 135.90864 | W30: =+U30-V30 -> 4.0913607 | X30: 0 | Y30: =+U30-X30 -> 140 | Z30: -157.6 | AA30: =+U30-Z30 -> 297.6 | AC30: 140 | AD30: 135.90864 | AE30: =+AC30-AD30 -> 4.0913607 | AF30: 0 | AG30: =+AC30-AF30 -> 140 | AH30: -157.6 | AI30: =+AC30-AH30 -> 297.6 | AK30: 0 | AL30: 369.64669 | AM30: =+AK30-AL30 -> -369.64669 | AN30: 0 | AO30: =+AK30-AN30 -> 0 | AP30: 396 | AQ30: =+AK30-AP30 -> -396 | AS30: 0 | AT30: 369.64669 | AU30: =+AS30-AT30 -> -369.64669 | AV30: 0 | AW30: =+AS30-AV30 -> 0 | AX30: 396 | AY30: =+AS30-AX30 -> -396 | BA30: 0 | BB30: 0 | BC30: =+BA30-BB30 -> 0 | BD30: 0 | BE30: =+BA30-BD30 -> 0 | BF30: 0 | BG30: =+BA30-BF30 -> 0 | BI30: 0 | BJ30: 0 | BK30: =+BI30-BJ30 -> 0 | BL30: 0 | BM30: =+BI30-BL30 -> 0 | BN30: 0 | BO30: =+BI30-BN30 -> 0
B31: =IF(SUM(T31:T31)<>0,"Show","Hide") -> Hide | C31: -1 | D31: Damage Revenue | E31: 11863.94 | F31: 9709.2724 | G31: =+E31-F31 -> 2154.6676 | H31: 0 | I31: =+E31-H31 -> 11863.94 | J31: 11429.49 | K31: =+E31-J31 -> 434.45 | M31: 11863.94 | N31: 9709.2724 | O31: =+M31-N31 -> 2154.6676 | P31: 0 | Q31: =+M31-P31 -> 11863.94 | R31: 11429.49 | S31: =+M31-R31 -> 434.45 | U31: 5771.23 | V31: 5308.3698 | W31: =+U31-V31 -> 462.86016 | X31: 0 | Y31: =+U31-X31 -> 5771.23 | Z31: 6631.02 | AA31: =+U31-Z31 -> -859.79 | AC31: 5771.23 | AD31: 5308.3698 | AE31: =+AC31-AD31 -> 462.86016 | AF31: 0 | AG31: =+AC31-AF31 -> 5771.23 | AH31: 6631.02 | AI31: =+AC31-AH31 -> -859.79 | AK31: 5384.36 | AL31: 4058.8893 | AM31: =+AK31-AL31 -> 1325.4707 | AN31: 0 | AO31: =+AK31-AN31 -> 5384.36 | AP31: 4798.47 | AQ31: =+AK31-AP31 -> 585.89 | AS31: 5384.36 | AT31: 4058.8893 | AU31: =+AS31-AT31 -> 1325.4707 | AV31: 0 | AW31: =+AS31-AV31 -> 5384.36 | AX31: 4798.47 | AY31: =+AS31-AX31 -> 585.89 | BA31: 708.35 | BB31: 342.01319 | BC31: =+BA31-BB31 -> 366.33681 | BD31: 0 | BE31: =+BA31-BD31 -> 708.35 | BF31: 0 | BG31: =+BA31-BF31 -> 708.35 | BI31: 708.35 | BJ31: 342.01319 | BK31: =+BI31-BJ31 -> 366.33681 | BL31: 0 | BM31: =+BI31-BL31 -> 708.35 | BN31: 0 | BO31: =+BI31-BN31 -> 708.35
... B66: =IF(SUM(T66:T66)<>0,"Show","Hide") -> Hide | C66: -1 | D66: Total Combined Revenue | E66: 400720.94 | F66: 535587.18 | G66: =+E66-F66 -> -134866.24 | H66: 0 | I66: =+E66-H66 -> 400720.94 | J66: 443596.88 | K66: =+E66-J66 -> -42875.94 | M66: 400720.94 | N66: 535587.18 | O66: =+M66-N66 -> -134866.24 | P66: 0 | Q66: =+M66-P66 -> 400720.94 | R66: 443596.88 | S66: =+M66-R66 -> -42875.94 | U66: 280349.36 | V66: 400740.21 | W66: =+U66-V66 -> -120390.85 | X66: 0 | Y66: =+U66-X66 -> 280349.36 | Z66: 238054.33 | AA66: =+U66-Z66 -> 42295.03 | AC66: 280349.36 | AD66: 400740.21 | AE66: =+AC66-AD66 -> -120390.85 | AF66: 0 | AG66: =+AC66-AF66 -> 280349.36 | AH66: 238054.33 | AI66: =+AC66-AH66 -> 42295.03 | AK66: 96627.67 | AL66: 124824.97 | AM66: =+AK66-AL66 -> -28197.298 | AN66: 0 | AO66: =+AK66-AN66 -> 96627.67 | AP66: 170108.07 | AQ66: =+AK66-AP66 -> -73480.4 | AS66: 96627.67 | AT66: 124824.97 | AU66: =+AS66-AT66 -> -28197.298 | AV66: 0 | AW66: =+AS66-AV66 -> 96627.67 | AX66: 170108.07 | AY66: =+AS66-AX66 -> -73480.4 | BA66: 23743.91 | BB66: 10022 | BC66: =+BA66-BB66 -> 13721.91 | BD66: 0 | BE66: =+BA66-BD66 -> 23743.91 | BF66: 35434.48 | BG66: =+BA66-BF66 -> -11690.57 | BI66: 23743.91 | BJ66: 10022 | BK66: =+BI66-BJ66 -> 13721.91 | BL66: 0 | BM66: =+BI66-BL66 -> 23743.91 | BN66: 35434.48 | BO66: =+BI66-BN66 -> -11690.57
B67: SHOW | D67: REPAIRS & MAINTENANCE | E67: 0 | F67: 0 | G67: =+E67-F67 -> 0 | H67: 0 | I67: =+E67-H67 -> 0 | J67: 0 | K67: =+E67-J67 -> 0 | M67: 0 | N67: 0 | O67: =+M67-N67 -> 0 | P67: 0 | Q67: =+M67-P67 -> 0 | R67: 0 | S67: =+M67-R67 -> 0 | U67: 0 | V67: 0 | W67: =+U67-V67 -> 0 | X67: 0 | Y67: =+U67-X67 -> 0 | Z67: 0 | AA67: =+U67-Z67 -> 0 | AC67: 0 | AD67: 0 | AE67: =+AC67-AD67 -> 0 | AF67: 0 | AG67: =+AC67-AF67 -> 0 | AH67: 0 | AI67: =+AC67-AH67 -> 0 | AK67: 0 | AL67: 0 | AM67: =+AK67-AL67 -> 0 | AN67: 0 | AO67: =+AK67-AN67 -> 0 | AP67: 0 | AQ67: =+AK67-AP67 -> 0 | AS67: 0 | AT67: 0 | AU67: =+AS67-AT67 -> 0 | AV67: 0 | AW67: =+AS67-AV67 -> 0 | AX67: 0 | AY67: =+AS67-AX67 -> 0 | BA67: 0 | BB67: 0 | BC67: =+BA67-BB67 -> 0 | BD67: 0 | BE67: =+BA67-BD67 -> 0 | BF67: 0 | BG67: =+BA67-BF67 -> 0 | BI67: 0 | BJ67: 0 | BK67: =+BI67-BJ67 -> 0 | BL67: 0 | BM67: =+BI67-BL67 -> 0 | BN67: 0 | BO67: =+BI67-BN67 -> 0
B68: =IF(SUM(T68:T68)<>0,"Show","Hide") -> Hide | C68: 1 | D68: 2376 - Not Specified | E68: 0 | F68: 0 | G68: =+E68-F68 -> 0 | H68: 0 | I68: =+E68-H68 -> 0 | J68: 0 | K68: =+E68-J68 -> 0 | M68: 0 | N68: 0 | O68: =+M68-N68 -> 0 | P68: 0 | Q68: =+M68-P68 -> 0 | R68: 0 | S68: =+M68-R68 -> 0 | U68: 0 | V68: 0 | W68: =+U68-V68 -> 0 | X68: 0 | Y68: =+U68-X68 -> 0 | Z68: 0 | AA68: =+U68-Z68 -> 0 | AC68: 0 | AD68: 0 | AE68: =+AC68-AD68 -> 0 | AF68: 0 | AG68: =+AC68-AF68 -> 0 | AH68: 0 | AI68: =+AC68-AH68 -> 0 | AK68: 0 | AL68: 0 | AM68: =+AK68-AL68 -> 0 | AN68: 0 | AO68: =+AK68-AN68 -> 0 | AP68: 0 | AQ68: =+AK68-AP68 -> 0 | AS68: 0 | AT68: 0 | AU68: =+AS68-AT68 -> 0 | AV68: 0 | AW68: =+AS68-AV68 -> 0 | AX68: 0 | AY68: =+AS68-AX68 -> 0 | BA68: 0 | BB68: 0 | BC68: =+BA68-BB68 -> 0 | BD68: 0 | BE68: =+BA68-BD68 -> 0 | BF68: 0 | BG68: =+BA68-BF68 -> 0 | BI68: 0 | BJ68: 0 | BK68: =+BI68-BJ68 -> 0 | BL68: 0 | BM68: =+BI68-BL68 -> 0 | BN68: 0 | BO68: =+BI68-BN68 -> 0
B69: =IF(SUM(T69:T69)<>0,"Show","Hide") -> Hide | C69: 1 | D69: 3217 - R&M Labour - Internal Service Jobs | E69: -559.25 | F69: -417.26186 | G69: =+E69-F69 -> -141.98814 | H69: 0 | I69: =+E69-H69 -> -559.25 | J69: 883.85 | K69: =+E69-J69 -> -1443.1 | M69: -559.25 | N69: -417.26186 | O69: =+M69-N69 -> -141.98814 | P69: 0 | Q69: =+M69-P69 -> -559.25 | R69: 883.85 | S69: =+M69-R69 -> -1443.1 | U69: -510.6 | V69: -391.37804 | W69: =+U69-V69 -> -119.22196 | X69: 0 | Y69: =+U69-X69 -> -510.6 | Z69: 885.55 | AA69: =+U69-Z69 -> -1396.15 | AC69: -510.6 | AD69: -391.37804 | AE69: =+AC69-AD69 -> -119.22196 | AF69: 0 | AG69: =+AC69-AF69 -> -510.6 | AH69: 885.55 | AI69: =+AC69-AH69 -> -1396.15 | AK69: -48.65 | AL69: -87.995105 | AM69: =+AK69-AL69 -> 39.345105 | AN69: 0 | AO69: =+AK69-AN69 -> -48.65 | AP69: -1.7 | AQ69: =+AK69-AP69 -> -46.95 | AS69: -48.65 | AT69: -87.995105 | AU69: =+AS69-AT69 -> 39.345105 | AV69: 0 | AW69: =+AS69-AV69 -> -48.65 | AX69: -1.7 | AY69: =+AS69-AX69 -> -46.95 | BA69: 0 | BB69: 62.111281 | BC69: =+BA69-BB69 -> -62.111281 | BD69: 0 | BE69: =+BA69-BD69 -> 0 | BF69: 0 | BG69: =+BA69-BF69 -> 0 | BI69: 0 | BJ69: 62.111281 | BK69: =+BI69-BJ69 -> -62.111281 | BL69: 0 | BM69: =+BI69-BL69 -> 0 | BN69: 0 | BO69: =+BI69-BN69 -> 0
B70: =IF(SUM(T70:T70)<>0,"Show","Hide") -> Hide | C70: 1 | D70: 2110 - R&M Parts - Internal Service Jobs | E70: 5269.05 | F70: -4414.4291 | G70: =+E70-F70 -> 9683.4791 | H70: 0 | I70: =+E70-H70 -> 5269.05 | J70: 1471.28 | K70: =+E70-J70 -> 3797.77 | M70: 5269.05 | N70: -4414.4291 | O70: =+M70-N70 -> 9683.4791 | P70: 0 | Q70: =+M70-P70 -> 5269.05 | R70: 1471.28 | S70: =+M70-R70 -> 3797.77 | U70: 1731.82 | V70: -7495.8063 | W70: =+U70-V70 -> 9227.6263 | X70: 0 | Y70: =+U70-X70 -> 1731.82 | Z70: 1185.99 | AA70: =+U70-Z70 -> 545.83 | AC70: 1731.82 | AD70: -7495.8063 | AE70: =+AC70-AD70 -> 9227.6263 | AF70: 0 | AG70: =+AC70-AF70 -> 1731.82 | AH70: 1185.99 | AI70: =+AC70-AH70 -> 545.83 | AK70: 3537.23 | AL70: 2793.5319 | AM70: =+AK70-AL70 -> 743.69811 | AN70: 0 | AO70: =+AK70-AN70 -> 3537.23 | AP70: 285.29 | AQ70: =+AK70-AP70 -> 3251.94 | AS70: 3537.23 | AT70: 2793.5319 | AU70: =+AS70-AT70 -> 743.69811 | AV70: 0 | AW70: =+AS70-AV70 -> 3537.23 | AX70: 285.29 | AY70: =+AS70-AX70 -> 3251.94 | BA70: 0 | BB70: 287.84534 | BC70: =+BA70-BB70 -> -287.84534 | BD70: 0 | BE70: =+BA70-BD70 -> 0 | BF70: 0 | BG70: =+BA70-BF70 -> 0 | BI70: 0 | BJ70: 287.84534 | BK70: =+BI70-BJ70 -> -287.84534 | BL70: 0 | BM70: =+BI70-BL70 -> 0 | BN70: 0 | BO70: =+BI70-BN70 -> 0
B71: =IF(SUM(T71:T71)<>0,"Show","Hide") -> Hide | C71: 1 | D71: 3217 - R&M Labour - Internal Service Jobs | E71: -559.25 | F71: -417.26186 | G71: =+E71-F71 -> -141.98814 | H71: 0 | I71: =+E71-H71 -> -559.25 | J71: 883.85 | K71: =+E71-J71 -> -1443.1 | M71: -559.25 | N71: -417.26186 | O71: =+M71-N71 -> -141.98814 | P71: 0 | Q71: =+M71-P71 -> -559.25 | R71: 883.85 | S71: =+M71-R71 -> -1443.1 | U71: -510.6 | V71: -391.37804 | W71: =+U71-V71 -> -119.22196 | X71: 0 | Y71: =+U71-X71 -> -510.6 | Z71: 885.55 | AA71: =+U71-Z71 -> -1396.15 | AC71: -510.6 | AD71: -391.37804 | AE71: =+AC71-AD71 -> -119.22196 | AF71: 0 | AG71: =+AC71-AF71 -> -510.6 | AH71: 885.55 | AI71: =+AC71-AH71 -> -1396.15 | AK71: -48.65 | AL71: -87.995105 | AM71: =+AK71-AL71 -> 39.345105 | AN71: 0 | AO71: =+AK71-AN71 -> -48.65 | AP71: -1.7 | AQ71: =+AK71-AP71 -> -46.95 | AS71: -48.65 | AT71: -87.995105 | AU71: =+AS71-AT71 -> 39.345105 | AV71: 0 | AW71: =+AS71-AV71 -> -48.65 | AX71: -1.7 | AY71: =+AS71-AX71 -> -46.95 | BA71: 0 | BB71: 62.111281 | BC71: =+BA71-BB71 -> -62.111281 | BD71: 0 | BE71: =+BA71-BD71 -> 0 | BF71: 0 | BG71: =+BA71-BF71 -> 0 | BI71: 0 | BJ71: 62.111281 | BK71: =+BI71-BJ71 -> -62.111281 | BL71: 0 | BM71: =+BI71-BL71 -> 0 | BN71: 0 | BO71: =+BI71-BN71 -> 0
B72: =IF(SUM(T72:T72)<>0,"Show","Hide") -> Hide | C72: 1 | D72: 2357 - R&M Parts | E72: -370.89 | F72: -954.17687 | G72: =+E72-F72 -> 583.28687 | H72: 0 | I72: =+E72-H72 -> -370.89 | J72: 0 | K72: =+E72-J72 -> -370.89 | M72: -370.89 | N72: -954.17687 | O72: =+M72-N72 -> 583.28687 | P72: 0 | Q72: =+M72-P72 -> -370.89 | R72: 0 | S72: =+M72-R72 -> -370.89 | U72: 0 | V72: -964.64043 | W72: =+U72-V72 -> 964.64043 | X72: 0 | Y72: =+U72-X72 -> 0 | Z72: 0 | AA72: =+U72-Z72 -> 0 | AC72: 0 | AD72: -964.64043 | AE72: =+AC72-AD72 -> 964.64043 | AF72: 0 | AG72: =+AC72-AF72 -> 0 | AH72: 0 | AI72: =+AC72-AH72 -> 0 | AK72: -370.89 | AL72: 10.463561 | AM72: =+AK72-AL72 -> -381.35356 | AN72: 0 | AO72: =+AK72-AN72 -> -370.89 | AP72: 0 | AQ72: =+AK72-AP72 -> -370.89 | AS72: -370.89 | AT72: 10.463561 | AU72: =+AS72-AT72 -> -381.35356 | AV72: 0 | AW72: =+AS72-AV72 -> -370.89 | AX72: 0 | AY72: =+AS72-AX72 -> -370.89 | BA72: 0 | BB72: 0 | BC72: =+BA72-BB72 -> 0 | BD72: 0 | BE72: =+BA72-BD72 -> 0 | BF72: 0 | BG72: =+BA72-BF72 -> 0 | BI72: 0 | BJ72: 0 | BK72: =+BI72-BJ72 -> 0 | BL72: 0 | BM72: =+BI72-BL72 -> 0 | BN72: 0 | BO72: =+BI72-BN72 -> 0
B73: =IF(SUM(T73:T73)<>0,"Show","Hide") -> Hide | C73: 1 | D73: 2370 - Outside Repairs | E73: 0 | F73: 4.2999716 | G73: =+E73-F73 -> -4.2999716 | H73: 0 | I73: =+E73-H73 -> 0 | J73: 0 | K73: =+E73-J73 -> 0 | M73: 0 | N73: 4.2999716 | O73: =+M73-N73 -> -4.2999716 | P73: 0 | Q73: =+M73-P73 -> 0 | R73: 0 | S73: =+M73-R73 -> 0 | U73: 0 | V73: 0 | W73: =+U73-V73 -> 0 | X73: 0 | Y73: =+U73-X73 -> 0 | Z73: 0 | AA73: =+U73-Z73 -> 0 | AC73: 0 | AD73: 0 | AE73: =+AC73-AD73 -> 0 | AF73: 0 | AG73: =+AC73-AF73 -> 0 | AH73: 0 | AI73: =+AC73-AH73 -> 0 | AK73: 0 | AL73: 4.2999716 | AM73: =+AK73-AL73 -> -4.2999716 | AN73: 0 | AO73: =+AK73-AN73 -> 0 | AP73: 0 | AQ73: =+AK73-AP73 -> 0 | AS73: 0 | AT73: 4.2999716 | AU73: =+AS73-AT73 -> -4.2999716 | AV73: 0 | AW73: =+AS73-AV73 -> 0 | AX73: 0 | AY73: =+AS73-AX73 -> 0 | BA73: 0 | BB73: 0 | BC73: =+BA73-BB73 -> 0 | BD73: 0 | BE73: =+BA73-BD73 -> 0 | BF73: 0 | BG73: =+BA73-BF73 -> 0 | BI73: 0 | BJ73: 0 | BK73: =+BI73-BJ73 -> 0 | BL73: 0 | BM73: =+BI73-BL73 -> 0 | BN73: 0 | BO73: =+BI73-BN73 -> 0
B74: =IF(SUM(T74:T74)<>0,"Show","Hide") -> Hide | C74: 1 | D74: 2371 - R&M - External Labour | E74: 14745 | F74: -3318.8095 | G74: =+E74-F74 -> 18063.81 | H74: 0 | I74: =+E74-H74 -> 14745 | J74: 9901.96 | K74: =+E74-J74 -> 4843.04 | M74: 14745 | N74: -3318.8095 | O74: =+M74-N74 -> 18063.81 | P74: 0 | Q74: =+M74-P74 -> 14745 | R74: 9901.96 | S74: =+M74-R74 -> 4843.04 | U74: 14315 | V74: -4573.1682 | W74: =+U74-V74 -> 18888.168 | X74: 0 | Y74: =+U74-X74 -> 14315 | Z74: 8429 | AA74: =+U74-Z74 -> 5886 | AC74: 14315 | AD74: -4573.1682 | AE74: =+AC74-AD74 -> 18888.168 | AF74: 0 | AG74: =+AC74-AF74 -> 14315 | AH74: 8429 | AI74: =+AC74-AH74 -> 5886 | AK74: 430 | AL74: 1152.1802 | AM74: =+AK74-AL74 -> -722.18021 | AN74: 0 | AO74: =+AK74-AN74 -> 430 | AP74: 1472.96 | AQ74: =+AK74-AP74 -> -1042.96 | AS74: 430 | AT74: 1152.1802 | AU74: =+AS74-AT74 -> -722.18021 | AV74: 0 | AW74: =+AS74-AV74 -> 430 | AX74: 1472.96 | AY74: =+AS74-AX74 -> -1042.96 | BA74: 0 | BB74: 102.1785 | BC74: =+BA74-BB74 -> -102.1785 | BD74: 0 | BE74: =+BA74-BD74 -> 0 | BF74: 0 | BG74: =+BA74-BF74 -> 0 | BI74: 0 | BJ74: 102.1785 | BK74: =+BI74-BJ74 -> -102.1785 | BL74: 0 | BM74: =+BI74-BL74 -> 0 | BN74: 0 | BO74: =+BI74-BN74 -> 0
B75: =IF(SUM(T75:T75)<>0,"Show","Hide") -> Hide | C75: 1 | D75: 2372 - R&M - External Parts | E75: 1740.59 | F75: -3419.3961 | G75: =+E75-F75 -> 5159.9861 | H75: 0 | I75: =+E75-H75 -> 1740.59 | J75: 0 | K75: =+E75-J75 -> 1740.59 | M75: 1740.59 | N75: -3419.3961 | O75: =+M75-N75 -> 5159.9861 | P75: 0 | Q75: =+M75-P75 -> 1740.59 | R75: 0 | S75: =+M75-R75 -> 1740.59 | U75: 0 | V75: -3613.5922 | W75: =+U75-V75 -> 3613.5922 | X75: 0 | Y75: =+U75-X75 -> 0 | Z75: 0 | AA75: =+U75-Z75 -> 0 | AC75: 0 | AD75: -3613.5922 | AE75: =+AC75-AD75 -> 3613.5922 | AF75: 0 | AG75: =+AC75-AF75 -> 0 | AH75: 0 | AI75: =+AC75-AH75 -> 0 | AK75: 1740.59 | AL75: 194.19609 | AM75: =+AK75-AL75 -> 1546.3939 | AN75: 0 | AO75: =+AK75-AN75 -> 1740.59 | AP75: 0 | AQ75: =+AK75-AP75 -> 1740.59 | AS75: 1740.59 | AT75: 194.19609 | AU75: =+AS75-AT75 -> 1546.3939 | AV75: 0 | AW75: =+AS75-AV75 -> 1740.59 | AX75: 0 | AY75: =+AS75-AX75 -> 1740.59 | BA75: 0 | BB75: 0 | BC75: =+BA75-BB75 -> 0 | BD75: 0 | BE75: =+BA75-BD75 -> 0 | BF75: 0 | BG75: =+BA75-BF75 -> 0 | BI75: 0 | BJ75: 0 | BK75: =+BI75-BJ75 -> 0 | BL75: 0 | BM75: =+BI75-BL75 -> 0 | BN75: 0 | BO75: =+BI75-BN75 -> 0
B76: =IF(SUM(T76:T76)<>0,"Show","Hide") -> Hide | C76: 1 | D76: 2374 - R&M - Rented & Operating Leased Fleet | E76: 0 | F76: 0 | G76: =+E76-F76 -> 0 | H76: 0 | I76: =+E76-H76 -> 0 | J76: 0 | K76: =+E76-J76 -> 0 | M76: 0 | N76: 0 | O76: =+M76-N76 -> 0 | P76: 0 | Q76: =+M76-P76 -> 0 | R76: 0 | S76: =+M76-R76 -> 0 | U76: 0 | V76: 0 | W76: =+U76-V76 -> 0 | X76: 0 | Y76: =+U76-X76 -> 0 | Z76: 0 | AA76: =+U76-Z76 -> 0 | AC76: 0 | AD76: 0 | AE76: =+AC76-AD76 -> 0 | AF76: 0 | AG76: =+AC76-AF76 -> 0 | AH76: 0 | AI76: =+AC76-AH76 -> 0 | AK76: 0 | AL76: 0 | AM76: =+AK76-AL76 -> 0 | AN76: 0 | AO76: =+AK76-AN76 -> 0 | AP76: 0 | AQ76: =+AK76-AP76 -> 0 | AS76: 0 | AT76: 0 | AU76: =+AS76-AT76 -> 0 | AV76: 0 | AW76: =+AS76-AV76 -> 0 | AX76: 0 | AY76: =+AS76-AX76 -> 0 | BA76: 0 | BB76: 0 | BC76: =+BA76-BB76 -> 0 | BD76: 0 | BE76: =+BA76-BD76 -> 0 | BF76: 0 | BG76: =+BA76-BF76 -> 0 | BI76: 0 | BJ76: 0 | BK76: =+BI76-BJ76 -> 0 | BL76: 0 | BM76: =+BI76-BL76 -> 0 | BN76: 0 | BO76: =+BI76-BN76 -> 0
B77: =IF(SUM(T77:T77)<>0,"Show","Hide") -> Hide | C77: 1 | D77: 2378 - Testing and Tagging | E77: 820 | F77: -178.78177 | G77: =+E77-F77 -> 998.78177 | H77: 0 | I77: =+E77-H77 -> 820 | J77: 1311.3 | K77: =+E77-J77 -> -491.3 | M77: 820 | N77: -178.78177 | O77: =+M77-N77 -> 998.78177 | P77: 0 | Q77: =+M77-P77 -> 820 | R77: 1311.3 | S77: =+M77-R77 -> -491.3 | U77: 820 | V77: -649.25624 | W77: =+U77-V77 -> 1469.2562 | X77: 0 | Y77: =+U77-X77 -> 820 | Z77: 0 | AA77: =+U77-Z77 -> 820 | AC77: 820 | AD77: -649.25624 | AE77: =+AC77-AD77 -> 1469.2562 | AF77: 0 | AG77: =+AC77-AF77 -> 820 | AH77: 0 | AI77: =+AC77-AH77 -> 820 | AK77: 0 | AL77: 470.47446 | AM77: =+AK77-AL77 -> -470.47446 | AN77: 0 | AO77: =+AK77-AN77 -> 0 | AP77: 1311.3 | AQ77: =+AK77-AP77 -> -1311.3 | AS77: 0 | AT77: 470.47446 | AU77: =+AS77-AT77 -> -470.47446 | AV77: 0 | AW77: =+AS77-AV77 -> 0 | AX77: 1311.3 | AY77: =+AS77-AX77 -> -1311.3 | BA77: 0 | BB77: 0 | BC77: =+BA77-BB77 -> 0 | BD77: 0 | BE77: =+BA77-BD77 -> 0 | BF77: 0 | BG77: =+BA77-BF77 -> 0 | BI77: 0 | BJ77: 0 | BK77: =+BI77-BJ77 -> 0 | BL77: 0 | BM77: =+BI77-BL77 -> 0 | BN77: 0 | BO77: =+BI77-BN77 -> 0
B78: =IF(SUM(T78:T78)<>0,"Show","Hide") -> Hide | C78: 1 | D78: 2150 - Consumables - Internal/Workshops | E78: 276.75 | F78: -662.91622 | G78: =+E78-F78 -> 939.66622 | H78: 0 | I78: =+E78-H78 -> 276.75 | J78: 602.36 | K78: =+E78-J78 -> -325.61 | M78: 276.75 | N78: -662.91622 | O78: =+M78-N78 -> 939.66622 | P78: 0 | Q78: =+M78-P78 -> 276.75 | R78: 602.36 | S78: =+M78-R78 -> -325.61 | U78: 0 | V78: -901.5942 | W78: =+U78-V78 -> 901.5942 | X78: 0 | Y78: =+U78-X78 -> 0 | Z78: 375.83 | AA78: =+U78-Z78 -> -375.83 | AC78: 0 | AD78: -901.5942 | AE78: =+AC78-AD78 -> 901.5942 | AF78: 0 | AG78: =+AC78-AF78 -> 0 | AH78: 375.83 | AI78: =+AC78-AH78 -> -375.83 | AK78: 256.25 | AL78: 78.831329 | AM78: =+AK78-AL78 -> 177.41867 | AN78: 0 | AO78: =+AK78-AN78 -> 256.25 | AP78: 226.53 | AQ78: =+AK78-AP78 -> 29.72 | AS78: 256.25 | AT78: 78.831329 | AU78: =+AS78-AT78 -> 177.41867 | AV78: 0 | AW78: =+AS78-AV78 -> 256.25 | AX78: 226.53 | AY78: =+AS78-AX78 -> 29.72 | BA78: 20.5 | BB78: 159.84665 | BC78: =+BA78-BB78 -> -139.34665 | BD78: 0 | BE78: =+BA78-BD78 -> 20.5 | BF78: 0 | BG78: =+BA78-BF78 -> 20.5 | BI78: 20.5 | BJ78: 159.84665 | BK78: =+BI78-BJ78 -> -139.34665 | BL78: 0 | BM78: =+BI78-BL78 -> 20.5 | BN78: 0 | BO78: =+BI78-BN78 -> 20.5
B79: =IF(SUM(T79:T79)<>0,"Show","Hide") -> Hide | C79: 1 | D79: R&M Parts and External Labour | E79: 21921.25 | F79: -13361.471 | G79: =+E79-F79 -> 35282.721 | H79: 0 | I79: =+E79-H79 -> 21921.25 | J79: 14170.75 | K79: =+E79-J79 -> 7750.5 | M79: 21921.25 | N79: -13361.471 | O79: =+M79-N79 -> 35282.721 | P79: 0 | Q79: =+M79-P79 -> 21921.25 | R79: 14170.75 | S79: =+M79-R79 -> 7750.5 | U79: 16356.22 | V79: -18589.436 | W79: =+U79-V79 -> 34945.656 | X79: 0 | Y79: =+U79-X79 -> 16356.22 | Z79: 10876.37 | AA79: =+U79-Z79 -> 5479.85 | AC79: 16356.22 | AD79: -18589.436 | AE79: =+AC79-AD79 -> 34945.656 | AF79: 0 | AG79: =+AC79-AF79 -> 16356.22 | AH79: 10876.37 | AI79: =+AC79-AH79 -> 5479.85 | AK79: 5544.53 | AL79: 4615.9824 | AM79: =+AK79-AL79 -> 928.54759 | AN79: 0 | AO79: =+AK79-AN79 -> 5544.53 | AP79: 3294.38 | AQ79: =+AK79-AP79 -> 2250.15 | AS79: 5544.53 | AT79: 4615.9824 | AU79: =+AS79-AT79 -> 928.54759 | AV79: 0 | AW79: =+AS79-AV79 -> 5544.53 | AX79: 3294.38 | AY79: =+AS79-AX79 -> 2250.15 | BA79: 20.5 | BB79: 611.98177 | BC79: =+BA79-BB79 -> -591.48177 | BD79: 0 | BE79: =+BA79-BD79 -> 20.5 | BF79: 0 | BG79: =+BA79-BF79 -> 20.5 | BI79: 20.5 | BJ79: 611.98177 | BK79: =+BI79-BJ79 -> -591.48177 | BL79: 0 | BM79: =+BI79-BL79 -> 20.5 | BN79: 0 | BO79: =+BI79-BN79 -> 20.5
... B102: =IF(SUM(T102:T102)<>0,"Show","Hide") -> Hide | C102: 1 | D102: 5236 - R&M - Rewards and Recognition | E102: 0 | F102: 0 | G102: =+E102-F102 -> 0 | H102: 0 | I102: =+E102-H102 -> 0 | J102: 0 | K102: =+E102-J102 -> 0 | M102: 0 | N102: 0 | O102: =+M102-N102 -> 0 | P102: 0 | Q102: =+M102-P102 -> 0 | R102: 0 | S102: =+M102-R102 -> 0 | U102: 0 | V102: 0 | W102: =+U102-V102 -> 0 | X102: 0 | Y102: =+U102-X102 -> 0 | Z102: 0 | AA102: =+U102-Z102 -> 0 | AC102: 0 | AD102: 0 | AE102: =+AC102-AD102 -> 0 | AF102: 0 | AG102: =+AC102-AF102 -> 0 | AH102: 0 | AI102: =+AC102-AH102 -> 0 | AK102: 0 | AL102: 0 | AM102: =+AK102-AL102 -> 0 | AN102: 0 | AO102: =+AK102-AN102 -> 0 | AP102: 0 | AQ102: =+AK102-AP102 -> 0 | AS102: 0 | AT102: 0 | AU102: =+AS102-AT102 -> 0 | AV102: 0 | AW102: =+AS102-AV102 -> 0 | AX102: 0 | AY102: =+AS102-AX102 -> 0 | BA102: 0 | BB102: 0 | BC102: =+BA102-BB102 -> 0 | BD102: 0 | BE102: =+BA102-BD102 -> 0 | BF102: 0 | BG102: =+BA102-BF102 -> 0 | BI102: 0 | BJ102: 0 | BK102: =+BI102-BJ102 -> 0 | BL102: 0 | BM102: =+BI102-BL102 -> 0 | BN102: 0 | BO102: =+BI102-BN102 -> 0
B103: =IF(SUM(T103:T103)<>0,"Show","Hide") -> Hide | C103: 1 | D103: 3219 - DO NOT USE | E103: #NUM! | F103: #NUM! | G103: =+E103-F103 -> #NUM! | H103: #NUM! | I103: =+E103-H103 -> #NUM! | J103: #NUM! | K103: =+E103-J103 -> #NUM! | M103: #NUM! | N103: #NUM! | O103: =+M103-N103 -> #NUM! | P103: #NUM! | Q103: =+M103-P103 -> #NUM! | R103: #NUM! | S103: =+M103-R103 -> #NUM! | U103: #NUM! | V103: #NUM! | W103: =+U103-V103 -> #NUM! | X103: #NUM! | Y103: =+U103-X103 -> #NUM! | Z103: #NUM! | AA103: =+U103-Z103 -> #NUM! | AC103: #NUM! | AD103: #NUM! | AE103: =+AC103-AD103 -> #NUM! | AF103: #NUM! | AG103: =+AC103-AF103 -> #NUM! | AH103: #NUM! | AI103: =+AC103-AH103 -> #NUM! | AK103: #NUM! | AL103: #NUM! | AM103: =+AK103-AL103 -> #NUM! | AN103: #NUM! | AO103: =+AK103-AN103 -> #NUM! | AP103: #NUM! | AQ103: =+AK103-AP103 -> #NUM! | AS103: #NUM! | AT103: #NUM! | AU103: =+AS103-AT103 -> #NUM! | AV103: #NUM! | AW103: =+AS103-AV103 -> #NUM! | AX103: #NUM! | AY103: =+AS103-AX103 -> #NUM! | BA103: #NUM! | BB103: #NUM! | BC103: =+BA103-BB103 -> #NUM! | BD103: #NUM! | BE103: =+BA103-BD103 -> #NUM! | BF103: #NUM! | BG103: =+BA103-BF103 -> #NUM! | BI103: #NUM! | BJ103: #NUM! | BK103: =+BI103-BJ103 -> #NUM! | BL103: #NUM! | BM103: =+BI103-BL103 -> #NUM! | BN103: #NUM! | BO103: =+BI103-BN103 -> #NUM!
B104: =IF(SUM(T104:T104)<>0,"Show","Hide") -> Hide | C104: 1 | D104: R&M Chargeable Wages | E104: 32537.56 | F104: 31185.977 | G104: =+E104-F104 -> 1351.5833 | H104: 0 | I104: =+E104-H104 -> 32537.56 | J104: 24298.37 | K104: =+E104-J104 -> 8239.19 | M104: 32537.56 | N104: 31185.977 | O104: =+M104-N104 -> 1351.5833 | P104: 0 | Q104: =+M104-P104 -> 32537.56 | R104: 24298.37 | S104: =+M104-R104 -> 8239.19 | U104: 22711.11 | V104: 21538.257 | W104: =+U104-V104 -> 1172.8534 | X104: 0 | Y104: =+U104-X104 -> 22711.11 | Z104: 23594.53 | AA104: =+U104-Z104 -> -883.42 | AC104: 22711.11 | AD104: 21538.257 | AE104: =+AC104-AD104 -> 1172.8534 | AF104: 0 | AG104: =+AC104-AF104 -> 22711.11 | AH104: 23594.53 | AI104: =+AC104-AH104 -> -883.42 | AK104: 9826.45 | AL104: 9647.7201 | AM104: =+AK104-AL104 -> 178.72989 | AN104: 0 | AO104: =+AK104-AN104 -> 9826.45 | AP104: 703.84 | AQ104: =+AK104-AP104 -> 9122.61 | AS104: 9826.45 | AT104: 9647.7201 | AU104: =+AS104-AT104 -> 178.72989 | AV104: 0 | AW104: =+AS104-AV104 -> 9826.45 | AX104: 703.84 | AY104: =+AS104-AX104 -> 9122.61 | BA104: 0 | BB104: 0 | BC104: =+BA104-BB104 -> 0 | BD104: 0 | BE104: =+BA104-BD104 -> 0 | BF104: 0 | BG104: =+BA104-BF104 -> 0 | BI104: 0 | BJ104: 0 | BK104: =+BI104-BJ104 -> 0 | BL104: 0 | BM104: =+BI104-BL104 -> 0 | BN104: 0 | BO104: =+BI104-BN104 -> 0
B105: =IF(SUM(T105:T105)<>0,"Show","Hide") -> Hide | C105: 1 | D105: 5410 - R&M NC - Salaries & Wages | E105: 19764.69 | F105: 29988.914 | G105: =+E105-F105 -> -10224.224 | H105: 0 | I105: =+E105-H105 -> 19764.69 | J105: 24577.76 | K105: =+E105-J105 -> -4813.07 | M105: 19764.69 | N105: 29988.914 | O105: =+M105-N105 -> -10224.224 | P105: 0 | Q105: =+M105-P105 -> 19764.69 | R105: 24577.76 | S105: =+M105-R105 -> -4813.07 | U105: 19764.69 | V105: 29988.914 | W105: =+U105-V105 -> -10224.224 | X105: 0 | Y105: =+U105-X105 -> 19764.69 | Z105: 17826.7 | AA105: =+U105-Z105 -> 1937.99 | AC105: 19764.69 | AD105: 29988.914 | AE105: =+AC105-AD105 -> -10224.224 | AF105: 0 | AG105: =+AC105-AF105 -> 19764.69 | AH105: 17826.7 | AI105: =+AC105-AH105 -> 1937.99 | AK105: 0 | AL105: 0 | AM105: =+AK105-AL105 -> 0 | AN105: 0 | AO105: =+AK105-AN105 -> 0 | AP105: 6751.06 | AQ105: =+AK105-AP105 -> -6751.06 | AS105: 0 | AT105: 0 | AU105: =+AS105-AT105 -> 0 | AV105: 0 | AW105: =+AS105-AV105 -> 0 | AX105: 6751.06 | AY105: =+AS105-AX105 -> -6751.06 | BA105: 0 | BB105: 0 | BC105: =+BA105-BB105 -> 0 | BD105: 0 | BE105: =+BA105-BD105 -> 0 | BF105: 0 | BG105: =+BA105-BF105 -> 0 | BI105: 0 | BJ105: 0 | BK105: =+BI105-BJ105 -> 0 | BL105: 0 | BM105: =+BI105-BL105 -> 0 | BN105: 0 | BO105: =+BI105-BN105 -> 0
B106: =IF(SUM(T106:T106)<>0,"Show","Hide") -> Hide | C106: 1 | D106: 5413 - R&M NC - Payroll Offset | E106: 0 | F106: -6345.0793 | G106: =+E106-F106 -> 6345.0793 | H106: 0 | I106: =+E106-H106 -> 0 | J106: 0 | K106: =+E106-J106 -> 0 | M106: 0 | N106: -6345.0793 | O106: =+M106-N106 -> 6345.0793 | P106: 0 | Q106: =+M106-P106 -> 0 | R106: 0 | S106: =+M106-R106 -> 0 | U106: 0 | V106: -6345.0793 | W106: =+U106-V106 -> 6345.0793 | X106: 0 | Y106: =+U106-X106 -> 0 | Z106: 0 | AA106: =+U106-Z106 -> 0 | AC106: 0 | AD106: -6345.0793 | AE106: =+AC106-AD106 -> 6345.0793 | AF106: 0 | AG106: =+AC106-AF106 -> 0 | AH106: 0 | AI106: =+AC106-AH106 -> 0 | AK106: 0 | AL106: 0 | AM106: =+AK106-AL106 -> 0 | AN106: 0 | AO106: =+AK106-AN106 -> 0 | AP106: 0 | AQ106: =+AK106-AP106 -> 0 | AS106: 0 | AT106: 0 | AU106: =+AS106-AT106 -> 0 | AV106: 0 | AW106: =+AS106-AV106 -> 0 | AX106: 0 | AY106: =+AS106-AX106 -> 0 | BA106: 0 | BB106: 0 | BC106: =+BA106-BB106 -> 0 | BD106: 0 | BE106: =+BA106-BD106 -> 0 | BF106: 0 | BG106: =+BA106-BF106 -> 0 | BI106: 0 | BJ106: 0 | BK106: =+BI106-BJ106 -> 0 | BL106: 0 | BM106: =+BI106-BL106 -> 0 | BN106: 0 | BO106: =+BI106-BN106 -> 0
B107: =IF(SUM(T107:T107)<>0,"Show","Hide") -> Hide | C107: 1 | D107: 5412 - R&M NC - Overtime | E107: 2113.15 | F107: 10401.485 | G107: =+E107-F107 -> -8288.3351 | H107: 0 | I107: =+E107-H107 -> 2113.15 | J107: 38.47 | K107: =+E107-J107 -> 2074.68 | M107: 2113.15 | N107: 10401.485 | O107: =+M107-N107 -> -8288.3351 | P107: 0 | Q107: =+M107-P107 -> 2113.15 | R107: 38.47 | S107: =+M107-R107 -> 2074.68 | U107: 2113.15 | V107: 10344.618 | W107: =+U107-V107 -> -8231.4684 | X107: 0 | Y107: =+U107-X107 -> 2113.15 | Z107: 0.01 | AA107: =+U107-Z107 -> 2113.14 | AC107: 2113.15 | AD107: 10344.618 | AE107: =+AC107-AD107 -> -8231.4684 | AF107: 0 | AG107: =+AC107-AF107 -> 2113.15 | AH107: 0.01 | AI107: =+AC107-AH107 -> 2113.14 | AK107: 0 | AL107: 56.866667 | AM107: =+AK107-AL107 -> -56.866667 | AN107: 0 | AO107: =+AK107-AN107 -> 0 | AP107: 38.46 | AQ107: =+AK107-AP107 -> -38.46 | AS107: 0 | AT107: 56.866667 | AU107: =+AS107-AT107 -> -56.866667 | AV107: 0 | AW107: =+AS107-AV107 -> 0 | AX107: 38.46 | AY107: =+AS107-AX107 -> -38.46 | BA107: 0 | BB107: 0 | BC107: =+BA107-BB107 -> 0 | BD107: 0 | BE107: =+BA107-BD107 -> 0 | BF107: 0 | BG107: =+BA107-BF107 -> 0 | BI107: 0 | BJ107: 0 | BK107: =+BI107-BJ107 -> 0 | BL107: 0 | BM107: =+BI107-BL107 -> 0 | BN107: 0 | BO107: =+BI107-BN107 -> 0
B108: =IF(SUM(T108:T108)<>0,"Show","Hide") -> Hide | C108: 1 | D108: 5415 - R&M NC Incentives | E108: 0 | F108: 0 | G108: =+E108-F108 -> 0 | H108: 0 | I108: =+E108-H108 -> 0 | J108: 0 | K108: =+E108-J108 -> 0 | M108: 0 | N108: 0 | O108: =+M108-N108 -> 0 | P108: 0 | Q108: =+M108-P108 -> 0 | R108: 0 | S108: =+M108-R108 -> 0 | U108: 0 | V108: 0 | W108: =+U108-V108 -> 0 | X108: 0 | Y108: =+U108-X108 -> 0 | Z108: 0 | AA108: =+U108-Z108 -> 0 | AC108: 0 | AD108: 0 | AE108: =+AC108-AD108 -> 0 | AF108: 0 | AG108: =+AC108-AF108 -> 0 | AH108: 0 | AI108: =+AC108-AH108 -> 0 | AK108: 0 | AL108: 0 | AM108: =+AK108-AL108 -> 0 | AN108: 0 | AO108: =+AK108-AN108 -> 0 | AP108: 0 | AQ108: =+AK108-AP108 -> 0 | AS108: 0 | AT108: 0 | AU108: =+AS108-AT108 -> 0 | AV108: 0 | AW108: =+AS108-AV108 -> 0 | AX108: 0 | AY108: =+AS108-AX108 -> 0 | BA108: 0 | BB108: 0 | BC108: =+BA108-BB108 -> 0 | BD108: 0 | BE108: =+BA108-BD108 -> 0 | BF108: 0 | BG108: =+BA108-BF108 -> 0 | BI108: 0 | BJ108: 0 | BK108: =+BI108-BJ108 -> 0 | BL108: 0 | BM108: =+BI108-BL108 -> 0 | BN108: 0 | BO108: =+BI108-BN108 -> 0
B109: =IF(SUM(T109:T109)<>0,"Show","Hide") -> Hide | C109: 1 | D109: 5416 - R&M NC - Fixed Allowance with super | E109: 836.23 | F109: 1254.351 | G109: =+E109-F109 -> -418.121 | H109: 0 | I109: =+E109-H109 -> 836.23 | J109: 1573.2 | K109: =+E109-J109 -> -736.97 | M109: 836.23 | N109: 1254.351 | O109: =+M109-N109 -> -418.121 | P109: 0 | Q109: =+M109-P109 -> 836.23 | R109: 1573.2 | S109: =+M109-R109 -> -736.97 | U109: 836.23 | V109: 1254.351 | W109: =+U109-V109 -> -418.121 | X109: 0 | Y109: =+U109-X109 -> 836.23 | Z109: 1573.2 | AA109: =+U109-Z109 -> -736.97 | AC109: 836.23 | AD109: 1254.351 | AE109: =+AC109-AD109 -> -418.121 | AF109: 0 | AG109: =+AC109-AF109 -> 836.23 | AH109: 1573.2 | AI109: =+AC109-AH109 -> -736.97 | AK109: 0 | AL109: 0 | AM109: =+AK109-AL109 -> 0 | AN109: 0 | AO109: =+AK109-AN109 -> 0 | AP109: 0 | AQ109: =+AK109-AP109 -> 0 | AS109: 0 | AT109: 0 | AU109: =+AS109-AT109 -> 0 | AV109: 0 | AW109: =+AS109-AV109 -> 0 | AX109: 0 | AY109: =+AS109-AX109 -> 0 | BA109: 0 | BB109: 0 | BC109: =+BA109-BB109 -> 0 | BD109: 0 | BE109: =+BA109-BD109 -> 0 | BF109: 0 | BG109: =+BA109-BF109 -> 0 | BI109: 0 | BJ109: 0 | BK109: =+BI109-BJ109 -> 0 | BL109: 0 | BM109: =+BI109-BL109 -> 0 | BN109: 0 | BO109: =+BI109-BN109 -> 0
B110: =IF(SUM(T110:T110)<>0,"Show","Hide") -> Hide | C110: 1 | D110: 5417 - R&M NC - Variable Allowance with super | E110: 0 | F110: 0 | G110: =+E110-F110 -> 0 | H110: 0 | I110: =+E110-H110 -> 0 | J110: 0 | K110: =+E110-J110 -> 0 | M110: 0 | N110: 0 | O110: =+M110-N110 -> 0 | P110: 0 | Q110: =+M110-P110 -> 0 | R110: 0 | S110: =+M110-R110 -> 0 | U110: 0 | V110: 0 | W110: =+U110-V110 -> 0 | X110: 0 | Y110: =+U110-X110 -> 0 | Z110: 0 | AA110: =+U110-Z110 -> 0 | AC110: 0 | AD110: 0 | AE110: =+AC110-AD110 -> 0 | AF110: 0 | AG110: =+AC110-AF110 -> 0 | AH110: 0 | AI110: =+AC110-AH110 -> 0 | AK110: 0 | AL110: 0 | AM110: =+AK110-AL110 -> 0 | AN110: 0 | AO110: =+AK110-AN110 -> 0 | AP110: 0 | AQ110: =+AK110-AP110 -> 0 | AS110: 0 | AT110: 0 | AU110: =+AS110-AT110 -> 0 | AV110: 0 | AW110: =+AS110-AV110 -> 0 | AX110: 0 | AY110: =+AS110-AX110 -> 0 | BA110: 0 | BB110: 0 | BC110: =+BA110-BB110 -> 0 | BD110: 0 | BE110: =+BA110-BD110 -> 0 | BF110: 0 | BG110: =+BA110-BF110 -> 0 | BI110: 0 | BJ110: 0 | BK110: =+BI110-BJ110 -> 0 | BL110: 0 | BM110: =+BI110-BL110 -> 0 | BN110: 0 | BO110: =+BI110-BN110 -> 0
B111: =IF(SUM(T111:T111)<>0,"Show","Hide") -> Hide | C111: 1 | D111: 5419 - R&M NC Allowance no super | E111: 0 | F111: 0 | G111: =+E111-F111 -> 0 | H111: 0 | I111: =+E111-H111 -> 0 | J111: 19.33 | K111: =+E111-J111 -> -19.33 | M111: 0 | N111: 0 | O111: =+M111-N111 -> 0 | P111: 0 | Q111: =+M111-P111 -> 0 | R111: 19.33 | S111: =+M111-R111 -> -19.33 | U111: 0 | V111: 0 | W111: =+U111-V111 -> 0 | X111: 0 | Y111: =+U111-X111 -> 0 | Z111: 19.33 | AA111: =+U111-Z111 -> -19.33 | AC111: 0 | AD111: 0 | AE111: =+AC111-AD111 -> 0 | AF111: 0 | AG111: =+AC111-AF111 -> 0 | AH111: 19.33 | AI111: =+AC111-AH111 -> -19.33 | AK111: 0 | AL111: 0 | AM111: =+AK111-AL111 -> 0 | AN111: 0 | AO111: =+AK111-AN111 -> 0 | AP111: 0 | AQ111: =+AK111-AP111 -> 0 | AS111: 0 | AT111: 0 | AU111: =+AS111-AT111 -> 0 | AV111: 0 | AW111: =+AS111-AV111 -> 0 | AX111: 0 | AY111: =+AS111-AX111 -> 0 | BA111: 0 | BB111: 0 | BC111: =+BA111-BB111 -> 0 | BD111: 0 | BE111: =+BA111-BD111 -> 0 | BF111: 0 | BG111: =+BA111-BF111 -> 0 | BI111: 0 | BJ111: 0 | BK111: =+BI111-BJ111 -> 0 | BL111: 0 | BM111: =+BI111-BL111 -> 0 | BN111: 0 | BO111: =+BI111-BN111 -> 0
B112: =IF(SUM(T112:T112)<>0,"Show","Hide") -> Hide | C112: 1 | D112: 5425 - R&M NC - Annual Leave Expense | E112: 565.75 | F112: 353.81152 | G112: =+E112-F112 -> 211.93848 | H112: 0 | I112: =+E112-H112 -> 565.75 | J112: 629.27 | K112: =+E112-J112 -> -63.52 | M112: 565.75 | N112: 353.81152 | O112: =+M112-N112 -> 211.93848 | P112: 0 | Q112: =+M112-P112 -> 565.75 | R112: 629.27 | S112: =+M112-R112 -> -63.52 | U112: 565.75 | V112: 353.81152 | W112: =+U112-V112 -> 211.93848 | X112: 0 | Y112: =+U112-X112 -> 565.75 | Z112: 629.27 | AA112: =+U112-Z112 -> -63.52 | AC112: 565.75 | AD112: 353.81152 | AE112: =+AC112-AD112 -> 211.93848 | AF112: 0 | AG112: =+AC112-AF112 -> 565.75 | AH112: 629.27 | AI112: =+AC112-AH112 -> -63.52 | AK112: 0 | AL112: 0 | AM112: =+AK112-AL112 -> 0 | AN112: 0 | AO112: =+AK112-AN112 -> 0 | AP112: 0 | AQ112: =+AK112-AP112 -> 0 | AS112: 0 | AT112: 0 | AU112: =+AS112-AT112 -> 0 | AV112: 0 | AW112: =+AS112-AV112 -> 0 | AX112: 0 | AY112: =+AS112-AX112 -> 0 | BA112: 0 | BB112: 0 | BC112: =+BA112-BB112 -> 0 | BD112: 0 | BE112: =+BA112-BD112 -> 0 | BF112: 0 | BG112: =+BA112-BF112 -> 0 | BI112: 0 | BJ112: 0 | BK112: =+BI112-BJ112 -> 0 | BL112: 0 | BM112: =+BI112-BL112 -> 0 | BN112: 0 | BO112: =+BI112-BN112 -> 0
B113: =IF(SUM(T113:T113)<>0,"Show","Hide") -> Hide | C113: 1 | D113: 5426 - R&M NC - Long Service Leave | E113: 374.72 | F113: 342.92038 | G113: =+E113-F113 -> 31.799621 | H113: 0 | I113: =+E113-H113 -> 374.72 | J113: 315.17 | K113: =+E113-J113 -> 59.55 | M113: 374.72 | N113: 342.92038 | O113: =+M113-N113 -> 31.799621 | P113: 0 | Q113: =+M113-P113 -> 374.72 | R113: 315.17 | S113: =+M113-R113 -> 59.55 | U113: 374.72 | V113: 342.92038 | W113: =+U113-V113 -> 31.799621 | X113: 0 | Y113: =+U113-X113 -> 374.72 | Z113: 315.17 | AA113: =+U113-Z113 -> 59.55 | AC113: 374.72 | AD113: 342.92038 | AE113: =+AC113-AD113 -> 31.799621 | AF113: 0 | AG113: =+AC113-AF113 -> 374.72 | AH113: 315.17 | AI113: =+AC113-AH113 -> 59.55 | AK113: 0 | AL113: 0 | AM113: =+AK113-AL113 -> 0 | AN113: 0 | AO113: =+AK113-AN113 -> 0 | AP113: 0 | AQ113: =+AK113-AP113 -> 0 | AS113: 0 | AT113: 0 | AU113: =+AS113-AT113 -> 0 | AV113: 0 | AW113: =+AS113-AV113 -> 0 | AX113: 0 | AY113: =+AS113-AX113 -> 0 | BA113: 0 | BB113: 0 | BC113: =+BA113-BB113 -> 0 | BD113: 0 | BE113: =+BA113-BD113 -> 0 | BF113: 0 | BG113: =+BA113-BF113 -> 0 | BI113: 0 | BJ113: 0 | BK113: =+BI113-BJ113 -> 0 | BL113: 0 | BM113: =+BI113-BL113 -> 0 | BN113: 0 | BO113: =+BI113-BN113 -> 0
B114: =IF(SUM(T114:T114)<>0,"Show","Hide") -> Hide | C114: 1 | D114: 5427 - R&M NC - Sick Leave Expense | E114: 0 | F114: 0 | G114: =+E114-F114 -> 0 | H114: 0 | I114: =+E114-H114 -> 0 | J114: 0 | K114: =+E114-J114 -> 0 | M114: 0 | N114: 0 | O114: =+M114-N114 -> 0 | P114: 0 | Q114: =+M114-P114 -> 0 | R114: 0 | S114: =+M114-R114 -> 0 | U114: 0 | V114: 0 | W114: =+U114-V114 -> 0 | X114: 0 | Y114: =+U114-X114 -> 0 | Z114: 0 | AA114: =+U114-Z114 -> 0 | AC114: 0 | AD114: 0 | AE114: =+AC114-AD114 -> 0 | AF114: 0 | AG114: =+AC114-AF114 -> 0 | AH114: 0 | AI114: =+AC114-AH114 -> 0 | AK114: 0 | AL114: 0 | AM114: =+AK114-AL114 -> 0 | AN114: 0 | AO114: =+AK114-AN114 -> 0 | AP114: 0 | AQ114: =+AK114-AP114 -> 0 | AS114: 0 | AT114: 0 | AU114: =+AS114-AT114 -> 0 | AV114: 0 | AW114: =+AS114-AV114 -> 0 | AX114: 0 | AY114: =+AS114-AX114 -> 0 | BA114: 0 | BB114: 0 | BC114: =+BA114-BB114 -> 0 | BD114: 0 | BE114: =+BA114-BD114 -> 0 | BF114: 0 | BG114: =+BA114-BF114 -> 0 | BI114: 0 | BJ114: 0 | BK114: =+BI114-BJ114 -> 0 | BL114: 0 | BM114: =+BI114-BL114 -> 0 | BN114: 0 | BO114: =+BI114-BN114 -> 0
B115: =IF(SUM(T115:T115)<>0,"Show","Hide") -> Hide | C115: 1 | D115: 5428 - R&M NC - EBA Severance | E115: 0 | F115: 0 | G115: =+E115-F115 -> 0 | H115: 0 | I115: =+E115-H115 -> 0 | J115: 0 | K115: =+E115-J115 -> 0 | M115: 0 | N115: 0 | O115: =+M115-N115 -> 0 | P115: 0 | Q115: =+M115-P115 -> 0 | R115: 0 | S115: =+M115-R115 -> 0 | U115: 0 | V115: 0 | W115: =+U115-V115 -> 0 | X115: 0 | Y115: =+U115-X115 -> 0 | Z115: 0 | AA115: =+U115-Z115 -> 0 | AC115: 0 | AD115: 0 | AE115: =+AC115-AD115 -> 0 | AF115: 0 | AG115: =+AC115-AF115 -> 0 | AH115: 0 | AI115: =+AC115-AH115 -> 0 | AK115: 0 | AL115: 0 | AM115: =+AK115-AL115 -> 0 | AN115: 0 | AO115: =+AK115-AN115 -> 0 | AP115: 0 | AQ115: =+AK115-AP115 -> 0 | AS115: 0 | AT115: 0 | AU115: =+AS115-AT115 -> 0 | AV115: 0 | AW115: =+AS115-AV115 -> 0 | AX115: 0 | AY115: =+AS115-AX115 -> 0 | BA115: 0 | BB115: 0 | BC115: =+BA115-BB115 -> 0 | BD115: 0 | BE115: =+BA115-BD115 -> 0 | BF115: 0 | BG115: =+BA115-BF115 -> 0 | BI115: 0 | BJ115: 0 | BK115: =+BI115-BJ115 -> 0 | BL115: 0 | BM115: =+BI115-BL115 -> 0 | BN115: 0 | BO115: =+BI115-BN115 -> 0
... B124: =IF(SUM(T124:T124)<>0,"Show","Hide") -> Hide | C124: 1 | D124: 3528 - Travel R&M | E124: 0 | F124: 0 | G124: =+E124-F124 -> 0 | H124: 0 | I124: =+E124-H124 -> 0 | J124: 0 | K124: =+E124-J124 -> 0 | M124: 0 | N124: 0 | O124: =+M124-N124 -> 0 | P124: 0 | Q124: =+M124-P124 -> 0 | R124: 0 | S124: =+M124-R124 -> 0 | U124: 0 | V124: 0 | W124: =+U124-V124 -> 0 | X124: 0 | Y124: =+U124-X124 -> 0 | Z124: 0 | AA124: =+U124-Z124 -> 0 | AC124: 0 | AD124: 0 | AE124: =+AC124-AD124 -> 0 | AF124: 0 | AG124: =+AC124-AF124 -> 0 | AH124: 0 | AI124: =+AC124-AH124 -> 0 | AK124: 0 | AL124: 0 | AM124: =+AK124-AL124 -> 0 | AN124: 0 | AO124: =+AK124-AN124 -> 0 | AP124: 0 | AQ124: =+AK124-AP124 -> 0 | AS124: 0 | AT124: 0 | AU124: =+AS124-AT124 -> 0 | AV124: 0 | AW124: =+AS124-AV124 -> 0 | AX124: 0 | AY124: =+AS124-AX124 -> 0 | BA124: 0 | BB124: 0 | BC124: =+BA124-BB124 -> 0 | BD124: 0 | BE124: =+BA124-BD124 -> 0 | BF124: 0 | BG124: =+BA124-BF124 -> 0 | BI124: 0 | BJ124: 0 | BK124: =+BI124-BJ124 -> 0 | BL124: 0 | BM124: =+BI124-BL124 -> 0 | BN124: 0 | BO124: =+BI124-BN124 -> 0
B125: =IF(SUM(T125:T125)<>0,"Show","Hide") -> Hide | D125: R&M Other | E125: 0 | F125: 0 | G125: =+E125-F125 -> 0 | H125: 0 | I125: =+E125-H125 -> 0 | J125: 0 | K125: =+E125-J125 -> 0 | M125: 0 | N125: 0 | O125: =+M125-N125 -> 0 | P125: 0 | Q125: =+M125-P125 -> 0 | R125: 0 | S125: =+M125-R125 -> 0 | U125: 0 | V125: 0 | W125: =+U125-V125 -> 0 | X125: 0 | Y125: =+U125-X125 -> 0 | Z125: 0 | AA125: =+U125-Z125 -> 0 | AC125: 0 | AD125: 0 | AE125: =+AC125-AD125 -> 0 | AF125: 0 | AG125: =+AC125-AF125 -> 0 | AH125: 0 | AI125: =+AC125-AH125 -> 0 | AK125: 0 | AL125: 0 | AM125: =+AK125-AL125 -> 0 | AN125: 0 | AO125: =+AK125-AN125 -> 0 | AP125: 0 | AQ125: =+AK125-AP125 -> 0 | AS125: 0 | AT125: 0 | AU125: =+AS125-AT125 -> 0 | AV125: 0 | AW125: =+AS125-AV125 -> 0 | AX125: 0 | AY125: =+AS125-AX125 -> 0 | BA125: 0 | BB125: 0 | BC125: =+BA125-BB125 -> 0 | BD125: 0 | BE125: =+BA125-BD125 -> 0 | BF125: 0 | BG125: =+BA125-BF125 -> 0 | BI125: 0 | BJ125: 0 | BK125: =+BI125-BJ125 -> 0 | BL125: 0 | BM125: =+BI125-BL125 -> 0 | BN125: 0 | BO125: =+BI125-BN125 -> 0
B126: =IF(SUM(T126:T126)<>0,"Show","Hide") -> Hide | C126: 1 | D126: Total Repairs & Maintenance | E126: 83582.93 | F126: 62304.963 | G126: =+E126-F126 -> 21277.967 | H126: 0 | I126: =+E126-H126 -> 83582.93 | J126: 71650.28 | K126: =+E126-J126 -> 11932.65 | M126: 83582.93 | N126: 62304.963 | O126: =+M126-N126 -> 21277.967 | P126: 0 | Q126: =+M126-P126 -> 83582.93 | R126: 71650.28 | S126: =+M126-R126 -> 11932.65 | U126: 68191.45 | V126: 47362.489 | W126: =+U126-V126 -> 20828.961 | X126: 0 | Y126: =+U126-X126 -> 68191.45 | Z126: 60009.77 | AA126: =+U126-Z126 -> 8181.68 | AC126: 68191.45 | AD126: 47362.489 | AE126: =+AC126-AD126 -> 20828.961 | AF126: 0 | AG126: =+AC126-AF126 -> 68191.45 | AH126: 60009.77 | AI126: =+AC126-AH126 -> 8181.68 | AK126: 15370.98 | AL126: 14330.492 | AM126: =+AK126-AL126 -> 1040.4876 | AN126: 0 | AO126: =+AK126-AN126 -> 15370.98 | AP126: 11640.51 | AQ126: =+AK126-AP126 -> 3730.47 | AS126: 15370.98 | AT126: 14330.492 | AU126: =+AS126-AT126 -> 1040.4876 | AV126: 0 | AW126: =+AS126-AV126 -> 15370.98 | AX126: 11640.51 | AY126: =+AS126-AX126 -> 3730.47 | BA126: 20.5 | BB126: 611.98177 | BC126: =+BA126-BB126 -> -591.48177 | BD126: 0 | BE126: =+BA126-BD126 -> 20.5 | BF126: 0 | BG126: =+BA126-BF126 -> 20.5 | BI126: 20.5 | BJ126: 611.98177 | BK126: =+BI126-BJ126 -> -591.48177 | BL126: 0 | BM126: =+BI126-BL126 -> 20.5 | BN126: 0 | BO126: =+BI126-BN126 -> 20.5
B127: Show | D127: EQUIPMENT OWNERSHIP COSTS (EXCL DEPN) | E127: 0 | F127: 0 | G127: =+E127-F127 -> 0 | H127: 0 | I127: =+E127-H127 -> 0 | J127: 0 | K127: =+E127-J127 -> 0 | M127: 0 | N127: 0 | O127: =+M127-N127 -> 0 | P127: 0 | Q127: =+M127-P127 -> 0 | R127: 0 | S127: =+M127-R127 -> 0 | U127: 0 | V127: 0 | W127: =+U127-V127 -> 0 | X127: 0 | Y127: =+U127-X127 -> 0 | Z127: 0 | AA127: =+U127-Z127 -> 0 | AC127: 0 | AD127: 0 | AE127: =+AC127-AD127 -> 0 | AF127: 0 | AG127: =+AC127-AF127 -> 0 | AH127: 0 | AI127: =+AC127-AH127 -> 0 | AK127: 0 | AL127: 0 | AM127: =+AK127-AL127 -> 0 | AN127: 0 | AO127: =+AK127-AN127 -> 0 | AP127: 0 | AQ127: =+AK127-AP127 -> 0 | AS127: 0 | AT127: 0 | AU127: =+AS127-AT127 -> 0 | AV127: 0 | AW127: =+AS127-AV127 -> 0 | AX127: 0 | AY127: =+AS127-AX127 -> 0 | BA127: 0 | BB127: 0 | BC127: =+BA127-BB127 -> 0 | BD127: 0 | BE127: =+BA127-BD127 -> 0 | BF127: 0 | BG127: =+BA127-BF127 -> 0 | BI127: 0 | BJ127: 0 | BK127: =+BI127-BJ127 -> 0 | BL127: 0 | BM127: =+BI127-BL127 -> 0 | BN127: 0 | BO127: =+BI127-BN127 -> 0
B128: =IF(SUM(T128:T128)<>0,"Show","Hide") -> Hide | C128: 1 | D128: 3575 - Rego & On Road - Hire Fleet | E128: 116.15 | F128: 78.77 | G128: =+E128-F128 -> 37.38 | H128: 0 | I128: =+E128-H128 -> 116.15 | J128: 78.77 | K128: =+E128-J128 -> 37.38 | M128: 116.15 | N128: 78.77 | O128: =+M128-N128 -> 37.38 | P128: 0 | Q128: =+M128-P128 -> 116.15 | R128: 78.77 | S128: =+M128-R128 -> 37.38 | U128: 99.83 | V128: 61.21 | W128: =+U128-V128 -> 38.62 | X128: 0 | Y128: =+U128-X128 -> 99.83 | Z128: 61.21 | AA128: =+U128-Z128 -> 38.62 | AC128: 99.83 | AD128: 61.21 | AE128: =+AC128-AD128 -> 38.62 | AF128: 0 | AG128: =+AC128-AF128 -> 99.83 | AH128: 61.21 | AI128: =+AC128-AH128 -> 38.62 | AK128: 2.31 | AL128: 4.28 | AM128: =+AK128-AL128 -> -1.97 | AN128: 0 | AO128: =+AK128-AN128 -> 2.31 | AP128: 4.28 | AQ128: =+AK128-AP128 -> -1.97 | AS128: 2.31 | AT128: 4.28 | AU128: =+AS128-AT128 -> -1.97 | AV128: 0 | AW128: =+AS128-AV128 -> 2.31 | AX128: 4.28 | AY128: =+AS128-AX128 -> -1.97 | BA128: 14.01 | BB128: 13.28 | BC128: =+BA128-BB128 -> 0.73 | BD128: 0 | BE128: =+BA128-BD128 -> 14.01 | BF128: 13.28 | BG128: =+BA128-BF128 -> 0.73 | BI128: 14.01 | BJ128: 13.28 | BK128: =+BI128-BJ128 -> 0.73 | BL128: 0 | BM128: =+BI128-BL128 -> 14.01 | BN128: 13.28 | BO128: =+BI128-BN128 -> 0.73
